Workbook

Sheet Hoja1
A1: Padre_familia | B1: id_familia | C1: Familia | D1: origen | E1: Codigo | F1: descripcion | G1: nombre web | H1: descripcion corta | J1: unidad | K1: Saldo | L1: Precio Venta | M1: PCP | N1: Proveedor | O1: VARIABLE | P1: COLOR | Q1: METRAJE
A2: LIBRERÍA | B2: 355 | C2: LIBRERÍA | D2: P | E2: P355PAP13383-3 | F2: EST.CARTULINA METALICA 10 HJS 7 COL.23,8 X 31,9 | G2: =VLOOKUP(E2,Hoja2!A:E,2,FALSE) -> ESTUCHE CARTULINA METALICA 10 HOJAS 7 COLORES 23,8 X 31,9 CM | H2: =VLOOKUP(E2,Hoja2!A:C,3,FALSE) -> Estuche Cartulina Metálica 10 Hojas 7 Colores 23,8 X 31,9 cm -Producto Nacional | J2: C/U | K2: 1 | L2: 2320 | M2: 1165 | N2: LIBE
A3: LIBRERÍA | B3: 355 | C3: LIBRERÍA | D3: P | E3: P355ESC25372-3 | F3: FORRO PROARTE LIBRO TRANSPA.BOLSA 10un CAJA PDQ | G3: =VLOOKUP(E3,Hoja2!A:E,2,FALSE) -> FORRO PROARTE LIBRO TRANSPA.BOLSA 10un CAJA PDQ | H3: =VLOOKUP(E3,Hoja2!A:C,3,FALSE) -> Forro PROARTE College Trasparente Bolsa 10 unidad -Producto Nacional | J3: C/U | K3: 15 | L3: 2920 | M3: 1469 | N3: LIBE
A4: LIBRERÍA | B4: 355 | C4: LIBRERÍA | D4: P | E4: P355ESC25367-7 | F4: FORRO PROARTE UNIVER.COL.SURT.BOLS.10un CAJA PD | G4: =VLOOKUP(E4,Hoja2!A:E,2,FALSE) -> FORRO PROARTE UNIVER.COL.SURT.BOLS.10un CAJA PD | H4: =VLOOKUP(E4,Hoja2!A:C,3,FALSE) -> Forro Proarte Univer.Col.Surt.Bols.10Un Caja Pd \n-Producto Nacional | J4: C/U | K4: 20 | L4: 2700 | M4: 1360 | N4: LIBE
A5: ACCESORIOS | B5: 108 | C5: ACCESORIOS AUTOMOVILES | D5: P | E5: P108HKY6004 | F5: PULPO ARTESANAL 4 BRAZOS 0,6MT | G5: =VLOOKUP(E5,Hoja2!A:E,2,FALSE) -> #N/A | H5: =VLOOKUP(E5,Hoja2!A:C,3,FALSE) -> #N/A | J5: C/U | K5: 0 | L5: 6500 | M5: 3300 | N5: JMUÑ
A6: LIBRERÍA | B6: 355 | C6: LIBRERÍA | D6: P | E6: P355ESC13442-2 | F6: ROLLO FORRO AUTOADHESIVO 0,33 X 1,50 TRANSPARENTE | G6: =VLOOKUP(E6,Hoja2!A:E,2,FALSE) -> ROLLO FORRO AUTOADHESIVO 0,33 X 1,50 TRANSPARENTE | H6: =VLOOKUP(E6,Hoja2!A:C,3,FALSE) -> Rollo Forro Autoadhesivo 0,33 X 1,50 Transparente \n \n-Producto Nacional | J6: C/U | K6: 0 | L6: 1400 | M6: 705 | N6: LIBE
A7: LIBRERÍA | B7: 355 | C7: LIBRERÍA | D7: P | E7: P355ESC14329-4 | F7: ROLLO FORRO AUTOADHESIVO 0,45 X 1,50 TRANSPARENTE | G7: =VLOOKUP(E7,Hoja2!A:E,2,FALSE) -> ROLLO FORRO AUTOADHESIVO 0,45 X 1,50 TRANSPARENTE | H7: =VLOOKUP(E7,Hoja2!A:C,3,FALSE) -> Rollo Forro Autoadhesivo 0,45 X 1,50 Transparente \n \n-Producto Nacional | J7: C/U | K7: 0 | L7: 1940 | M7: 978 | N7: LIBE
A8: LIBRERÍA | B8: 355 | C8: LIBRERÍA | D8: P | E8: P355PIN13074-5 | F8: TEMPERA PROARTE 6 col FRASCO 15 CC | G8: =VLOOKUP(E8,Hoja2!A:E,2,FALSE) -> TEMPERA PROARTE 6 colores FRASCO 15 CC | H8: =VLOOKUP(E8,Hoja2!A:C,3,FALSE) -> Tempera PROARTE 6 colores Frasco 15 CC -Producto Nacional | J8: C/U | K8: 1 | L8: 1400 | M8: 705 | N8: LIBE
A9: LIBRERÍA | B9: 355 | C9: LIBRERÍA | D9: P | E9: P355PIN34024-3 | F9: TEMPERA PROARTE 12+2 UNIDADES 15 CC | G9: =VLOOKUP(E9,Hoja2!A:E,2,FALSE) -> TEMPERA PROARTE 12 colores +2 UNIDADES 15 CC | H9: =VLOOKUP(E9,Hoja2!A:C,3,FALSE) -> Tempera PROARTE 12 colores +2 Unidades15 CC -Producto Nacional | J9: C/U | K9: 0 | L9: 2160 | M9: 1087 | N9: LIBE
A10: HOGAR | B10: 353 | C10: DECORACIÓN | D10: P | E10: P353CEST601745 | F10: 3 UNDS CESTA DE YUTE LT-334A,3PCS | G10: =VLOOKUP(E10,Hoja2!A:E,2,FALSE) -> 3 Unds Cesta De Yute Lt-334A,3Pcs | H10: =VLOOKUP(E10,Hoja2!A:C,3,FALSE) -> set cesta de yute A- 25 x 18, B- 23 x 16, C- 20 x 14 cm 3 unidades | J10: C/U | K10: 0 | L10: 13780 | M10: 5790 | N10: JUYIN
A11: HOGAR | B11: 353 | C11: DECORACIÓN | D11: P | E11: P353CEST601746 | F11: 3 UNDS CESTA DE YUTE S022-27,3PCS | G11: =VLOOKUP(E11,Hoja2!A:E,2,FALSE) -> 3 Unds Cesta De Yute S022-27,3Pcs | H11: =VLOOKUP(E11,Hoja2!A:C,3,FALSE) -> set de 3 cesta tejida de yute decorativa y de organización en tres tamaños | J11: C/U | K11: 0 | L11: 17180 | M11: 7218 | N11: JUYIN
A12: HOGAR | B12: 353 | C12: DECORACIÓN | D12: P | E12: P353CEST600099 | F12: 3UNDS CESTA DE MADERA 5423C-3PCS | G12: =VLOOKUP(E12,Hoja2!A:E,2,FALSE) -> 3Unds Cesta De Madera 5423C-3Pcs | H12: =VLOOKUP(E12,Hoja2!A:C,3,FALSE) -> Caja de madera decorativa con terminaciones, 3 unidades distintas dimensiones A- 40 x 30 x 20 cm. B- 34 x 24 x 18 cm. y C- 28 x 18 x 17 cm. | J12: C/U | K12: 2 | L12: 49580 | M12: 20832 | N12: JUYIN
A13: HOGAR | B13: 353 | C13: DECORACIÓN | D13: P | E13: P353CEST600042 | F13: 3UNDS CESTA DE YUTE LT-327A,3 PCS | G13: =VLOOKUP(E13,Hoja2!A:E,2,FALSE) -> 3Unds Cesta De Yute Lt-327A,3 Pcs | H13: =VLOOKUP(E13,Hoja2!A:C,3,FALSE) -> set cesta de yute A- 32 x 8, B- 25 x 6, C- 20 x 4 cm 3 unidades | J13: C/U | K13: 1 | L13: 12780 | M13: 5370 | N13: JUYIN
... A17: ACCESORIOS | B17: 114 | C17: ACCESORIOS HOGAR - FERRETERIA (ASEO) | D17: P | E17: P114CO25190558 | F17: 9193 JARRA 1,4 lts GRANADA | G17: =VLOOKUP(E17,Hoja2!A:E,2,FALSE) -> 9193 Jarra 1,4 Lts Granada | H17: =VLOOKUP(E17,Hoja2!A:C,3,FALSE) -> Transforma tus momentos de compartir en experiencias excepcionales con la Jarra de Vidrio Allegra, una pieza de elegancia atemporal que combina estilo y funcionalidad de manera magistral. Desde reuniones familiares hasta encuentros con amigos, esta jarra se convierte en el complemento perfecto para servir tus bebidas con distinción. La Jarra de Vid | J17: C/U | K17: 0 | L17: 5690 | M17: 2634 | N17: INVER
A18: ABRAZADERAS | B18: 103 | C18: ABRAZADERA ALAMBRE GALVANIZADO | D18: P | E18: P103CAG001G | F18: ABRAZADERA ALAMBRE GALV ( 1) 1/8 1/4 | G18: =VLOOKUP(E18,Hoja2!A:E,2,FALSE) -> #N/A | H18: =VLOOKUP(E18,Hoja2!A:C,3,FALSE) -> #N/A | J18: C/U | K18: 0 | L18: 215 | M18: 74
A19: ABRAZADERAS | B19: 103 | C19: ABRAZADERA ALAMBRE GALVANIZADO | D19: P | E19: P103CAG002G | F19: ABRAZADERA ALAMBRE GALV ( 2) 1/4 3/8 | G19: =VLOOKUP(E19,Hoja2!A:E,2,FALSE) -> #N/A | H19: =VLOOKUP(E19,Hoja2!A:C,3,FALSE) -> #N/A | J19: C/U | K19: 0 | L19: 234 | M19: 80
A20: ABRAZADERAS | B20: 103 | C20: ABRAZADERA ALAMBRE GALVANIZADO | D20: P | E20: P103CAG003G | F20: ABRAZADERA ALAMBRE GALV ( 3) 3/8 1/2 | G20: =VLOOKUP(E20,Hoja2!A:E,2,FALSE) -> #N/A | H20: =VLOOKUP(E20,Hoja2!A:C,3,FALSE) -> #N/A | J20: C/U | K20: 0 | L20: 245 | M20: 85
A21: ABRAZADERAS | B21: 103 | C21: ABRAZADERA ALAMBRE GALVANIZADO | D21: P | E21: P103CAG004G | F21: ABRAZADERA ALAMBRE GALV ( 4) 1/2 5/8 | G21: =VLOOKUP(E21,Hoja2!A:E,2,FALSE) -> #N/A | H21: =VLOOKUP(E21,Hoja2!A:C,3,FALSE) -> #N/A | J21: C/U | K21: 0 | L21: 258 | M21: 89
A22: ABRAZADERAS | B22: 103 | C22: ABRAZADERA ALAMBRE GALVANIZADO | D22: P | E22: P103CAG005G | F22: ABRAZADERA ALAMBRE GALV ( 5) 5/8 3/4 | G22: =VLOOKUP(E22,Hoja2!A:E,2,FALSE) -> #N/A | H22: =VLOOKUP(E22,Hoja2!A:C,3,FALSE) -> #N/A | J22: C/U | K22: 0 | L22: 271 | M22: 93
A23: ABRAZADERAS | B23: 103 | C23: ABRAZADERA ALAMBRE GALVANIZADO | D23: P | E23: P103CAG006G | F23: ABRAZADERA ALAMBRE GALV ( 6) 7/8 1 | G23: =VLOOKUP(E23,Hoja2!A:E,2,FALSE) -> #N/A | H23: =VLOOKUP(E23,Hoja2!A:C,3,FALSE) -> #N/A | J23: C/U | K23: 0 | L23: 282 | M23: 97
A24: ABRAZADERAS | B24: 103 | C24: ABRAZADERA ALAMBRE GALVANIZADO | D24: P | E24: P103CAG007G | F24: ABRAZADERA ALAMBRE GALV ( 7) 1 1/8 1 1/4 | G24: =VLOOKUP(E24,Hoja2!A:E,2,FALSE) -> #N/A | H24: =VLOOKUP(E24,Hoja2!A:C,3,FALSE) -> #N/A | J24: C/U | K24: 0 | L24: 295 | M24: 101
A25: ABRAZADERAS | B25: 103 | C25: ABRAZADERA ALAMBRE GALVANIZADO | D25: P | E25: P103CAG008G | F25: ABRAZADERA ALAMBRE GALV ( 8) 1 3/8 1 1/2 | G25: =VLOOKUP(E25,Hoja2!A:E,2,FALSE) -> #N/A | H25: =VLOOKUP(E25,Hoja2!A:C,3,FALSE) -> #N/A | J25: C/U | K25: 0 | L25: 306 | M25: 106
A26: ABRAZADERAS | B26: 103 | C26: ABRAZADERA ALAMBRE GALVANIZADO | D26: P | E26: P103CAG009G | F26: ABRAZADERA ALAMBRE GALV ( 9) 1 5/8 1 3/4 | G26: =VLOOKUP(E26,Hoja2!A:E,2,FALSE) -> #N/A | H26: =VLOOKUP(E26,Hoja2!A:C,3,FALSE) -> #N/A | J26: C/U | K26: 0 | L26: 321 | M26: 111 | N26: PRIS
A27: ABRAZADERAS | B27: 103 | C27: ABRAZADERA ALAMBRE GALVANIZADO | D27: P | E27: P103CAG010G | F27: ABRAZADERA ALAMBRE GALV (10) 1 7/8 2 | G27: =VLOOKUP(E27,Hoja2!A:E,2,FALSE) -> #N/A | H27: =VLOOKUP(E27,Hoja2!A:C,3,FALSE) -> #N/A | J27: C/U | K27: 0 | L27: 339 | M27: 116
A28: ABRAZADERAS | B28: 102 | C28: ABRAZADERA ACERO INOXIDABLE ALTA PRESION | D28: P | E28: P102CAPZG | F28: ABRAZADERA ALTA PRESION 32-35mm | G28: =VLOOKUP(E28,Hoja2!A:E,2,FALSE) -> #N/A | H28: =VLOOKUP(E28,Hoja2!A:C,3,FALSE) -> #N/A | J28: C/U | K28: 0 | L28: 1823 | M28: 575
A29: ABRAZADERAS | B29: 102 | C29: ABRAZADERA ACERO INOXIDABLE ALTA PRESION | D29: P | E29: P102CAPAG | F29: ABRAZADERA ALTA PRESION 35-38mm | G29: =VLOOKUP(E29,Hoja2!A:E,2,FALSE) -> #N/A | H29: =VLOOKUP(E29,Hoja2!A:C,3,FALSE) -> #N/A | J29: C/U | K29: 0 | L29: 1829 | M29: 586
A30: ABRAZADERAS | B30: 102 | C30: ABRAZADERA ACERO INOXIDABLE ALTA PRESION | D30: P | E30: P102CAPBG | F30: ABRAZADERA ALTA PRESION 38-41mm | G30: =VLOOKUP(E30,Hoja2!A:E,2,FALSE) -> #N/A | H30: =VLOOKUP(E30,Hoja2!A:C,3,FALSE) -> #N/A | J30: C/U | K30: 0 | L30: 1836 | M30: 589
A31: ABRAZADERAS | B31: 102 | C31: ABRAZADERA ACERO INOXIDABLE ALTA PRESION | D31: P | E31: P102CAPCG | F31: ABRAZADERA ALTA PRESION 41-44mm | G31: =VLOOKUP(E31,Hoja2!A:E,2,FALSE) -> #N/A | H31: =VLOOKUP(E31,Hoja2!A:C,3,FALSE) -> #N/A | J31: C/U | K31: 0 | L31: 1845 | M31: 591
A32: ABRAZADERAS | B32: 102 | C32: ABRAZADERA ACERO INOXIDABLE ALTA PRESION | D32: P | E32: P102CAPMG | F32: ABRAZADERA ALTA PRESION 83-88mm | G32: =VLOOKUP(E32,Hoja2!A:E,2,FALSE) -> #N/A | H32: =VLOOKUP(E32,Hoja2!A:C,3,FALSE) -> #N/A | J32: C/U | K32: 0 | L32: 1964 | M32: 757
A33: ABRAZADERAS | B33: 104 | C33: ABRAZADERA BANDA ANGOSTA | D33: P | E33: P104CBA20G | F33: ABRAZADERA BANDA ANGOSTA (1) 7/8 - 1 1/8 | G33: =VLOOKUP(E33,Hoja2!A:E,2,FALSE) -> #N/A | H33: =VLOOKUP(E33,Hoja2!A:C,3,FALSE) -> #N/A | J33: C/U | K33: 0 | L33: 287 | M33: 96
A34: ABRAZADERAS | B34: 104 | C34: ABRAZADERA BANDA ANGOSTA | D34: P | E34: P104CBA1G | F34: ABRAZADERA BANDA ANGOSTA (3) 1 1/4 - 2 | G34: =VLOOKUP(E34,Hoja2!A:E,2,FALSE) -> #N/A | H34: =VLOOKUP(E34,Hoja2!A:C,3,FALSE) -> #N/A | J34: C/U | K34: 0 | L34: 333 | M34: 112
A35: ABRAZADERAS | B35: 105 | C35: ABRAZADERA CREMALLERA | D35: P | E35: P105ACMSAG | F35: ABRAZADERA CREMALLERA ( 1) 5/16 - 3/8 | G35: =VLOOKUP(E35,Hoja2!A:E,2,FALSE) -> #N/A | H35: =VLOOKUP(E35,Hoja2!A:C,3,FALSE) -> #N/A | J35: C/U | K35: 41 | L35: 224 | M35: 86
A36: ABRAZADERAS | B36: 105 | C36: ABRAZADERA CREMALLERA | D36: P | E36: P105ACFSG | F36: ABRAZADERA CREMALLERA ( 4) 5/8 - 7/8 | G36: =VLOOKUP(E36,Hoja2!A:E,2,FALSE) -> #N/A | H36: =VLOOKUP(E36,Hoja2!A:C,3,FALSE) -> #N/A | J36: C/U | K36: 0 | L36: 271 | M36: 92
A37: ABRAZADERAS | B37: 105 | C37: ABRAZADERA CREMALLERA | D37: P | E37: P105AC30G | F37: ABRAZADERA CREMALLERA ( 5) 3/4 - 7/8 (19-22 MM 3/0) | G37: =VLOOKUP(E37,Hoja2!A:E,2,FALSE) -> #N/A | H37: =VLOOKUP(E37,Hoja2!A:C,3,FALSE) -> #N/A | J37: C/U | K37: 77 | L37: 338 | M37: 130 | N37: PRIS
A38: ABRAZADERAS | B38: 105 | C38: ABRAZADERA CREMALLERA | D38: P | E38: P105AC20G | F38: ABRAZADERA CREMALLERA ( 6) 7/8 - 1 1/8 (22-28 MM 2/0) | G38: =VLOOKUP(E38,Hoja2!A:E,2,FALSE) -> #N/A | H38: =VLOOKUP(E38,Hoja2!A:C,3,FALSE) -> #N/A | J38: C/U | K38: 43 | L38: 352 | M38: 117 | N38: PRIS
A39: ABRAZADERAS | B39: 105 | C39: ABRAZADERA CREMALLERA | D39: P | E39: P105AC10G | F39: ABRAZADERA CREMALLERA ( 7) 1 - 1 1/4 (24-32 MM 1/0) | G39: =VLOOKUP(E39,Hoja2!A:E,2,FALSE) -> #N/A | H39: =VLOOKUP(E39,Hoja2!A:C,3,FALSE) -> #N/A | J39: C/U | K39: 82 | L39: 365 | M39: 141 | N39: PRIS
A40: ABRAZADERAS | B40: 105 | C40: ABRAZADERA CREMALLERA | D40: P | E40: P105ACOEG | F40: ABRAZADERA CREMALLERA ( 8) 1 1/4 - 1 3/4 (32-44 MM 0E) | G40: =VLOOKUP(E40,Hoja2!A:E,2,FALSE) -> #N/A | H40: =VLOOKUP(E40,Hoja2!A:C,3,FALSE) -> #N/A | J40: C/U | K40: 115 | L40: 375 | M40: 125 | N40: PRIS
A41: ABRAZADERAS | B41: 105 | C41: ABRAZADERA CREMALLERA | D41: P | E41: P105AC1G | F41: ABRAZADERA CREMALLERA ( 9) 1 1/4 - 2 (32-52 MM 1) | G41: =VLOOKUP(E41,Hoja2!A:E,2,FALSE) -> #N/A | H41: =VLOOKUP(E41,Hoja2!A:C,3,FALSE) -> #N/A | J41: C/U | K41: 32 | L41: 390 | M41: 150 | N41: PRIS
A42: ABRAZADERAS | B42: 105 | C42: ABRAZADERA CREMALLERA | D42: P | E42: P105AC1EG | F42: ABRAZADERA CREMALLERA (10) 1 5/8 - 2 1/4 (41-56 MM 1E) | G42: =VLOOKUP(E42,Hoja2!A:E,2,FALSE) -> #N/A | H42: =VLOOKUP(E42,Hoja2!A:C,3,FALSE) -> #N/A | J42: C/U | K42: 91 | L42: 409 | M42: 137 | N42: PRIS
A43: ABRAZADERAS | B43: 105 | C43: ABRAZADERA CREMALLERA | D43: P | E43: P105AC2G | F43: ABRAZADERA CREMALLERA (11) 2 - 2 1/2 (47-57 MM 2) | G43: =VLOOKUP(E43,Hoja2!A:E,2,FALSE) -> #N/A | H43: =VLOOKUP(E43,Hoja2!A:C,3,FALSE) -> #N/A | J43: C/U | K43: 97 | L43: 417 | M43: 139 | N43: PRIS
A44: ABRAZADERAS | B44: 105 | C44: ABRAZADERA CREMALLERA | D44: P | E44: P105AC3G | F44: ABRAZADERA CREMALLERA (12) 2 1/2 - 3 1/4 (62-82 MM 3) | G44: =VLOOKUP(E44,Hoja2!A:E,2,FALSE) -> #N/A | H44: =VLOOKUP(E44,Hoja2!A:C,3,FALSE) -> #N/A | J44: C/U | K44: 25 | L44: 437 | M44: 146 | N44: PRIS
A45: ABRAZADERAS | B45: 107 | C45: ABRAZADERA PLASTICA | D45: P | E45: P107APN13G | F45: ABRAZADERA PLASTICA NEGRO 13 cm | G45: =VLOOKUP(E45,Hoja2!A:E,2,FALSE) -> #N/A | H45: =VLOOKUP(E45,Hoja2!A:C,3,FALSE) -> #N/A | J45: C/U | K45: 0 | L45: 44 | M45: 17
A46: ABRAZADERAS | B46: 107 | C46: ABRAZADERA PLASTICA | D46: P | E46: P107APN36G | F46: ABRAZADERA PLASTICA NEGRO 36 cm | G46: =VLOOKUP(E46,Hoja2!A:E,2,FALSE) -> #N/A | H46: =VLOOKUP(E46,Hoja2!A:C,3,FALSE) -> #N/A | J46: C/U | K46: 0 | L46: 163 | M46: 63
A47: ABRAZADERAS | B47: 107 | C47: ABRAZADERA PLASTICA | D47: P | E47: P107APN368 | F47: ABRAZADERA PLASTICA NEGRO 36 GRUESA | G47: =VLOOKUP(E47,Hoja2!A:E,2,FALSE) -> #N/A | H47: =VLOOKUP(E47,Hoja2!A:C,3,FALSE) -> #N/A | J47: C/U | K47: 0 | L47: 211 | M47: 81
A48: ASEO | B48: 400 | C48: ABRILLANTADOR DE PISO | D48: P | E48: P4005LT5VIRGIN | F48: ABRILLANTADOR PISOS FLOTANTES LAVANDA VIRGINIA PRO 5LT | G48: =VLOOKUP(E48,Hoja2!A:E,2,FALSE) -> Abrillantador Pisos Flotantes Lavanda Virginia Pro 5 Lt | H48: =VLOOKUP(E48,Hoja2!A:C,3,FALSE) -> Virginia Pro Abrillantador de Pisos Flotantes y Laminados es un producto especialmente diseñado para brindar un brillo excepcional y una protección duradera a sus pisos, prolongando su vida útil. | J48: C/U | K48: 22 | L48: 16086 | M48: 11601.333 | N48: DEMA
A49: ASEO | B49: 400 | C49: ABRILLANTADOR DE PISO | D49: P | E49: P400900ML2VIRG | F49: ABRILLANTADOR PISOS FLOTANTES VIRGINIA FRUTOS ROJOS 900ML | G49: =VLOOKUP(E49,Hoja2!A:E,2,FALSE) -> Abrillantador Pisos Flotantes Virginia Frutos Rojos 900 Ml | H49: =VLOOKUP(E49,Hoja2!A:C,3,FALSE) -> Protege y renueva tus ambientes con el Abrillantador de Pisos Flotantes Virginia Frutos Rojos de 900 ml. Su fórmula auto-brillante resalta el aspecto natural de pisos flotantes y laminados sin necesidad de lustrar, atenuando rayas. Fácil de aplicar, se seca en solo 20 minutos dejando una agradable y duradera fragancia a frutos silvestres. | J49: C/U | K49: 40 | L49: 3492 | M49: 2537.8618 | N49: DEMA
A50: ASEO | B50: 400 | C50: ABRILLANTADOR DE PISO | D50: P | E50: P4001,8LT4VIRG | F50: ABRILLANTADOR PISOS FLOTANTES VIRGINIA LAVANDA 1,8LT | G50: =VLOOKUP(E50,Hoja2!A:E,2,FALSE) -> #N/A | H50: =VLOOKUP(E50,Hoja2!A:C,3,FALSE) -> #N/A | J50: C/U | K50: 2 | L50: 6844 | M50: 4115 | N50: DEMA
A51: LUBRICANTES | B51: 236 | C51: LUBRICANTES ACEITE PARA MOTORES A GASOLINA | D51: P | E51: P23648020056 | F51: ACEITE MOBIL SUPER S 10W-40 SINT 1 LT. | G51: =VLOOKUP(E51,Hoja2!A:E,2,FALSE) -> #N/A | H51: =VLOOKUP(E51,Hoja2!A:C,3,FALSE) -> #N/A | J51: C/U | K51: 0 | L51: 10293 | M51: 4217 | N51: SCCR
A52: LUBRICANTES | B52: 236 | C52: LUBRICANTES ACEITE PARA MOTORES A GASOLINA | D52: P | E52: P2364802034K | F52: ACEITE MOBIL SUPER S 10W-40 SINT 4 LTS | G52: =VLOOKUP(E52,Hoja2!A:E,2,FALSE) -> #N/A | H52: =VLOOKUP(E52,Hoja2!A:C,3,FALSE) -> #N/A | J52: C/U | K52: 0 | L52: 34989 | M52: 11565 | N52: SCCR
A53: ACCESORIOS | B53: 114 | C53: ACCESORIOS HOGAR - FERRETERIA (ASEO) | D53: P | E53: P114JARDGL325 | F53: ACOPLE RAPIDO PARA MANGUERA 1/2"" | G53: =VLOOKUP(E53,Hoja2!A:E,2,FALSE) -> Acople Rapido Para Manguera 1/2"" | H53: =VLOOKUP(E53,Hoja2!A:C,3,FALSE) -> Este acople rápido para manguera 1/2 es un indispensable accesorio que te permitirá conectar y desconectar de forma rápida y segura tus mangueras de riego. Fabricado con materiales de alta calidad, garantiza una resistencia excepcional y una durabilidad prolongada que resistirá incluso las condiciones más exigentes. Con solo un clic, podrás acopl | J53: C/U | K53: 8 | L53: 893 | M53: 434 | N53: IMPRO
A54: ACCESORIOS | B54: 114 | C54: ACCESORIOS HOGAR - FERRETERIA (ASEO) | D54: P | E54: P114JARDGL327 | F54: ACOPLE RAPIDO PARA MANGUERA 3/4"" | G54: =VLOOKUP(E54,Hoja2!A:E,2,FALSE) -> Acople Rapido Para Manguera 3/4"" | H54: =VLOOKUP(E54,Hoja2!A:C,3,FALSE) -> Cruzeiro Gomas y el material del producto es caucho; Meta detalles: palabras clave = ACOPLE RAPIDO, MANGUERA, 3/4 RUBBER, CRUZEIRO GOMAS. ¡Prepárate para el verano con el resistente Acople Rápido para Manguera 3/4 de Cruzeiro Gomas! Nuestro Acople Rápido para Manguera 3/4 es la solución perfecta para tus necesidades de riego. Fabricado con cauch | J54: C/U | K54: 12 | L54: 992 | M54: 485 | N54: IMPRO
A55: ADHESIVOS | B55: 116 | C55: ADHESIVOS | D55: P | E55: P116VIPAFIX | F55: ADHESIVO (0,600 KG) + CATALIZADOR - PACK | G55: =VLOOKUP(E55,Hoja2!A:E,2,FALSE) -> Adhesivo (0,600 Kg) + Catalizador - Pack | H55: =VLOOKUP(E55,Hoja2!A:C,3,FALSE) -> Adhesivo de contacto sobre la base de policloropreno de rápida cristalización, aditivado de óxidos metalicos, agentes protectores, resinas de pegajosidad y disolventes.Líquido viscoso, de color crema. El Cemento Vipafix E forma retículas con resinas, óxidos y policloropreno, resultando en la adhesión y unión con antioxidantes que ofrecen protección | J55: C/U | K55: 81 | L55: 36124 | M55: 18214 | N55: VIPAL
A56: ADHESIVOS | B56: 118 | C56: ADHESIVOS GOBUSA | D56: P | E56: P118HG0003 | F56: ADHESIVO GOBUSA (1) 1/16 GALÓN 236ML | G56: =VLOOKUP(E56,Hoja2!A:E,2,FALSE) -> Adhesivo Contacto Gobusa 236 ml | H56: =VLOOKUP(E56,Hoja2!A:C,3,FALSE) -> Adhesivo de contacto de alta resistencia, ideal para uniones permanentes en múltiples materiales con excelente adherencia y flexibilidad | J56: C/U | K56: 9 | L56: 3035 | M56: 1268 | N56: HGON
A57: ADHESIVOS | B57: 118 | C57: ADHESIVOS GOBUSA | D57: P | E57: P118HG0005 | F57: ADHESIVO GOBUSA (2) 3/4 LT (0,75 LT) | G57: =VLOOKUP(E57,Hoja2!A:E,2,FALSE) -> Adhesivo Contacto Gobusa 750 ml | H57: =VLOOKUP(E57,Hoja2!A:C,3,FALSE) -> ADHESIVO GOBUSA (2) 3/4 LT (0,75 LT) Características: Adhesivo de Contacto Multiuso Color Café de Gran Resistencia. Pega: cuero, goma, madera, espuma, telas, metales, alfombras ,formalita, plásticos, etc. Rendimiento: 4 a 5m2 por litro aprox. Recomendación: Usar en lugares ventilados, el uso adecuado de este producto no perjudica al | J57: C/U | K57: 13 | L57: 7788 | M57: 3314.9998 | N57: HGON
A58: ADHESIVOS | B58: 118 | C58: ADHESIVOS GOBUSA | D58: P | E58: P118HG0002 | F58: ADHESIVO GOBUSA (3) 1 LT. | G58: =VLOOKUP(E58,Hoja2!A:E,2,FALSE) -> Adhesivo Contacto Gobusa 1 Litro | H58: =VLOOKUP(E58,Hoja2!A:C,3,FALSE) -> Adhesivo de contacto de alta resistencia, ideal para uniones permanentes en múltiples materiales con excelente adherencia y flexibilidad | J58: C/U | K58: 4 | L58: 9084 | M58: 4030 | N58: HGON
A59: ADHESIVOS | B59: 118 | C59: ADHESIVOS GOBUSA | D59: U | E59: UB118HG0001 | F59: ADHESIVO GOBUSA (4) 1 GL (3,79 LT) | G59: =VLOOKUP(E59,Hoja2!A:E,2,FALSE) -> #N/A | H59: =VLOOKUP(E59,Hoja2!A:C,3,FALSE) -> #N/A | J59: C/U | K59: 0 | L59: 16427 | M59: 17255
A60: ADHESIVOS | B60: 118 | C60: ADHESIVOS GOBUSA | D60: P | E60: P118HG0001 | F60: ADHESIVO GOBUSA (4) 1 GL (3,79 LT) | G60: =VLOOKUP(E60,Hoja2!A:E,2,FALSE) -> Adhesivo Contacto Gobusa 1 Galón 3.79 L | H60: =VLOOKUP(E60,Hoja2!A:C,3,FALSE) -> Adhesivo de contacto de alta resistencia, ideal para uniones permanentes en múltiples materiales con excelente adherencia y flexibilidad | J60: C/U | K60: 19 | L60: 29334 | M60: 13195 | N60: HGON
A61: ADHESIVOS | B61: 118 | C61: ADHESIVOS GOBUSA | D61: P | E61: P118HG0004 | F61: ADHESIVO GOBUSA (5) 1 LATA 18 LTS | G61: =VLOOKUP(E61,Hoja2!A:E,2,FALSE) -> Adhesivo Contacto Gobusa 18 Litros | H61: =VLOOKUP(E61,Hoja2!A:C,3,FALSE) -> Adhesivo de contacto de alta resistencia, ideal para uniones permanentes en múltiples materiales con excelente adherencia y flexibilidad | J61: C/U | K61: 11 | L61: 136209 | M61: 60450 | N61: HGON
A62: ADHESIVOS | B62: 117 | C62: ADHESIVOS AGOREX | D62: P | E62: P117HD0006 | F62: ADHESIVO HENKEL AGOREX (284638) TRANSP POMO 120 CC. | G62: =VLOOKUP(E62,Hoja2!A:E,2,FALSE) -> Adhesivo Henkel Agorex 120cc Transparente | H62: =VLOOKUP(E62,Hoja2!A:C,3,FALSE) -> Adhesivo transparente de alta calidad Henkel, ideal para reparaciones precisas y uniones permanentes con acabado invisible y máxima resistencia | J62: C/U | K62: 0 | L62: 6514 | M62: 4048.4 | N62: FERRO
A63: ADHESIVOS | B63: 117 | C63: ADHESIVOS AGOREX | D63: P | E63: P117HD0004 | F63: ADHESIVO HENKEL AGOREX (284639) TRANSP POMO 120 CC. | G63: =VLOOKUP(E63,Hoja2!A:E,2,FALSE) -> Adhesivo Henkel Agorex 120cc Transparente | H63: =VLOOKUP(E63,Hoja2!A:C,3,FALSE) -> Adhesivo transparente de alta calidad Henkel, ideal para reparaciones precisas y uniones permanentes con acabado invisible y máxima resistencia | J63: C/U | K63: 0 | L63: 6252 | M63: 3463 | N63: FERRO
A64: ADHESIVOS | B64: 117 | C64: ADHESIVOS AGOREX | D64: P | E64: P117HD0001 | F64: ADHESIVO HENKEL AGOREX-60 (0) POMO 20 CC. (284628) | G64: =VLOOKUP(E64,Hoja2!A:E,2,FALSE) -> Adhesivo Henkel Agorex 60-20cc | H64: =VLOOKUP(E64,Hoja2!A:C,3,FALSE) -> Adhesivo de alta calidad Henkel, ideal para reparaciones precisas y uniones permanentes con aplicación controlada y máxima resistencia | J64: C/U | K64: 0 | L64: 2918 | M64: 1594 | N64: LPHI
A65: ADHESIVOS | B65: 117 | C65: ADHESIVOS AGOREX | D65: P | E65: P117HD0008 | F65: ADHESIVO HENKEL AGOREX-60 (284616) 1 LT. | G65: =VLOOKUP(E65,Hoja2!A:E,2,FALSE) -> Adhesivo Henkel Agorex 60 1 Litro | H65: =VLOOKUP(E65,Hoja2!A:C,3,FALSE) -> Adhesivo de alta calidad Henkel, ideal para aplicaciones industriales y uniones permanentes con curado rápido y máxima resistencia | J65: C/U | K65: 8 | L65: 16464 | M65: 9173 | N65: FERRO
A66: ADHESIVOS | B66: 117 | C66: ADHESIVOS AGOREX | D66: P | E66: P117HD0010 | F66: ADHESIVO HENKEL AGOREX-60 (284617) GL (3,79 LT) | G66: =VLOOKUP(E66,Hoja2!A:E,2,FALSE) -> Adhesivo Henkel Agorex 60 1 Galón 3.79L | H66: =VLOOKUP(E66,Hoja2!A:C,3,FALSE) -> Adhesivo de alta calidad Henkel, ideal para aplicaciones industriales y uniones permanentes con curado rápido y máxima resistencia | J66: C/U | K66: 0 | L66: 48790 | M66: 28631 | N66: LPHI
A67: ADHESIVOS | B67: 117 | C67: ADHESIVOS AGOREX | D67: P | E67: P117HD0005 | F67: ADHESIVO HENKEL AGOREX-60 (284633) POMO 120 CC | G67: =VLOOKUP(E67,Hoja2!A:E,2,FALSE) -> Adhesivo Henkel Agorex 60 120cc | H67: =VLOOKUP(E67,Hoja2!A:C,3,FALSE) -> Adhesivo de alta calidad Henkel, ideal para reparaciones precisas y uniones permanentes con curado rápido y máxima resistencia | J67: C/U | K67: 0 | L67: 5471 | M67: 3037.6552 | N67: FERRO
A68: ADHESIVOS | B68: 117 | C68: ADHESIVOS AGOREX | D68: P | E68: P117HD18LT | F68: ADHESIVO HENKEL AGOREX-60 (5) LATA 18 LTS | G68: =VLOOKUP(E68,Hoja2!A:E,2,FALSE) -> #N/A | H68: =VLOOKUP(E68,Hoja2!A:C,3,FALSE) -> #N/A | J68: C/U | K68: 2 | L68: 194776 | M68: 134395 | N68: LPHI
A69: ADHESIVOS | B69: 117 | C69: ADHESIVOS AGOREX | D69: P | E69: P117HD0002 | F69: ADHESIVO HENKEL AGOREX-60 POMO 120 CC (284634) | G69: =VLOOKUP(E69,Hoja2!A:E,2,FALSE) -> Adhesivo Henkel Agorex 60 120cc | H69: =VLOOKUP(E69,Hoja2!A:C,3,FALSE) -> Adhesivo de alta calidad Henkel, ideal para reparaciones precisas y uniones permanentes con curado rápido y máxima resistencia | J69: C/U | K69: 0 | L69: 5211 | M69: 2846 | N69: FED
A70: ADHESIVOS | B70: 120 | C70: ADHESIVOS LOCTITE | D70: P | E70: P120HD0011 | F70: ADHESIVO HENKEL LOCTITE SUPER BONDER(2818298) ULTRA 20GR | G70: =VLOOKUP(E70,Hoja2!A:E,2,FALSE) -> Adhesivo Henkel Loctite Super Bonder Ultra 20gr | H70: =VLOOKUP(E70,Hoja2!A:C,3,FALSE) -> Adhesivo instantáneo de máxima resistencia Henkel Loctite, ideal para uniones rápidas y permanentes con tecnología Ultra de alto rendimiento | J70: C/U | K70: 0 | L70: 3636 | M70: 1991 | N70: FERRO
A71: HAWAIANAS | B71: 231 | C71: HAWAIANAS | D71: P | E71: P231MERRYC2097 | F71: Adorno Mery Christmas 15 x 35 Cm | G71: =VLOOKUP(E71,Hoja2!A:E,2,FALSE) -> Adorno Mery Christmas 15 X 35 Cm | H71: =VLOOKUP(E71,Hoja2!A:C,3,FALSE) -> Adorno Mery Christmas 15 x 35 Cm Material : Madera | J71: C/U | K71: 2 | L71: 6240 | M71: 3403 | N71: IMPOR
... A121: AJUSTES | B121: 128 | C121: AJUSTES MALETA | D121: P | E121: P128PV10C | F121: AJUSTE MALETA UNIV M-13 PV10 CNA | G121: =VLOOKUP(E121,Hoja2!A:E,2,FALSE) -> #N/A | H121: =VLOOKUP(E121,Hoja2!A:C,3,FALSE) -> #N/A | J121: MT | K121: 0 | L121: 2138 | M121: 1592 | N121: THM
A122: AJUSTES | B122: 128 | C122: AJUSTES MALETA | D122: U | E122: UB128PV10C | F122: AJUSTE MALETA UNIV M-13 PV10 CNA | G122: =VLOOKUP(E122,Hoja2!A:E,2,FALSE) -> #N/A | H122: =VLOOKUP(E122,Hoja2!A:C,3,FALSE) -> #N/A | J122: MT | K122: 0 | L122: 601 | M122: 631
A123: AJUSTES | B123: 125 | C123: AJUSTES ANTIRRUIDO | D123: F | E123: F125103378 | F123: AJUSTE MERCEDES BENZ 1113/14 ANTIRRUIDO TAPABARRO | G123: =VLOOKUP(E123,Hoja2!A:E,2,FALSE) -> #N/A | H123: =VLOOKUP(E123,Hoja2!A:C,3,FALSE) -> #N/A | J123: Mt | K123: 0 | L123: 5453.026 | M123: 1457 | N123: LPHI
A124: AJUSTES | B124: 125 | C124: AJUSTES ANTIRRUIDO | D124: F | E124: F125103376 | F124: AJUSTE MERCEDES BENZ ANTIRRUIDO TAPABARRO | G124: =VLOOKUP(E124,Hoja2!A:E,2,FALSE) -> #N/A | H124: =VLOOKUP(E124,Hoja2!A:C,3,FALSE) -> #N/A | J124: Mt | K124: 0 | L124: 4185.2505 | M124: 391 | N124: LPHI
A125: AJUSTES | B125: 124 | C125: AJUSTES | D125: P | E125: P124103079 | F125: AJUSTE MOTONETA PISO,CAUCHO SBR, DUREZA 70 SH | G125: =VLOOKUP(E125,Hoja2!A:E,2,FALSE) -> #N/A | H125: =VLOOKUP(E125,Hoja2!A:C,3,FALSE) -> #N/A | J125: MT | K125: 0 | L125: 4254 | M125: 1690 | N125: MCP
A126: AJUSTES | B126: 124 | C126: AJUSTES | D126: F | E126: F124103336 | F126: AJUSTE NERVIO P/CORREDERA No.1 CHICO | G126: =VLOOKUP(E126,Hoja2!A:E,2,FALSE) -> #N/A | H126: =VLOOKUP(E126,Hoja2!A:C,3,FALSE) -> #N/A | J126: Mt | K126: 162 | L126: 1360.0738 | M126: 445.84584 | N126: LPHI
A127: AJUSTES | B127: 124 | C127: AJUSTES | D127: F | E127: F124103335 | F127: AJUSTE NERVIO P/CORREDERA No.2 CHICO | G127: =VLOOKUP(E127,Hoja2!A:E,2,FALSE) -> #N/A | H127: =VLOOKUP(E127,Hoja2!A:C,3,FALSE) -> #N/A | J127: Mt | K127: 207 | L127: 1353.7084 | M127: 446 | N127: LPHI
A128: AJUSTES | B128: 124 | C128: AJUSTES | D128: F | E128: F124103337 | F128: AJUSTE NERVIO P/CORREDERA No.3 MEDIANO | G128: =VLOOKUP(E128,Hoja2!A:E,2,FALSE) -> #N/A | H128: =VLOOKUP(E128,Hoja2!A:C,3,FALSE) -> #N/A | J128: Mt | K128: 75 | L128: 3006.5906 | M128: 896 | N128: LPHI
A129: AJUSTES | B129: 124 | C129: AJUSTES | D129: F | E129: F124103338 | F129: AJUSTE NERVIO P/CORREDERA No.4 GRANDE | G129: =VLOOKUP(E129,Hoja2!A:E,2,FALSE) -> Ajuste Nervio P/Corredera No.4 Grande | H129: =VLOOKUP(E129,Hoja2!A:C,3,FALSE) -> Ajuste Nervio P/Corredera No.4 Grande - Venta X Metro-Fabricado Por Cruzeiro Gomas | J129: Mt | K129: 0 | L129: 1283.689 | M129: 236.41667 | N129: LPHI
A130: AJUSTES | B130: 124 | C130: AJUSTES | D130: F | E130: F124103502 | F130: AJUSTE P.EMBARCACION No.1 PANGA TIRA MAX 5.5 MTS | G130: =VLOOKUP(E130,Hoja2!A:E,2,FALSE) -> #N/A | H130: =VLOOKUP(E130,Hoja2!A:C,3,FALSE) -> #N/A | J130: MT | K130: 0 | L130: 81625.646 | M130: 15388 | N130: LPHI
A131: AJUSTES | B131: 124 | C131: AJUSTES | D131: F | E131: F124103503 | F131: AJUSTE P.EMBARCACION No.2 TIRA MAX 5.5 MTS | G131: =VLOOKUP(E131,Hoja2!A:E,2,FALSE) -> #N/A | H131: =VLOOKUP(E131,Hoja2!A:C,3,FALSE) -> #N/A | J131: C/U | K131: 0 | L131: 39306.345 | M131: 7410 | N131: LPHI
A132: AJUSTES | B132: 124 | C132: AJUSTES | D132: F | E132: F124103120 | F132: AJUSTE P.EMBARCACION No.5 CHILOE TIRA MAX 5.5 | G132: =VLOOKUP(E132,Hoja2!A:E,2,FALSE) -> #N/A | H132: =VLOOKUP(E132,Hoja2!A:C,3,FALSE) -> #N/A | J132: Mt | K132: 0 | L132: 27238.607 | M132: 5726 | N132: LPHI
A133: TRABAJOS ESPECIALES | B133: 331 | C133: TRABAJOS ESPECIALES TRAFILADO | D133: P | E133: P3310004859 | F133: AJUSTE PARA PUERTA, CON ALETAS, DUREZA 70 SH, SBR | G133: =VLOOKUP(E133,Hoja2!A:E,2,FALSE) -> #N/A | H133: =VLOOKUP(E133,Hoja2!A:C,3,FALSE) -> #N/A | J133: MT | K133: 0 | L133: 19450 | M133: 9700 | N133: MCP
A134: AJUSTES | B134: 124 | C134: AJUSTES | D134: F | E134: F124103051 | F134: AJUSTE PEUGEOT 404 CAPOT | G134: =VLOOKUP(E134,Hoja2!A:E,2,FALSE) -> #N/A | H134: =VLOOKUP(E134,Hoja2!A:C,3,FALSE) -> #N/A | J134: Mt | K134: 247.8 | L134: 5830.7064 | M134: 1838.789 | N134: LPHI
A135: AJUSTES | B135: 124 | C135: AJUSTES | D135: U | E135: UB124103051 | F135: AJUSTE PEUGEOT 404 CAPOT | G135: =VLOOKUP(E135,Hoja2!A:E,2,FALSE) -> #N/A | H135: =VLOOKUP(E135,Hoja2!A:C,3,FALSE) -> #N/A | J135: Mt | K135: 0 | L135: 1521 | M135: 1597
A136: AJUSTES | B136: 129 | C136: AJUSTES PUERTA | D136: F | E136: F129103209 | F136: AJUSTE PEUGEOT 404 TAPIZ PUERTA | G136: =VLOOKUP(E136,Hoja2!A:E,2,FALSE) -> #N/A | H136: =VLOOKUP(E136,Hoja2!A:C,3,FALSE) -> #N/A | J136: Mt | K136: 0 | L136: 2152.5661 | M136: 429 | N136: LPHI
A137: AJUSTES | B137: 126 | C137: AJUSTES BOTA AGUA | D137: F | E137: F126103236 | F137: AJUSTE PEUGEOT 404 VIDRIO LATERAL BOTA AGUA | G137: =VLOOKUP(E137,Hoja2!A:E,2,FALSE) -> #N/A | H137: =VLOOKUP(E137,Hoja2!A:C,3,FALSE) -> #N/A | J137: Mt | K137: 0 | L137: 1106.5187 | M137: 183 | N137: LPHI
A138: AJUSTES | B138: 124 | C138: AJUSTES | D138: F | E138: F124103519 | F138: AJUSTE PROT. BARANDA PICK UP KIA/HYUNDAI TIRA 8,1 MTS | G138: =VLOOKUP(E138,Hoja2!A:E,2,FALSE) -> #N/A | H138: =VLOOKUP(E138,Hoja2!A:C,3,FALSE) -> #N/A | J138: MT | K138: 48.6 | L138: 73671.018 | M138: 13097 | N138: LPHI
A139: AJUSTES | B139: 129 | C139: AJUSTES PUERTA | D139: P | E139: P129PV12C | F139: AJUSTE PUERTA "PL" UNIV P-30 PV12 CNA | G139: =VLOOKUP(E139,Hoja2!A:E,2,FALSE) -> #N/A | H139: =VLOOKUP(E139,Hoja2!A:C,3,FALSE) -> #N/A | J139: MT | K139: 0 | L139: 2848.86 | M139: 1257 | N139: THM
A140: AJUSTES | B140: 132 | C140: AJUSTES- LAMAS PUERTA FRIGORIFICO | D140: P | E140: P132103242 | F140: AJUSTE PUERTA FRIGORIFICO , ACRILO, DUREZA 70 SH | G140: =VLOOKUP(E140,Hoja2!A:E,2,FALSE) -> #N/A | H140: =VLOOKUP(E140,Hoja2!A:C,3,FALSE) -> #N/A | J140: MT | K140: 0 | L140: 10911 | M140: 5960 | N140: MCP
A141: TRABAJOS ESPECIALES | B141: 331 | C141: TRABAJOS ESPECIALES TRAFILADO | D141: X | E141: X331003442 | F141: AJUSTE PUERTA FRIGORIFICO 41MM ALTURA, 14MM ANCHO, 3,5MMS DE ESPESOR | G141: =VLOOKUP(E141,Hoja2!A:E,2,FALSE) -> #N/A | H141: =VLOOKUP(E141,Hoja2!A:C,3,FALSE) -> #N/A | J141: mt. | K141: 0 | L141: 16645.72 | M141: 5325 | N141: LPHI
A142: AJUSTES | B142: 132 | C142: AJUSTES- LAMAS PUERTA FRIGORIFICO | D142: F | E142: F132103225 | F142: AJUSTE PUERTA FRIGORIFICO No. 1 TIRAS 2,70 MTS | G142: =VLOOKUP(E142,Hoja2!A:E,2,FALSE) -> #N/A | H142: =VLOOKUP(E142,Hoja2!A:C,3,FALSE) -> #N/A | J142: Mt | K142: 0 | L142: 6997.6964 | M142: 1834 | N142: LPHI
A143: AJUSTES | B143: 132 | C143: AJUSTES- LAMAS PUERTA FRIGORIFICO | D143: F | E143: F132103242 | F143: AJUSTE PUERTA FRIGORIFICO No. 2 TIRAS 2,70 MTS | G143: =VLOOKUP(E143,Hoja2!A:E,2,FALSE) -> #N/A | H143: =VLOOKUP(E143,Hoja2!A:C,3,FALSE) -> #N/A | J143: MT | K143: 62 | L143: 21658.273 | M143: 7206 | N143: LPHI
A144: AJUSTES | B144: 132 | C144: AJUSTES- LAMAS PUERTA FRIGORIFICO | D144: F | E144: F132103309 | F144: AJUSTE PUERTA FRIGORIFICO No. 6 TIRAS 2,70 MTS | G144: =VLOOKUP(E144,Hoja2!A:E,2,FALSE) -> #N/A | H144: =VLOOKUP(E144,Hoja2!A:C,3,FALSE) -> #N/A | J144: Mt | K144: 0 | L144: 3758.7687 | M144: 571 | N144: LPHI
A145: AJUSTES | B145: 132 | C145: AJUSTES- LAMAS PUERTA FRIGORIFICO | D145: F | E145: F132103327 | F145: AJUSTE PUERTA FRIGORIFICO No. 7 TIRAS 2,70 MTS | G145: =VLOOKUP(E145,Hoja2!A:E,2,FALSE) -> #N/A | H145: =VLOOKUP(E145,Hoja2!A:C,3,FALSE) -> #N/A | J145: Mt | K145: 0 | L145: 4012.3238 | M145: 658 | N145: LPHI
A146: AJUSTES | B146: 132 | C146: AJUSTES- LAMAS PUERTA FRIGORIFICO | D146: F | E146: F132103429 | F146: AJUSTE PUERTA FRIGORIFICO No. 8 TIRAS 2,70 MTS | G146: =VLOOKUP(E146,Hoja2!A:E,2,FALSE) -> #N/A | H146: =VLOOKUP(E146,Hoja2!A:C,3,FALSE) -> #N/A | J146: Mt | K146: 0 | L146: 5044.5795 | M146: 1189 | N146: LPHI
A147: AJUSTES | B147: 132 | C147: AJUSTES- LAMAS PUERTA FRIGORIFICO | D147: F | E147: F132103450 | F147: AJUSTE PUERTA FRIGORIFICO No.10 | G147: =VLOOKUP(E147,Hoja2!A:E,2,FALSE) -> #N/A | H147: =VLOOKUP(E147,Hoja2!A:C,3,FALSE) -> #N/A | J147: Mt | K147: 125 | L147: 5375.5803 | M147: 1559.3921 | N147: LPHI
... A153: AJUSTES | B153: 129 | C153: AJUSTES PUERTA | D153: I | E153: I129PV12C | F153: AJUSTE PUERTA UNIV P-30 PV12 CNA | G153: =VLOOKUP(E153,Hoja2!A:E,2,FALSE) -> #N/A | H153: =VLOOKUP(E153,Hoja2!A:C,3,FALSE) -> #N/A | J153: MT | K153: 8087 | L153: 2352 | M153: 661.01217 | N153: XING
A154: AJUSTES | B154: 129 | C154: AJUSTES PUERTA | D154: U | E154: UB129PV12C | F154: AJUSTE PUERTA UNIV P-30 PV12 CNA | G154: =VLOOKUP(E154,Hoja2!A:E,2,FALSE) -> #N/A | H154: =VLOOKUP(E154,Hoja2!A:C,3,FALSE) -> #N/A | J154: MT | K154: 0 | L154: 601 | M154: 631
A155: AJUSTES | B155: 129 | C155: AJUSTES PUERTA | D155: I | E155: I129PV08C | F155: AJUSTE PUERTA UNIV P-40 PV08 CNA | G155: =VLOOKUP(E155,Hoja2!A:E,2,FALSE) -> #N/A | H155: =VLOOKUP(E155,Hoja2!A:C,3,FALSE) -> #N/A | J155: MT | K155: 5475 | L155: 3097.5 | M155: 727.61837 | N155: XING
A156: AJUSTES | B156: 129 | C156: AJUSTES PUERTA | D156: I | E156: I129PV07C | F156: AJUSTE PUERTA UNIV P-60 PV07 CNA | G156: =VLOOKUP(E156,Hoja2!A:E,2,FALSE) -> #N/A | H156: =VLOOKUP(E156,Hoja2!A:C,3,FALSE) -> #N/A | J156: MT | K156: 741 | L156: 3076.5 | M156: 835.2311 | N156: XING
A157: AJUSTES | B157: 129 | C157: AJUSTES PUERTA | D157: I | E157: I129PV18C | F157: AJUSTE PUERTA UNIV PEUGEOT OPEL PV18 CNA | G157: =VLOOKUP(E157,Hoja2!A:E,2,FALSE) -> #N/A | H157: =VLOOKUP(E157,Hoja2!A:C,3,FALSE) -> #N/A | J157: MT | K157: 253 | L157: 2583 | M157: 712.00086 | N157: XING
...

Sheet Hoja3
A1: PISOS GOMA EN ROLLO SIN TELA | B1: Por tipo de tráfico | C1: Diseño | D1: Uso Comercial e Industrial | E1: Uso Deportivo y Recreacional | F1: Uso Transporte y Logística | G1: Uso Residencial y Áreas Comunes
B2: Tránsito Ligero o Peatonal Espacios: Casas, oficinas pequeñas, logias, maleteros de autos particulares y salas de juego infantiles. Carga: Solo el caminar de personas, mascotas o muebles livianos. Espesor recomendado: 2 mm a 3 mm. Es flexible, fácil de cortar con cartonero y liviano para instalar. | C2: Diseño Estoperol (Monedas o Botones) Características: Superficie con círculos en relieve que ofrecen un excelente agarre multidireccional.Usos ideales: Pasillos comerciales, transporte público (buses y trenes), rampas de acceso y zonas de alto tráfico peatonal.Ventaja: Es el diseño antideslizante por excelencia y estéticamente el más moderno. | D2: Talleres mecánicos: Soportan el derrame de aceites, grasas y fluidos automotrices sin absorberlos. | E2: Gimnasios y zonas de pesas: Absorben los impactos de las mancuernas y protegen la estructura del suelo. | F2: Pisos de buses y furgones: Recubren el suelo de vehículos de pasajeros para evitar resbalones los días de lluvia. | G2: Garajes domésticos: Permiten estacionar el auto protegiendo el radier de manchas de aceite difíciles de sacar.
B3: Tránsito Moderado o Comercial Espacios: Pasillos comerciales, gimnasios de entrenamiento funcional, furgones de reparto y garajes domésticos. Espesor recomendado: 3 mm a 5 mm. Ofrece un buen equilibrio entre amortiguación de impactos y resistencia al desgaste diario. Carga: Tránsito continuo de personas, carros de mano livianos, uso de mancuernas medianas y estacionamiento de vehículos comerciales. | C3: Diseño Acanalado (Estriado o Americano) Características: Líneas paralelas en relieve que corren a lo largo del rollo.Usos ideales: Cajas de camiones, pick-ups de camionetas, pasillos angostos y zonas de entrada.Ventaja: Facilita el escurrimiento de líquidos y permite canalizar la suciedad o el agua hacia los extremos. | D3: Fábricas y líneas de producción: Aíslan el frío del suelo y amortiguan la vibración de las maquinarias. | E3: Centros de crossfit: Ofrecen una superficie antideslizante para evitar caídas durante entrenamientos intensos. | F3: Maleteros y pick-ups: Protegen la lata de camionetas y autos del roce de la carga. | G3: Logias y lavaderos: Al ser impermeables, resisten la humedad constante y las salpicaduras de detergente.
B4: Tránsito Pesado o Industrial Espacios: Zonas de crossfit con caída libre de barras, talleres mecánicos pesados, cajas de camiones de carga y fábricas.Carga: Maquinaria pesada, arrastre de pallets, caída de herramientas pesadas y vehículos de gran tonelaje.Espesor recomendado: 5 mm a 8 mm (o más). Absorbe impactos severos, evita que se rompa el suelo base y aísla ruidos y vibraciones extremas. | C4: Diseño Liso Características: Superficie totalmente plana, sin texturas ni relieves.Usos ideales: Talleres mecánicos, laboratorios o áreas de ensamblaje donde se trabaja con piezas muy pequeñas.Ventaja: Es el más fácil de barrer, limpiar y fregar, ya que no acumula polvo ni grasa en las uniones. | D4: Pasillos de alto tráfico: Resisten el tránsito constante de personas y carros de carga ligera. | E4: Zonas de juegos infantiles: Amortiguan golpes y caídas de niños, siendo fáciles de limpiar de restos de comida o líquidos. | F4: Cajas de camiones: Evitan que la mercadería se deslice bruscamente durante el trayecto. | G4: Rampas y accesos: Se instalan en zonas inclinadas exteriores para transformarlas en superficies peatonales seguras. [1]
C5: Diseño Diamantado (Semilla de Melón) Características: Relieves en forma de rombos cruzados que imitan a las planchas metálicas industriales.Usos ideales: Talleres industriales, rampas de carga pesada y zonas exteriores resbaladizas.Ventaja: Ofrece la máxima tracción para calzado industrial y ruedas de maquinaria | D5: Bodegas y almacenes: Protegen el suelo de concreto contra la caída de herramientas u objetos pesados.
A6: EMPAQUETADURA POR ROLLO NR/SBR SIN TELA | B6: Límites técnicos de temperatura y presión | C6: Contacto con algún químico, combustible o aceite | D6: Uso en Fabricación de Juntas y Sellado | E6: Uso Protección y Amortiguación Industrial | F6: Uso Raspadores y Limpieza | G6: Uso Aislamiento General
B7: Rango de Temperatura Temperatura de trabajo: -20 °C hasta +70 °C (máximo continuo).Picos intermitentes: Puede tolerar hasta +80 °C por periodos muy cortos. Comportamiento: Si se supera este límite, la goma se reseca, se endurece y pierde su elasticidad, rompiendo el sello hermético. | C7: Aceites, Combustibles y Derivados del Petróleo Comportamiento: NO resiste. Efecto: El contacto con gasolina, petróleo diésel, aceites de motor, fluidos hidráulicos o grasas minerales disuelve los enlaces del SBR. La goma se hincha, se ablanda como chicle y se destruye rápidamente, perdiendo toda capacidad de sellado. Alternativa: Si tu aplicación involucra estos fluidos, debes usar Caucho Nitrilo (NBR). | D7: Juntas para bridas de agua: Sellado seguro en tuberías de agua fría, agua caliente (temperaturas moderadas) y fluidos no corrosivos. | E7: Cortinas protectoras: Cortinas de goma en cabinas de granallado o arenado para resistir la abrasión del impacto. | F7: Hojas de raspadores: Gomas para barredoras industriales o maquinaria de despeje de nieve y lodo. | G7: Aislantes de contacto: Barreras para evitar el contacto directo entre metales (corrosión galvánica) en estructuras livianas.
B8: Rango de Presión Restricción por espesor: A mayor espesor de la empaquetadura, menor es su resistencia a la presión, ya que el material tiende a "escupirse" o deformarse hacia afuera de la brida. Comportamiento: Al no tener tela interior, carece de resistencia estructural contra la deformación por aplastamiento o por el empuje de fluidos a alta presión. | C8: Ácidos y Químicos Fuertes Comportamiento: Resistencia baja a nula. Efecto: Los ácidos concentrados (como el sulfúrico o clorhídrico), solventes (diluyente, acetona) y químicos oxidantes degradan y queman el material de forma inmediata. Alternativa: Para químicos agresivos, se debe utilizar EPDM (para ácidos diluidos) o Viton (FKM) (para químicos severos y alta temperatura). | D8: Gasquetes industriales: Fabricación de empaquetaduras a medida para estanques de almacenamiento de fluidos neutros. | E8: Apoyos antivibratorios: Almohadillas para colocar debajo de equipos ligeros, motores eléctricos o compresores para absorber ruidos. | F8: Rasquetas de limpieza: Tiras de goma flexibles utilizadas para escurrir grandes volúmenes de líquidos en plantas procesadoras. | G8: Cubiertas protectoras: Tapas provisionales para proteger hilos de flanges o uniones mecánicas durante trabajos de mantenimiento.
C9: Fluidos Compatibles (Uso Seguro) Agua: Excelente resistencia a agua dulce, agua salada, aguas servidas y soluciones acuosas diluidas. Aire y Gases Inertes: Ideal para sellar sistemas de paso de aire comprimido a baja presión, nitrógeno o dióxido de carbono. Alcoholes y Álcalis Débiles: Soporta el contacto con alcoholes comerciales y soluciones de limpieza muy diluidas. | D9: Sellos de compuertas: Juntas de estanqueidad para ductos de ventilación, escotillas ligeras y cajas de inspección. | E9: Faldones para cintas transportadoras: Guías laterales (placas de desgaste) que contienen el material transportado sin dañar la banda en movimiento.
A10: PISOS NOMAD | B10: Tipo de Suelo Instalación | C10: Zona de Instalación | D10: Uso Accesos Principales y Entradas | E10: Uso Transporte y Vehículos | F10: Uso Zonas Húmedas y Áreas Deportivas | G10: Uso Industria y Áreas de Trabajo
B11: Sobre Hormigón Rugoso Instalación sin base (Exterior): Es la mejor opción. No requiere pegamento. La rugosidad del hormigón ayuda a que el piso Nomad no se deslice, y los poros permiten que el agua de lluvia corra libremente por debajo.Instalación con base (Techado) y pegado: Si necesitas pegarlo, la superficie rugosa consumirá mucho adhesivo. Debes aplicar un primer o sellador para concreto antes de poner el pegamento de doble contacto (Neoprén). Esto tapará los poros y evitará que el hormigón "se absorba" el pegamento. | C11: Exterior sin Techo (Exposición Directa a Lluvia y Sol) En esta zona, el objetivo principal es detener el barro grueso, las piedras y permitir que el agua drene para que el piso no flote ni se transforme en una piscina. El material correcto: Debes usar obligatoriamente un piso Nomad SIN BASE (abierto). Esto permite que el agua pase a través de los rulos hacia el suelo. Tipo de instalación: Se recomienda una instalación suelta (sin pegar). Al no llevar pegamento, puedes enrollar el piso fácilmente para limpiar con hidrolavadora el barro acumulado abajo. Fijación perimetral: Si la zona es muy ventosa o transitan carros pesados, se fija únicamente el borde superior (el lado por donde entra la gente) con perfiles metálicos atornillados al hormigón. El resto del rollo se deja libre para que drene el agua. | D11: Edificios corporativos: Se instalan en las puertas de entrada para mantener limpios los pisos interiores de mármol, porcelanato o madera. | E11: Cubre alfombras para autos: Se cortan a la medida del piso del vehículo. Su estructura atrapa las piedras, arena y barro de los zapatos, evitando que manchen el tapiz original. | F11: Bordes de piscinas: Los modelos sin base permiten que el agua drene hacia el suelo, ofreciendo una superficie antideslizante y segura para caminar descalzo. | G11: Pasillos de fábricas: Retienen virutas, polvillos metálicos o aserrín que los operarios transportan en sus botas de seguridad.
B12: Sobre Cerámica o Baldosa Instalación Suelta: Si el tránsito es bajo o medio, el piso Nomad con base de goma se adherirá muy bien gracias al peso del vinilo. No se deslizará fácilmente sobre la cerámica.Instalación Pegada (Alto Tráfico): Si hay cerámicas sueltas o quebradas, debes repararlas primero. Al aplicar el adhesivo de contacto, asegúrate de rellenar bien las líneas de fragüe para que queden al mismo nivel de la cerámica, evitando que con el tiempo se calque la forma de los cuadrados en la alfombra Nomad. | C12: Entrada Techada (Zona de Transición) Esta es la zona crítica donde el piso Nomad debe retener la humedad fina y el polvo que queda en los zapatos antes de pisar el suelo interior del edificio.El material correcto: Se utiliza un piso Nomad CON BASE de goma (cerrado). La base actúa como un contenedor que atrapa el agua y la suciedad, evitando que pasen al radier o baldosa inferior.Tipo de instalación: Depende del flujo de personas:Tráfico Alto (Edificios, Malls): Se debe pegar al 100% con adhesivo de doble contacto resistente a la humedad (o instalarlo suelto dentro de una fosa o rebaje en el piso). Esto evita que la alfombra se arrugue o se desplace con el frenado de los zapatos.Tráfico Medio/Bajo (Locales chicos, Casas): Se instala suelto. El propio peso de la base de goma y el calzado mantendrán el piso firme. | D12: Centros comerciales y malls: Soportan el flujo continuo de miles de personas diarias, reteniendo el polvo y el barro. | E12: Buses y transporte público: Se usan en las pisaderas o pasillos de entrada para evitar resbalones en días lluviosos. | F12: Camarines y duchas: Aíslan los pies del suelo húmedo, reduciendo el riesgo de caídas y la proliferación de hongos. | G12: Zonas de alto tráfico peatonal: Protegen los pisos base del desgaste prematuro causado por el roce constante.
B13: Sobre Pavimento Liso (Hormigón Afinador o Epóxico) Instalación Pegada: Requiere muy poca cantidad de adhesivo de doble contacto porque no hay porosidad. El agarre será inmediato y extremadamente firme.Precaución: El suelo debe estar completamente desengrasado. Si el pavimento liso tiene restos de ceras, aceites industriales o abrillantadores, el pegamento fallará. Se debe limpiar previamente con un desengrasante industrial o alcohol isopropílico. | D13: Hoteles y restaurantes: Evitan que la suciedad arruine la estética del lobby o las alfombras interiores. | F13: Saunas y spas: Resisten la humedad constante sin pudrirse ni generar malos olores. [1]
A14: PISOS PLANCHA GOMA | B14: PALMETA TÁCTIL DE GOMA NO VIDENTE | C14: PISO EN PLANCHA ESTOPEROL | D14: PISO PASTELON JUEGOS | E14: PISO PLANCHA ANTIDESLIZANTE | F14: PISO PLANCHA ANTIF/COCINA | G14: PISO PLANCHA GYM EPDM PUZZLE | H14: PISO GIMNASIO MIX
B15: Palmetas de Alerta o Precaución (Diseño de Botones / Estoperoles) Estas palmetas tienen relieve de círculos truncados. Su función es advertir sobre un peligro inminente, un cambio de nivel o una parada obligatoria.Bordes de andenes y estaciones: Indican el límite seguro antes de las vías en metros, trenes y terminales de buses.Cruces peatonales y esquinas: Se ubican justo antes de bajar a la calzada o calle para que el peatón se detenga.Inicio y término de escaleras o rampas: Avisan que comienza un cambio de nivel para evitar caídas.Frente a puertas de ascensores: Altan el área de acceso seguro al elevador. | C15: Uso Comercial y Edificios Públicos Entradas y accesos peatonales: Retiene el avance de la humedad de los zapatos en días lluviosos antes de ingresar a locales comerciales.Escaleras y rampas de acceso: Se instala en los peldaños y zonas inclinadas para asegurar el apoyo del pie y evitar caídas.Pasillos de alto tráfico: Ideal para centros médicos, oficinas públicas y colegios debido a su alta durabilidad al desgaste mecánico. | D15: Áreas Infantiles y de Recreación Zonas de juegos en plazas públicas: Se instalan bajo columpios, resbalines, rampas y juegos modulares donde los niños saltan o caen constantemente.Patios de jardines infantiles y colegios: Reemplazan el hormigón rugoso o el pasto natural por una superficie limpia, suave y libre de astillas o piedras.Zonas de juegos en condominios: Crean espacios seguros dentro de comunidades residenciales para el uso seguro de bicicletas pequeñas o triciclos. | E15: El piso en plancha antideslizante (fabricado comúnmente en caucho, goma o PVC) es un revestimiento modular diseñado para entregar la máxima tracción, estabilidad y seguridad en zonas propensas a resbalones, caídas o donde se requiere un tránsito firme. Al venir en formato de plancha (palmeta), ofrece un excelente soporte estructural, es muy resistente al desgaste pesado y permite cambiar piezas dañadas de forma independiente. Sus usos principales se dividen según el entorno: | F15: Zonas de Cocción y Calientes (Línea de Fuegos) Frente a cocinas, freidoras y hornos: Aíslan al cocinero del calor del suelo y resisten las salpicaduras de aceite hirviendo y grasas pesadas sin deformarse ni derretirse. | G15: Los pisos en plancha para gimnasio de caucho EPDM con sistema puzzle (encajables) son revestimientos de alta densidad diseñados específicamente para el entrenamiento deportivo de alta intensidad. Las chispas o pecas de colores que tienen estas palmetas son de caucho EPDM, un material que les otorga una mayor resistencia al desgaste, protección UV y evita que se desgranen con el tiempo. Su formato tipo "puzzle" permite un armado rápido, modular y sin necesidad de usar adhesivos químicos. Sus usos principales se dividen según las distintas zonas de entrenamiento: | H15: El piso de gimnasio MIX (también conocido como piso mixto) es un revestimiento técnico que combina dos tipos de caucho: una base amortiguadora de caucho SBR negro reciclado y una capa superior decorativa y ultra resistente de caucho EPDM virgen en formato de chispas o pecas de colores. Su uso principal es el alto tráfico deportivo y comercial, destacando por ofrecer una excelente relación precio-calidad, ya que entrega la resistencia del EPDM en la superficie donde se pisa, pero reduce costos utilizando SBR en la base. Sus aplicaciones específicas son:
B16: Palmetas de Guía o Dirección (Diseño Acanalado / Bastones) Estas palmetas tienen relieve de líneas rectas paralelas. Su función es señalar la ruta segura a seguir o un camino libre de obstáculos.Ejes de circulación en veredas: Crean pasillos peatonales accesibles en plazas, paseos públicos y calles céntricas.Guiado en grandes recintos: Conducen al usuario desde la entrada de un edificio público (malls, hospitales, municipalidades) hacia los mesones de atención, tótems informativos o ascensores.Pasillos de tránsito libre: Indican tramos largos y rectos donde no existen postes, escaños ni basureros con los que chocar. | C16: Transporte y Logística Montacargas y ascensores de carga: Soporta el peso y el movimiento giratorio de las ruedas sin deformarse.Estaciones de metro y terminales de buses: Delimita zonas de tránsito peatonal pesado y áreas de espera segura.Pasillos de aviones y trenes: Absorbe el ruido de las pisadas y ofrece una superficie firme durante el movimiento del vehículo. | D16: Uso Deportivo Ligero y Gimnasios Infantiles Muros de escalada (boulder) para niños: Absorben los impactos de las caídas de baja altura en zonas de iniciación deportiva.Pistas de psicomotricidad: Utilizados en centros de terapia infantil o salas de estimulación temprana para que los niños gateen, rueden y corran sin riesgo de moretones. | E16: Uso Industrial y Talleres Accesos principales y entradas: Retiene el agua y el barro de los zapatos en días lluviosos, protegiendo las zonas interiores.Escaleras y pasillos de alto tráfico: Se instala en los peldaños y descansos de hospitales, colegios y malls para evitar caídas masivas.Zonas de cajas y atención al público: Brinda comodidad al personal y delimita de forma segura las áreas de espera. | F16: Zonas de Lavado y Desengrase (Scullery) Frente a lavavajillas industriales y lavaplatos: Sus perforaciones permiten que el agua y el jabón drenen inmediatamente hacia la pileta del suelo, manteniendo los pies del operario elevados y secos, evitando resbalones críticos. | G16: Zonas de Peso Libre y Musculación Áreas de mancuernas pesadas: Absorben el fuerte impacto y el ruido cuando los usuarios dejan caer las mancuernas o discos al suelo.Jaulas de potencia y racks: Protegen la losa de hormigón estructural del edificio de las trizaduras causadas por las cargas extremas de sentadillas o press de banca. | H16: Zonas de Musculación y Máquinas de Selectorizadas Gimnasios en Casa (Home Gyms) Premium Salas de Cardio y Clases Grupales Recepciones, Pasillos y Tiendas Deportivas
C17: Uso Industrial y de Talleres Líneas de ensamblaje: Funciona como un piso de descanso para operarios que pasan muchas horas de pie, aislando el frío del concreto.Zonas de empaque y bodegaje: Protege el suelo base del arrastre de cajas o golpes por caídas de productos.Talleres mecánicos ligeros: Evita los resbalones por goteo de agua o humedad ambiental (para aceites pesados se requiere una versión específica de nitrilo). | D17: Uso Residencial y Terrazas Patios traseros particulares: Ideales para delimitar el sector donde se instala una cama elástica, una piscina estructural o una casa de juegos de plástico.Senderos de jardín: Permiten crear caminos suaves y antideslizantes que aíslan la humedad del pasto para el tránsito seguro de niños y adultos mayores. | E17: Transporte y Logística Montacargas y ascensores de carga: Soporta el peso y el torque de las ruedas sin romperse ni desplazarse.Estaciones de pasajeros y andenes: Delimita las zonas de tránsito peatonal continuo en terminales de buses o trenes.Talleres mecánicos automotrices: Evita resbalones por goteo de agua (para contacto con aceites pesados se utiliza una versión especial de nitrilo NBR). | F17: Áreas de Preparación y Producción (Cuarto Frío/Caliente) Mesones de picado y ensamblaje: Reducen drásticamente el cansancio, dolores lumbares y fatiga muscular de los maestros de cocina y ayudantes que pasan turnos de pie de 8 a 12 horas.Zonas de emplatado: Protegen la loza, vasos o utensilios que caen por accidente, evitando que se quiebren al impactar contra el piso de cerámica tradicional. | G17: Zonas de Crossfit y Levantamiento Olímpico (Weightlifting) Plataformas de levantamiento: Soportan las caídas libres de barras olímpicas cargadas desde la altura de los hombros o sobre la cabeza.Áreas de lanzamientos de balones (Slam Balls): Amortiguan el rebote de balones medicinales pesados, protegiendo tanto el balón como el suelo base.
C18: Uso Deportivo y Recreativo Zonas de recepción en gimnasios: Soporta el tráfico de deportistas con calzado rudo.Pasillos de camarines: Resiste el tránsito con pies húmedos ofreciendo una superficie segura y de rápido secado. | D18: Ventajas Técnicas clave de este formato Drenaje incorporado: La mayoría de los pastelones tienen canales inferiores que permiten que el agua de lluvia corra hacia los desagües, evitando charcos.Fácil recambio: Si una zona se gasta o se rompe (por ejemplo, justo debajo del columpio), se cambia únicamente la palmeta dañada sin alterar el resto del piso. | E18: Uso Deportivo y Áreas Húmedas Pasillos de camarines y duchas: Resiste el tránsito con pies húmedos en gimnasios o clubes deportivos, ofreciendo un secado rápido.Zonas de recepción y cardio: Soporta el movimiento constante de personas y el peso de trotadoras o bicicletas estáticas. | F18: Áreas de Almacenamiento y Cámaras Frías Cámaras de refrigeración: Funcionan como aislante térmico para que el frío del piso de la cámara no traspase el calzado del personal de bodega.Zonas de barras y despachos: Permiten un tránsito fluido y seguro para los garzones que entran y salen rápido de la cocina hacia el comedor. | G18: Salas de Cardio y Clases Dirigidas Bajo trotadoras, elípticas y spinning: Aíslan las vibraciones y el ruido de los motores de las máquinas, evitando que se traspasen a los pisos inferiores del edificio. También evitan que las máquinas se deslicen por el movimiento.Entrenamiento funcional y HIIT: Ofrecen una superficie antideslizante con un excelente agarre para zapatillas, ideal para hacer piques cortos, saltos al cajón o burpees sin riesgo de lesiones en las articulaciones.
A19: GRADAS ESCALA DE GOMA | B19: LUGAR DE INSTALACIÓN | C19: MATERIAL DE LA BASE DE LA ESCALERA (HORMIGÓN, METAL O MADERA) | D19: USO EDIFICIOS PÚBLICOS Y DE ALTO TRÁNSITO PEATONAL | E19: USOS INDUSTRIAS, FÁBRICAS Y TALLERES | F19: USO TRANSPORTE PÚBLICO E INFRAESTRUCTURA | G19: ÁREAS COMUNES RESIDENCIALES Y CONDOMINIOS
B20: El lugar de instalación (interior o exterior con lluvia) es el factor más importante para definir el tipo de goma y el pegamento químico que se debe utilizar para que las gradas no se despeguen ni se deslicen. | C20: Base de Hormigón (Cemento / Radier) Es la base más común, pero al ser porosa e irregular requiere la mayor preparación antes de instalar. Preparación: El hormigón debe estar completamente curado, seco y liso. Si tiene baches, hoyos o el canto (la nariz del peldaño) está picado, se debe reparar previamente con un mortero de reparación de alta resistencia. Hay que barrer muy bien para eliminar todo el polvo suelto. Pegamento adecuado:En interiores: Adhesivo de contacto (Neoprén) aplicado a doble cara.En exteriores con lluvia: Adhesivo de poliuretano (PU) de dos componentes o adhesivo híbrido, ya que la humedad del cemento suelta el neoprén. | D20: Escuelas y universidades: Previenen caídas masivas de estudiantes en zonas de escaleras durante los horarios de recreo o evacuación. Hospitales y clínicas: Ofrecen una superficie segura y amortiguada para pacientes con movilidad reducida, adultos mayores o personal de emergencia que se traslada rápido. Malls y centros comerciales: Protegen los bordes de los peldaños de concreto o cerámica del desgaste y picaduras causadas por el flujo constante de miles de personas. | E20: Escaleras de emergencia y vías de evacuación: Aseguran un escape rápido y sin resbalones en situaciones de pánico o cortes de luz. Acceso a plataformas de maquinaria: Aíslan al trabajador del frío del metal y evitan caídas causadas por calzado industrial húmedo o con restos de polvo seco. Bodegas y almacenes: Soportan el impacto del calzado rudo de los operarios que suben y bajan con carga manual pesada. | F20: Estaciones de metro y terminales de buses: Soportan el tránsito rudo y la fricción constante, resistiendo el agua de lluvia que los pasajeros arrastran en sus zapatos. Peldaños de buses y trenes: Se instalan en los accesos de los vehículos de pasajeros para evitar accidentes graves al subir o bajar los días de lluvia. | G20: Escaleras exteriores de edificios: Soportan la humedad ambiental y las heladas matinales, evitando que los peldaños se vuelvan resbaladizos. Accesos a subterráneos o estacionamientos: Delimitan visualmente cada peldaño gracias a sus diseños texturizados (usualmente con líneas acanaladas).
B21: Instalación en Escalera Interior En interiores, el foco está en la resistencia al desgaste, la facilidad de limpieza y que el adhesivo no emita olores tóxicos durante el montaje. Material recomendado: Se pueden usar gradas tanto de Caucho Sintético como de PVC de alta densidad. Tipo de adhesivo: Se utiliza adhesivo de contacto tradicional (tipo Neoprén) de base solvente, o idealmente adhesivos acrílicos base agua de bajo olor si el edificio está en funcionamiento (colegios u hospitales). Mantenimiento: Al estar protegidas del sol, las gradas no sufren decoloración ni resecamiento, por lo que su vida útil supera fácilmente los 10 años con un trapeado húmedo normal. | C21: Base de Metal (Fierro / Plancha Diamantada o Lisa) El metal no absorbe pegamento, por lo que el agarre depende de una superficie limpia y libre de óxido. Preparación: Si la escalera tiene pintura suelta u óxido, se debe pasar una escobilla de acero o esmeril hasta dejar el metal firme. Luego, se debe limpiar toda la superficie con alcohol isopropílico o diluyente para eliminar cualquier rastro de grasa o aceite protector del fierro. Pegamento adecuado: Se utiliza adhesivo de poliuretano (PU) en cartucho o adhesivos híbridos de alta resistencia. El neoprén tradicional no tiene buena vejez sobre superficies metálicas lisas sometidas a vibración o flexión al pisar.
B22: Instalación en Escalera Exterior (Expuesta a la Lluvia y Sol) En exteriores, el agua y los cambios de temperatura destruyen los pegamentos comunes, y la radiación UV quema el plástico de baja calidad. Material recomendado: Debes usar obligatoriamente Caucho Natural/Sintético (goma dura) con aditivos de protección UV. Evita el PVC económico en exteriores, ya que el sol lo cristaliza (se pone rígido) y la lluvia lo vuelve extremadamente resbaladizo. Diseño obligatorio: Debe tener estrías o canales profundos en la huella para que el agua de lluvia evacúe hacia los lados y la suela del zapato mantenga el contacto con la goma. Tipo de adhesivo (Crítico): NO utilices Neoprén común, ya que el agua de lluvia y la humedad del hormigón lo terminan soltando. Se debe instalar con adhesivo de poliuretano de dos componentes (PU) o adhesivos de montaje híbridos de alta resistencia para exteriores. Estos pegamentos sellan mecánicamente la grada al suelo y son 100% impermeables. | C22: Base de Madera La madera se mueve, se dilata con el calor y se contrae con el frío, por lo que el pegamento debe ser flexible. Preparación: La madera debe estar firme, sin crujidos ni tablas sueltas. Si tiene capas antiguas de cera, barniz o pintura brillante, se debe lijar profundamente hasta llegar a la madera porosa natural para que el pegamento penetre. Pegamento adecuado: Adhesivo de contacto de alta flexibilidad o adhesivos de montaje específicos para madera y goma. En zonas de alto tráfico, además del pegamento, se recomienda fijar la nariz de la grada con pequeños tornillos autorroscantes planos o corchetes industriales en los extremos para asegurar que la madera no escupa la goma al dilatarse.
A23: GRADAS ESCALA DE PVC | B23: LUGAR DE INSTALACIÓN | C23: MATERIAL DE LA BASE DE LA ESCALERA (HORMIGÓN, METAL O MADERA) | D23: USO EDIFICIOS PÚBLICOS Y DE ALTO TRÁNSITO PEATONAL | E23: USOS INDUSTRIAS, FÁBRICAS Y TALLERES | F23: USO TRANSPORTE PÚBLICO E INFRAESTRUCTURA | G23: ÁREAS COMUNES RESIDENCIALES Y CONDOMINIOS
B24: El lugar de instalación (interior o exterior con lluvia) es el factor más importante para definir el tipo de goma y el pegamento químico que se debe utilizar para que las gradas no se despeguen ni se deslicen. | C24: Base de Hormigón (Cemento / Radier) Es la base más común, pero al ser porosa e irregular requiere la mayor preparación antes de instalar. Preparación: El hormigón debe estar completamente curado, seco y liso. Si tiene baches, hoyos o el canto (la nariz del peldaño) está picado, se debe reparar previamente con un mortero de reparación de alta resistencia. Hay que barrer muy bien para eliminar todo el polvo suelto. Pegamento adecuado:En interiores: Adhesivo de contacto (Neoprén) aplicado a doble cara.En exteriores con lluvia: Adhesivo de poliuretano (PU) de dos componentes o adhesivo híbrido, ya que la humedad del cemento suelta el neoprén. | D24: Escuelas y universidades: Previenen caídas masivas de estudiantes en zonas de escaleras durante los horarios de recreo o evacuación. Hospitales y clínicas: Ofrecen una superficie segura y amortiguada para pacientes con movilidad reducida, adultos mayores o personal de emergencia que se traslada rápido. Malls y centros comerciales: Protegen los bordes de los peldaños de concreto o cerámica del desgaste y picaduras causadas por el flujo constante de miles de personas. | E24: Escaleras de emergencia y vías de evacuación: Aseguran un escape rápido y sin resbalones en situaciones de pánico o cortes de luz. Acceso a plataformas de maquinaria: Aíslan al trabajador del frío del metal y evitan caídas causadas por calzado industrial húmedo o con restos de polvo seco. Bodegas y almacenes: Soportan el impacto del calzado rudo de los operarios que suben y bajan con carga manual pesada. | F24: Estaciones de metro y terminales de buses: Soportan el tránsito rudo y la fricción constante, resistiendo el agua de lluvia que los pasajeros arrastran en sus zapatos. Peldaños de buses y trenes: Se instalan en los accesos de los vehículos de pasajeros para evitar accidentes graves al subir o bajar los días de lluvia. | G24: Escaleras exteriores de edificios: Soportan la humedad ambiental y las heladas matinales, evitando que los peldaños se vuelvan resbaladizos. Accesos a subterráneos o estacionamientos: Delimitan visualmente cada peldaño gracias a sus diseños texturizados (usualmente con líneas acanaladas).
B25: Instalación en Escalera Interior En interiores, el foco está en la resistencia al desgaste, la facilidad de limpieza y que el adhesivo no emita olores tóxicos durante el montaje. Material recomendado: Se pueden usar gradas tanto de Caucho Sintético como de PVC de alta densidad. Tipo de adhesivo: Se utiliza adhesivo de contacto tradicional (tipo Neoprén) de base solvente, o idealmente adhesivos acrílicos base agua de bajo olor si el edificio está en funcionamiento (colegios u hospitales). Mantenimiento: Al estar protegidas del sol, las gradas no sufren decoloración ni resecamiento, por lo que su vida útil supera fácilmente los 10 años con un trapeado húmedo normal. | C25: Base de Metal (Fierro / Plancha Diamantada o Lisa) El metal no absorbe pegamento, por lo que el agarre depende de una superficie limpia y libre de óxido. Preparación: Si la escalera tiene pintura suelta u óxido, se debe pasar una escobilla de acero o esmeril hasta dejar el metal firme. Luego, se debe limpiar toda la superficie con alcohol isopropílico o diluyente para eliminar cualquier rastro de grasa o aceite protector del fierro. Pegamento adecuado: Se utiliza adhesivo de poliuretano (PU) en cartucho o adhesivos híbridos de alta resistencia. El neoprén tradicional no tiene buena vejez sobre superficies metálicas lisas sometidas a vibración o flexión al pisar.
B26: Instalación en Escalera Exterior (Expuesta a la Lluvia y Sol) En exteriores, el agua y los cambios de temperatura destruyen los pegamentos comunes, y la radiación UV quema el plástico de baja calidad. Material recomendado: Debes usar obligatoriamente Caucho Natural/Sintético (goma dura) con aditivos de protección UV. Evita el PVC económico en exteriores, ya que el sol lo cristaliza (se pone rígido) y la lluvia lo vuelve extremadamente resbaladizo. Diseño obligatorio: Debe tener estrías o canales profundos en la huella para que el agua de lluvia evacúe hacia los lados y la suela del zapato mantenga el contacto con la goma. Tipo de adhesivo (Crítico): NO utilices Neoprén común, ya que el agua de lluvia y la humedad del hormigón lo terminan soltando. Se debe instalar con adhesivo de poliuretano de dos componentes (PU) o adhesivos de montaje híbridos de alta resistencia para exteriores. Estos pegamentos sellan mecánicamente la grada al suelo y son 100% impermeables. | C26: Base de Madera La madera se mueve, se dilata con el calor y se contrae con el frío, por lo que el pegamento debe ser flexible. Preparación: La madera debe estar firme, sin crujidos ni tablas sueltas. Si tiene capas antiguas de cera, barniz o pintura brillante, se debe lijar profundamente hasta llegar a la madera porosa natural para que el pegamento penetre. Pegamento adecuado: Adhesivo de contacto de alta flexibilidad o adhesivos de montaje específicos para madera y goma. En zonas de alto tráfico, además del pegamento, se recomienda fijar la nariz de la grada con pequeños tornillos autorroscantes planos o corchetes industriales en los extremos para asegurar que la madera no escupa la goma al dilatarse.
A27: PISOS PVC | B27: LUGAR DE INSTALACIÓN | C27: MATERIAL DE LA BASE | D27: PISO PVC DIAMANTADO | E27: PISO PVC ESTOPEROL | F27: PISO PVC TIPO WET | G27: PISO PVC TIPO CAMARÍN
B28: Para instalar correctamente pisos de PVC (tanto en rollo como en listones Click, LVT o SPC), es fundamental analizar el lugar de instalación, ya que la humedad, la temperatura y el sol directo influyen en el comportamiento del plástico.Los requerimientos técnicos y recomendaciones se dividen según las características del espacio: | C28: El éxito de la instalación de cualquier piso de PVC (ya sea en rollo, listones Click, SPC o LVT) depende al 100% del tipo de base o suelo actual donde se va a montar [LVT (PVC puro), SPC de alto tráfico]. Como el PVC es un material flexible y delgado, cualquier imperfección, humedad o desnivel de la base se terminará transmitiendo o "calcando" en la superficie.A continuación, te detallo los requisitos técnicos y la preparación necesaria según cada tipo de base: | D28: El piso de PVC diamantado (con diseño de "semilla de melón" o rombos en relieve) es un revestimiento plástico de alta resistencia diseñado específicamente para entregar la máxima tracción, seguridad y durabilidad en zonas propensas a resbalones. Al ser de PVC, ofrece un acabado moderno, es más liviano que la goma y resulta extremadamente fácil de limpiar. Sus usos principales se dividen por sectores: | E28: El piso de PVC diamantado (con diseño de "semilla de melón" o rombos en relieve) es un revestimiento plástico de alta resistencia diseñado específicamente para entregar la máxima tracción, seguridad y durabilidad en zonas propensas a resbalones. Al ser de PVC, ofrece un acabado moderno, es más liviano que la goma y resulta extremadamente fácil de limpiar. Sus usos principales se dividen por sectores: | F28: Principales Usos y Aplicaciones Este tipo de piso es ampliamente utilizado en entornos comerciales, industriales y residenciales, tales como: Áreas recreativas y deportivas: Bordes de piscinas, saunas, jacuzzis, spas y terrazas exteriores. Zonas sanitarias y vestuarios: Duchas públicas, camarines, baños de gimnasios, hospitales y clínicas. Rubro gastronómico e industrial: Cocinas industriales, bares, plantas de procesamiento de alimentos y laboratorios. Protección de superficies: Se usa también en el fondo de cajones, estantes o lavaplatos comerciales para amortiguar y proteger vajilla o cristalería. | G28: Principales Usos y Aplicaciones Este tipo de piso es ampliamente utilizado en entornos comerciales, industriales y residenciales, tales como: Áreas recreativas y deportivas: Bordes de piscinas, saunas, jacuzzis, spas y terrazas exteriores. Zonas sanitarias y vestuarios: Duchas públicas, camarines, baños de gimnasios, hospitales y clínicas. Rubro gastronómico e industrial: Cocinas industriales, bares, plantas de procesamiento de alimentos y laboratorios. Protección de superficies: Se usa también en el fondo de cajones, estantes o lavaplatos comerciales para amortiguar y proteger vajilla o cristalería.
B29: Espacios Interiores Secos (Habitaciones, Pasillos, Oficinas) Es el entorno ideal para cualquier tipo de piso de PVC. Al no haber variaciones extremas de temperatura, el material no sufre deformaciones [LVT (PVC puro)].Espacios comunes: Dormitorios, livings, comedores, pasillos, salas de clases y oficinas de plantas libres [LVT (PVC puro)].Formato recomendado: Pisos vinílicos SPC o LVT en listones (sistema Click) para un acabado estético de alta gama, o PVC en rollo si buscas una alternativa económica y de rápida instalación [LVT (PVC puro), SPC de alto tráfico].Ventaja: Máxima durabilidad. El material no se raya fácilmente y mantiene su color original por años. | C29: Base de Radier o Hormigón (Cemento) Es la base más común, pero requiere una revisión estricta antes de trabajar.Requisito crítico: El cemento debe estar 100% seco (mínimo 28 días de secado si es nuevo) y libre de porosidad extrema.Preparación: Si la superficie está rugosa o tiene grietas, es obligatorio aplicar un mortero autonivelante para dejar el suelo liso como un espejo. Si instalas PVC en rollo sobre un cemento rugoso, el pegamento no agarrará bien y el piso se romperá rápido.Formato ideal: Si el radier está bien nivelado, acepta tanto PVC en rollo (pegado) como listones SPC Click. | D29: Zonas Industriales, Talleres y Bodegas Pasillos de tránsito peatonal seguro: Ideal para delimitar rutas de caminata en fábricas y almacenes. Talleres eléctricos y salas de tableros: Al ser un material plástico, reduce el riesgo de conducción eléctrica estática en áreas técnicas de mantenimiento. Montacargas y cabinas de ascensores: Recubre el piso de elevadores de carga para evitar que las transpaletas, carros manuales o pallets se deslicen bruscamente. | E29: Zonas Industriales, Talleres y Bodegas Pasillos de tránsito peatonal seguro: Ideal para delimitar rutas de caminata en fábricas y almacenes. Talleres eléctricos y salas de tableros: Al ser un material plástico, reduce el riesgo de conducción eléctrica estática en áreas técnicas de mantenimiento. Montacargas y cabinas de ascensores: Recubre el piso de elevadores de carga para evitar que las transpaletas, carros manuales o pallets se deslicen bruscamente. | F29: Características y Beneficios Clave Diseño Drenante (Trama Abierta): Su estructura en forma de "S" u ondas caladas permite que el agua y los líquidos filtren inmediatamente hacia el suelo base. Evita la acumulación de charcos. Propiedades Higiénicas: Cuenta con tratamientos antimicóticos y antibacteriales. Impide la proliferación de hongos, moho y malos olores en ambientes constantemente mojados. Confort a Pie Descalzo: Su textura es suave y agradable al tacto. No se sobrecalienta excesivamente bajo el sol, protegiendo los pies de quemaduras. Alta Resistencia: Tolera la exposición directa a los rayos UV (no pierde el color fácilmente) y resiste el contacto con químicos de limpieza o cloro. Instalación Inmediata: Generalmente se comercializa en rollos (de espesores entre 5 mm). No requiere adhesivos ni mano de obra compleja; simplemente se desenrolla sobre la superficie existente (cemento, cerámica, etc.). | G29: Características y Beneficios Clave Diseño Drenante (Trama Abierta): Su estructura en forma de "S" u ondas caladas permite que el agua y los líquidos filtren inmediatamente hacia el suelo base. Evita la acumulación de charcos. Propiedades Higiénicas: Cuenta con tratamientos antimicóticos y antibacteriales. Impide la proliferación de hongos, moho y malos olores en ambientes constantemente mojados. Confort a Pie Descalzo: Su textura es suave y agradable al tacto. No se sobrecalienta excesivamente bajo el sol, protegiendo los pies de quemaduras. Alta Resistencia: Tolera la exposición directa a los rayos UV (no pierde el color fácilmente) y resiste el contacto con químicos de limpieza o cloro. Instalación Inmediata: Generalmente se comercializa en rollos (de espesores entre 5 mm). No requiere adhesivos ni mano de obra compleja; simplemente se desenrolla sobre la superficie existente (cemento, cerámica, etc.).
B30: Zonas Húmedas Interiores (Baños, Cocinas, Lavaderos) El PVC es 100% impermeable, lo que lo convierte en el sustituto perfecto para la cerámica tradicional en áreas expuestas al agua [LVT (PVC puro)].Espacios comunes: Cocinas residenciales, baños públicos y privados, logias y zonas de lavado [LVT (PVC puro)].Formato recomendado: Pisos SPC Click (ya que su alma de piedra caliza evita que el agua filtre entre las uniones) o PVC en rollo pegado, el cual crea una superficie continua y sellada [LVT (PVC puro), SPC de alto tráfico].Precaución: Aunque el piso no se daña con el agua, si queda una filtración debajo del piso, se pueden generar hongos en el hormigón. El suelo base debe estar completamente seco antes de montar el piso. | C30: Base de Cerámica o Baldosa Antigua Es muy común en remodelaciones rápidas para evitar demoler el piso anterior.Requisito crítico: Las cerámicas deben estar firmes y pegadas. Si hay palmetas sueltas, se deben retirar y rellenar el hueco.Preparación: La línea del fragüe (la unión entre cerámicas) crea un pequeño hundimiento. Si pones un PVC encima, con los meses esa cuadrícula se marcará en la superficie. Para evitarlo, se debe aplicar una pasta de revisión o tapaporos sobre toda la cerámica para rellenar las uniones y dejar el suelo liso.Formato ideal: El piso SPC Click es el mejor para este caso, ya que al ser más rígido disimula mejor las pequeñas imperfecciones que el PVC en rollo. | D30: Logística, Garajes y Furgones Maleteros de vehículos y pick-ups: Protege la lata de camionetas o furgones del roce diario de herramientas o cajas de reparto. Estacionamientos residenciales techados: Resiste el goteo ligero de fluidos del motor (agua, refrigerante) y protege el radier del desgaste por el giro de las ruedas al estacionar. | E30: Logística, Garajes y Furgones Maleteros de vehículos y pick-ups: Protege la lata de camionetas o furgones del roce diario de herramientas o cajas de reparto. Estacionamientos residenciales techados: Resiste el goteo ligero de fluidos del motor (agua, refrigerante) y protege el radier del desgaste por el giro de las ruedas al estacionar.
B31: Recintos Sanitarios e Industriales (Espacios de Alta Higiene) Zonas que requieren desinfección constante y donde no se permite la acumulación de suciedad en juntas.Espacios comunes: Clínicas, pabellones quirúrgicos, laboratorios, clínicas veterinarias y cocinas comerciales [LVT (PVC puro)].Formato recomendado: Piso de PVC en rollo homogéneo o conductivo, instalado obligatoriamente con soldadura al calor en las uniones y zócalo sanitario (curvatura que sube hacia la pared) | C31: Base de Madera, Terciado o Planchas de OSB Se encuentra habitualmente en segundos pisos o construcciones ligeras.Requisito crítico: La madera debe estar completamente firme, atornillada y sin "juego" o crujidos al caminar. El movimiento de la base quiebra las uniones del PVC.Preparación: Se deben lijar las uniones entre planchas de madera y tapar las cabezas de los tornillos o clavos con masilla elastomérica.Formato ideal: El piso vinílico Click (LVT o SPC) funciona excelente porque flota sobre la madera y absorbe mejor las micro-dilataciones de la estructura. | D31: Uso Comercial, Eventos y Exhibiciones Rampas y pendientes de acceso: Entrega un excelente agarre para el público en zonas inclinadas techadas. Escenarios y stands de ferias: Es muy utilizado en el montaje temporal de eventos debido a su atractiva estética industrial, rapidez de despliegue y resistencia al calzado rudo. Locales comerciales y discotecas: Su superficie impermeable permite trapear y limpiar de forma muy rápida los derramamientos de líquidos o tragos. | E31: Uso Comercial, Eventos y Exhibiciones Rampas y pendientes de acceso: Entrega un excelente agarre para el público en zonas inclinadas techadas. Escenarios y stands de ferias: Es muy utilizado en el montaje temporal de eventos debido a su atractiva estética industrial, rapidez de despliegue y resistencia al calzado rudo. Locales comerciales y discotecas: Su superficie impermeable permite trapear y limpiar de forma muy rápida los derramamientos de líquidos o tragos.
B32: Exteriores Sin Techo (Terrazas, Patios, Balcones Descubiertos) Los pisos de PVC NO se deben instalar en exteriores descubiertos.Efecto del sol: La radiación UV directa cristaliza y decolora el PVC. En pocos meses se pondrá rígido y se quebrará.Efecto de la temperatura: El calor extremo del sol directo hace que el plástico se dilate de forma masiva, levantando las uniones Click o creando globos si está pegado.Alternativa: Para zonas exteriores sin techo se debe usar WPC (Deck compuesto) o Palmetas de caucho/goma. | C32: Base de Piso Flotante o Alfombra Antigua Requisito crítico: NO se puede instalar encima.Preparación: Si tienes una alfombra o un piso flotante antiguo, debes retirarlos por completo antes de la instalación. La alfombra es una base blanda que romperá los clics del piso vinílico, y el piso flotante antiguo puede acumular humedad y pudrirse debajo del PVC. | D32: Áreas Comunes y del Hogar Logias y salas de lavado: Resiste la humedad constante, salpicaduras de agua y derrames de detergente sin deformarse.Descansos de escaleras: Evita resbalamientos en los giros de escaleras de alto flujo en colegios, institutos o casas particulares [Cruzeiro Gomas]. | E32: Áreas Comunes y del Hogar Logias y salas de lavado: Resiste la humedad constante, salpicaduras de agua y derrames de detergente sin deformarse.Descansos de escaleras: Evita resbalamientos en los giros de escaleras de alto flujo en colegios, institutos o casas particulares [Cruzeiro Gomas].
A33: ESPONJAS DIMENSIONADAS | B33: ESPONJAS DIMENSIONADAS CNA | C33: ESPONJA AUTOADHESIVA PVC | D33: ESPONJAS DIMENSIONADAS SBR | E33: ESPONJAS EN PLANCHA | F33: ESPONJAS RODON NEOPREN | G33: ESPONJAS RODON SBR
B34: Las esponjas dimensionadas CNA (comúnmente fabricadas en caucho EPDM o poliuretano de alta densidad) son perfiles de espuma cortados a medidas específicas que se utilizan principalmente como sellos de estanqueidad, amortiguadores de impacto y aislantes industriales. Su principal función es evitar el desgaste por roce entre materiales duros y proteger contra filtraciones. | C34: La esponja autoadhesiva de PVC (también conocida como cinta de espuma de PVC de celda cerrada) se utiliza principalmente para el sellado hermético, aislamiento termoacústico y amortiguación de baja compresión en ventanas, tabiques, automóviles y conductos de climatización. Al estar fabricada con cloruro de polivinilo expandido de celda cerrada, esta espuma es 100% impermeable al agua y al aire cuando se comprime ligeramente. El adhesivo en una de sus caras permite una instalación sumamente rápida sobre metal, madera, vidrio o plástico. | D34: Las esponjas dimensionadas SBR son tiras o perfiles de goma esponja fabricados a partir de Caucho Estireno Butadieno (SBR), cortados a medidas específicas de ancho y espesor. Su uso principal es actuar como sellos de estanqueidad estáticos, amortiguadores de impactos mecánicos severos y barreras antivibración en entornos industriales, de transporte y construcción pesada. A diferencia del EPDM (que destaca en exteriores), el caucho SBR esponjoso es el estándar elegido cuando se requiere una máxima resistencia al desgaste por roce continuo, excelente absorción de impactos pesados y alta resiliencia mecánica a un costo más económico. | E34: Las esponjas en plancha (también llamadas planchas de espuma o bloques de elastómeros expandidos) se utilizan principalmente para la confección de empaquetaduras industriales, amortiguación de embalajes técnicos, aislamiento acústico y tapicería pesada. A diferencia de los perfiles en rollo, el formato en plancha permite recortar piezas a medida, arandelas gigantes o siluetas complejas según los requerimientos del proyecto. Su uso varía drásticamente según el tipo de material con el que estén fabricadas: | F34: La esponja rodón de neopreno (también conocida como cordón de goma esponja o burlete cilíndrico) se utiliza principalmente como sello elástico y compresible para rellenar ranuras, juntas de dilatación e irregularidades en estructuras industriales, marinas y de construcción. Su diseño en formato cilíndrico (redondo) y su estructura interna de celda cerrada permiten que actúe como un tapón hermético. Al ser presionada por una tapa o panel, la goma se deforma copiando las imperfecciones de la superficie y bloquea el paso de fluidos sin absorber agua ni humedad. | G34: La esponja rodón de SBR (también conocida como cordón de goma esponja de sección redonda) se utiliza principalmente como sello de estanqueidad suave, amortiguador de baja compresión y aislante vibratorio en juntas de formas irregulares o ranuras cilíndricas. Al estar fabricado de Caucho Estireno Butadieno (SBR) con una estructura celular o microporosa, este cordón es altamente flexible y ligero. Su principal ventaja es que puede comprimirse con muy poca fuerza para copiar las imperfecciones de las superficies y recuperar su forma original (memoria elástica) una vez que se retira la presión.
B35: Principales usos y aplicaciones Aislamiento y sellado industrial: Se colocan en juntas de dilatación, puertas industriales y escotillas para evitar el paso de aire, polvo, viento o agua. Separación de materiales: Funcionan como barrera protectora para evitar el contacto directo y destructivo entre superficies como vidrio-metal o metal-metal. Amortiguación de vibraciones: Absorben impactos en maquinaria, portones pesados, carrocerías de vehículos y estructuras metálicas. Sector construcción y techumbre: Se usan para rellenar los huecos en las terminaciones de techos, impidiendo la entrada de suciedad o pequeños animales. | C35: Usos y Aplicaciones Principales Aislamiento Térmico y Acústico Residencial: Es el burlete doméstico por excelencia. Se pega en los marcos de puertas y ventanas para eliminar las corrientes de aire (chiflonazos), impedir la entrada de polvo fino y reducir el ruido proveniente de la calle. Sistemas de Climatización y Ventilación (HVAC): Se instala en las juntas y uniones de los ductos de aire acondicionado y calefacción central. Actúa como sello para evitar pérdidas de presión de aire y absorbe las vibraciones metálicas del sistema para eliminar ruidos molestos. Sector Automotriz y Carrocerías: Se aplica en el contorno de focos traseros, parlantes, paneles interiores de puertas y cúpulas de camionetas. Evita que las piezas plásticas o metálicas vibren entre sí y detiene filtraciones de agua hacia los circuitos eléctricos. Construcción y Tabiquería Estructural: Se coloca en la base de los perfiles metálicos (como el Metalcon o estructuras de aluminio) antes de fijarlos al suelo o a la pared. Funciona como barrera acústica para que el sonido no se transmita a través de la estructura del edificio. Electrónica y Línea Blanca: Actúa como junta protectora antivibración en tapas de lavadoras, refrigeradores y paneles de instrumentos eléctricos delicados. | D35: Usos y Aplicaciones Principales Amortiguación de Puertas Pesadas y Portones: Se instalan como topes continuos en los marcos de portones metálicos industriales, puertas de bodegas y accesos de talleres para absorber el golpe del cierre y evitar el daño estructural por impacto fierro con fierro. Sellado de Escotillas y Compuertas Industriales: Actúan como juntas de estanqueidad en compuertas de descarga de tolvas, mezcladoras de cemento y silos de almacenamiento, impidiendo la fuga de materiales pulverulentos o agua sin presión. Aislamiento Antivibración de Maquinaria: Colocadas en tiras debajo de bases de motores eléctricos, compresores de aire de taller, ventiladores industriales o cajas de transmisión para cortar la propagación del ruido y las vibraciones hacia la estructura del suelo. Carrocerías y Paneles de Transporte: Se aplican en las uniones de las planchas metálicas de camiones de carga, remolques y maquinaria agrícola. Evitan el desgaste por fricción provocado por el movimiento en ruta y sellan contra el ingreso de polvo grueso. Apoyo Estructural en Construcción: Funcionan como bandas de asiento o juntas de dilatación ligeras entre paneles prefabricados de hormigón o estructuras metálicas para absorber pequeñas tolerancias y asentamientos. | E35: Usos principales según el tipo de material 1. Planchas de Goma Esponja EPDM (Uso Industrial Exterior)Sellado de Gabinetes y Tableros: Fabricación de empaquetaduras para cajas eléctricas exteriores, transformadores o shelters expuestos a la intemperie.Uso Náutico: Sellos para escotillas de barcos, lanchas y compuertas de carga.Ventaja: Soporta de forma sobresaliente los rayos UV, el ozono y las temperaturas extremas sin cuartearse. 2. Planchas de Goma Esponja SBR o Neopreno (Uso Mecánico Pesado)Bases Antivibración: Se colocan debajo de compresores, motores industriales o generadores para cortar la transmisión de vibraciones hacia el piso.Topes de Impacto: Revestimiento para compuertas de tolvas, camiones de carga o portones pesados.Ventaja: Excelente resistencia al desgaste por roce, tracción e impactos mecánicos severos. | F35: Usos y Aplicaciones Principales Fabricación de empaquetaduras y O'Rings a medida: Se utiliza para construir anillos de sellado o juntas con formas irregulares en tapas de estanques, cajas de engranajes o depósitos industriales. Sellado de escotillas y compuertas marinas: Es el estándar en el sector náutico para sellar los marcos de las escotillas de barcos, botes y contenedores, impidiendo las filtraciones de agua salada hacia el interior. Gabinetes eléctricos y tableros de control (IP Sealing): Se introduce dentro de los canales o rieles de las puertas de tableros eléctricos exteriores para proteger los circuitos del ingreso de polvo fino, tierra y agua de lluvia. Conductos de climatización y HVAC: Actúa como sello estanco en paneles de acceso a sistemas de aire acondicionado centralizado, amortiguando además las vibraciones de los motores para eliminar ruidos mecánicos. Juntas de dilatación en construcción: Funciona como cordón de respaldo (backing rod) para rellenar juntas de expansión en pavimentos o estructuras de hormigón y acero antes de aplicar el sellador de poliuretano definitivo. | G35: Usos y Aplicaciones Principales Sellado de tapas, escotillas y cajas metálicas: Se introduce a presión dentro de los canales perimetrales de compuertas industriales, tolvas de descarga o cajas de herramientas para evitar el paso de polvo grueso, viento y humedad. Fabricación de empaquetaduras y juntas O-Ring a medida: Es la opción más económica para armar anillos de sellado estático con diámetros personalizados en bridas o uniones mecánicas que no requieran soportar fluidos corrosivos. Aislamiento acústico y antivibración: Funciona como junta amortiguadora en las uniones de estructuras metálicas o paneles de tabiquería, absorbiendo los ruidos por vibración mecánica generados por motores o corrientes de aire. Puertas y gabinetes industriales ligeros: Sello perimetral compresivo para paneles de inspección y tableros donde el cierre no ejerce un torque extremo pero se requiere un contacto hermético uniforme. Construcción (Cordón de respaldo / Backing Rod): Relleno base para juntas de dilatación profundas en pavimentos antes de la aplicación del sellador elástico definitivo.
B36: Características técnicas clave Material de alta resistencia: Al estar hechas usualmente de compuestos como el caucho EPDM, ofrecen una excelente resistencia al agua, al vapor, al ozono y a la intemperie (rayos UV). Formato comercial: Se comercializan habitualmente en rollos de metrajes largos (por ejemplo, tiras cuadradas de 20x20 mm en rollos de 50 metros) para cortarse fácilmente según el largo requerido por el proyecto. | C36: Ventajas Clave del Material Estructura de Celda Cerrada: A diferencia de las esponjas comunes (como las de poliuretano), el PVC de celda cerrada no absorbe agua como una esponja de baño; la repele por completo, lo que evita la acumulación de humedad, moho y hongos. Instalación Limpia: Al contar con una cara autoadhesiva protegida por un film de papel, no requiere pegamentos de contacto adicionales ni herramientas complejas. Solo se limpia la superficie, se corta a la medida y se presiona. Memoria de Compresión: Tiene la capacidad de recuperar su forma original después de ser presionada por una puerta o ventana, garantizando un sello constante a lo largo del tiempo. | D36: Características Técnicas Clave Estructura Celular Mixta/Cerrada: No absorbe fluidos fácilmente bajo una compresión moderada, lo que garantiza que mantenga sus propiedades físicas sin ablandarse por acumulación de agua. Excelente Resistencia al Desgaste: Tolera el cizallamiento y la fricción mecánica mucho mejor que la espuma de poliuretano o la esponja de PVC. Dureza y Flexibilidad: Generalmente posee una consistencia blanda pero firme, lo que le permite deformarse para copiar las imperfecciones de las superficies metálicas y recuperar su forma original (memoria elástica) al retirar la presión. | F36: Ventajas del Neopreno en este Formato Estructura de celda cerrada: Tiene burbujas de aire atrapadas de forma aislada. Esto garantiza que la esponja no funcione como una esponja de baño; no retiene ni absorbe aceites, agua u olores. Resistencia química moderada: A diferencia del caucho natural o el SBR, el neopreno resiste de buena manera el contacto intermitente con aceites minerales, grasas y combustibles ligeros sin ablandarse. Excelente memoria elástica: Aunque pase largos periodos bajo compresión extrema, la esponja recupera su forma cilíndrica original al abrir la compuerta, asegurando que el sello siga funcionando en el próximo cierre.
A37: EMPAQUETADURA POR ROLLO NR/SBR CON TELA | B37: DESCRIPCIÓN | C37: USOS Y APLICACIONES PRINCIPALES | D37: ESPECIFICACIONES TÉCNICAS COMUNES
B38: La empaquetadura por rollo de caucho NR/SBR con tela se utiliza principalmente para el sellado hermético de juntas industriales, bridas, tanques y conexiones expuestas a cargas mecánicas y presiones medias. Este material combina la flexibilidad del caucho natural (NR) y la resistencia al desgaste del caucho sintético de estireno-butadieno (SBR). La inclusión del refuerzo textil interno (generalmente una o varias telas de poliéster o algodón) tiene una función crítica: evitar el estiramiento excesivo del caucho, prevenir deformaciones bajo presión y otorgarle una alta estabilidad dimensional. | C38: Juntas de estanqueidad para bridas: Fabricación de sellos a medida para unir tuberías de agua o fluidos no corrosivos sometidos a presiones medias y altas. Sistemas mecánicos y de bombeo: Sellado en bridas de bombas hidráulicas y sistemas neumáticos de baja a mediana exigencia química. Empaques para tanques y contenedores: Tapas y compuertas industriales que requieren un cierre hermético sin que el caucho se desplace o pierda su forma con el apriete de los pernos. Amortiguación de vibraciones pesadas: Al tener mayor resistencia estructural por la tela, sirve como base de apoyo o soporte para maquinaria pesada, aislando vibraciones mecánicas. Arandelas y sellos de motores: Componentes de sellado en el sector automotriz y maquinaria pesada que operen dentro de rangos normales de temperatura. | D38: Para asegurar que se adapta a su proyecto, estas son las propiedades habituales de la mezcla NR/SBR con tela: Característica: Rango Estándar Temperatura de trabajo: Generalmente de -30°C a +80°C (algunos compuestos toleran picos de hasta 110°C). Resistencia Química: Buena ante el agua, soluciones salinas, ácidos débiles y alcoholes. No apto para aceites minerales, hidrocarburos o combustibles concentrados. Dureza comercial: 60 a 75 Shore A, ofreciendo un equilibrio óptimo entre flexibilidad y rigidez. Espesores comunes: Desde 1,6 mm (1/16") hasta 12,7 mm (1/2") según la cantidad de telas de refuerzo.
A39: CORREDERAS | B39: DESCRIPCIÓN | C39: USO AUTOMOTRIZ (TRANSPORTE) | D39: USO EN CONSTRUCCIÓN Y HOGAR | E39: USO INDUSTRIAL Y PORTONES AUTOMÁTICOS | F39: CORREDERA ANGULO | G39: CORREDERA CASITA CHICA | H39: CORREDERA AVALOS GONZALEZ | I39: CORREDERA CON NERVIO | J39: CORREDERA CORAMINA | K39: CORREDERA FF CC | L39: CORREDERA FINITA CHICA | M39: CORREDERA FLEXIBLE | N39: CORREDERA GORDILLO | O39: CORREDERA HARNERO | P39: CORREDERA MARCOPARABRISA | Q39: CORREDERA S ESPECIAL | R39: CORREDERA U
B40: Las correderas de goma (o perfiles corredera de caucho) se usan principalmente para sellar, proteger, guiar el deslizamiento y amortiguar impactos en elementos móviles como ventanas, puertas y portones. Su función principal varía según el sector donde se apliquen: | C40: Guías de vidrios: Permiten que las ventanas de autos, camionetas y autobuses suban y bajen suavemente sin rayar el cristal ni golpear el metal. Sellado contra el clima: Evitan las filtraciones de agua de lluvia, polvo y aíslan el ruido del viento hacia el interior de la cabina. Ventanas de buses: Los perfiles específicos (como los que distribuyen empresas del rubro se encastran en las estructuras metálicas para fijar vidrios fijos o móviles en el transporte público | D40: Ventanas y puertas correderas de aluminio: Se colocan en los rieles para amortiguar el cierre, reducir el cabeceo del marco y asegurar un hermetismo térmico eficiente. Mamparas de baño: Actúan como barreras de contención de agua en las juntas inferiores y laterales de las puertas correderas de cristal. Topes de fin de carrera: Bloques de goma densa dispuestos al final del riel para evitar que la puerta golpee con fuerza la pared. | E40: Gomas de seguridad (Bordes sensibles): En portones eléctricos correderos de bodegas o condominios, se instalan perfiles de goma con sensores internos (antipinzamiento) que detienen el motor si detectan un obstáculo. Maquinaria pesada: Protegen los bordes de paneles metálicos móviles y absorben las vibraciones generadas por la operación del equipo. | F40: La corredera ángulo (también conocida en el mercado técnico como corredera con nervio) es un perfil de goma diseñado específicamente para guiar, sellar y amortiguar el deslizamiento de vidrios en estructuras con marcos en ángulo o esquinas vivas. Está fabricada principalmente de caucho SBR (con una dureza estándar de 70 Shore-A), lo que le otorga una alta resistencia a la fricción constante, tracción mecánica e impactos sin deformarse. | G40: La corredera casita chica es un perfil técnico de goma (habitualmente fabricado de caucho SBR con una dureza de 70 Shore-A) que recibe su nombre popular debido a que su sección geométrica o silueta se asemeja a la silueta de una pequeña casa. Su uso principal es actuar como guía, sello y amortiguador en canales de ventanas correderas, especialmente donde se requiere fijar un vidrio o acrílico delgado de forma segura y hermética. | H40: La corredera Ávalos González es un perfil técnico de goma (habitualmente fabricado de caucho SBR con una dureza de 70 Shore-A) diseñado con una geometría específica de canales para actuar como guía y sello de estanqueidad en sistemas de ventanas correderas industriales y automotrices pesadas. Lleva este nombre característico en el mercado chileno de elastómeros (producido por fabricantes especializados como la Cruzeiro Gomas) debido al diseño de matriz patentado o popularizado para un tipo de carrocería o marco estructural específico. | I40: La corredera con nervio (también conocida en el mercado técnico como corredera ángulo) es un perfil de goma diseñado específicamente para guiar, sellar y amortiguar el deslizamiento de vidrios en estructuras con marcos en ángulo o esquinas vivas. El "nervio" es una pestaña o relieve longitudinal en su estructura que permite un encastre a presión firme dentro del riel metálico, evitando que la goma se desplace o se salga de su posición con el movimiento constante del vidrio. Está fabricada principalmente de caucho SBR (con una dureza estándar de 70 Shore-A), lo que le otorga una alta resistencia a la fricción constante, tracción mecánica e impactos sin deformarse. | J40: La corredera Coramina es un perfil técnico de goma diseñado específicamente para actuar como guía deslizante, amortiguador y sello de estanqueidad en ventanas correderas de vehículos de transporte, maquinaria pesada y estructuras metálicas industriales. Está fabricada de caucho SBR de alta resistencia y consistencia. Su matriz geométrica cuenta con un diseño específico que le permite encajarse firmemente en el marco y recibir el borde del cristal, garantizando estabilidad y un aislamiento óptimo. | K40: La corredera FF CC (abreviación técnica utilizada históricamente para Ferrocarriles) es un perfil de goma de alta resistencia diseñado originalmente para actuar como guía deslizante, amortiguador y sello de estanqueidad en las ventanas y puertas correderas de vagones de trenes y locomotoras. Debido a su excelente desempeño ante vibraciones extremas, este modelo se estandarizó en el mercado industrial de elastómeros para su uso en todo tipo de transporte pesado y estructuras industriales de gran envergadura. Está fabricado de caucho SBR con una dureza de 70 Shore-A, lo que le otorga una alta resistencia al desgaste mecánico por roce continuo. | L40: La corredera finita chica es un perfil técnico de goma (fabricado de caucho SBR con una dureza de 70 Shore-A) diseñado con paredes delgadas y un canal estrecho. Su uso principal es actuar como guía deslizante, sello climático y amortiguador en marcos de ventanas que utilizan vidrios o acrílicos de muy bajo espesor, donde un perfil estándar quedaría demasiado suelto. | M40: La corredera flexible es un perfil técnico de goma (habitualmente fabricado de caucho SBR con una dureza de 70 Shore-A) cuya principal característica es su alta maleabilidad y capacidad de torsión. A diferencia de los perfiles rígidos, este modelo está diseñado para adaptarse a rieles con curvas pronunciadas, contornos irregulares o esquinas redondeadas, actuando como guía, amortiguador y sello hermético para vidrios y acrílicos. | N40: La corredera Gordillo es un perfil técnico de goma de alta consistencia (fabricado en caucho SBR con una dureza de 70 Shore A) diseñado específicamente para actuar como guía deslizante, amortiguador y sello de estanqueidad en ventanas correderas de vehículos pesados e industriales.Al igual que otros modelos clásicos del mercado de elastómeros en Chile (como el catálogo especializado de Cruzeiro Gomas), su nombre proviene de un diseño geométrico de matriz estandarizado para carrocerías de transporte. | O40: La corredera harnero es un perfil técnico de goma de alta densidad diseñado específicamente para actuar como guía deslizante, amortiguador y sello hermético en los marcos de ventanas y compuertas de equipos de clasificación de material (harneros) o en aberturas expuestas a partículas gruesas.A diferencia de los modelos residenciales o automotrices livianos, esta corredera está fabricada con compuestos de caucho SBR de alta consistencia (70 Shore-A) para resistir condiciones severas de abrasión y movimientos vibratorios continuos. | P40: La corredera marcoparabrisa es un perfil técnico de goma diseñado específicamente para revestir, fijar y sellar los bordes de los vidrios en marcos de parabrisas, lunetas traseras y espejos de seguridad. Su función principal es proporcionar un canal de ajuste que proteja el cristal contra los impactos del marco rígido y evite filtraciones hacia el interior de la cabina.Está fabricada de caucho SBR con una dureza de 70 Shore-A, lo que le otorga una alta resistencia al desgaste mecánico por roce, tracción e intemperie. | Q40: La corredera S Especial es un perfil técnico de goma industrial diseñado específicamente para actuar como guía deslizante, amortiguador de alto impacto y sello hermético en ventanas correderas pesadas. Su nombre proviene de su matriz geométrica optimizada para rieles o canales con requerimientos estructurales específicos en equipos e infraestructuras expuestos a un uso extremadamente severo. Al igual que las variantes más exigentes de la industria, está fabricada en caucho SBR con una dureza de 70 Shore-A, lo que le confiere una máxima resistencia mecánica contra el desgaste por fricción y el agrietamiento. | R40: La corredera U (o perfil de goma en canal U) es el modelo más versátil y universal dentro del mercado de elastómeros. Su diseño simétrico en forma de "U" se utiliza principalmente para revestir cantos vivos, guiar el deslizamiento de vidrios o acrílicos y actuar como sello de estanqueidad en una gran variedad de estructuras metálicas, plásticas o de madera.
B41: Tipos de materiales comunes EPDM: El más recomendado para exteriores porque resiste de forma sobresaliente los rayos UV, el ozono y las temperaturas extremas sin cuartearse. SBR o Caucho Natural: Excelente resistencia a la fricción mecánica y al impacto constante, ideal para uso pesado en talleres | F41: Usos y Aplicaciones Principales Marcos de ventanas en esquinas: Se utiliza para revestir las uniones en ángulo de los marcos metálicos o de aluminio, asegurando que el vidrio se deslice de forma segura sin riesgo de trizaduras por el contacto directo metal-cristal. Maquinaria pesada y agrícola: Se instala en las cabinas de grúas, tractores o excavadoras para sostener y sellar los parabrisas o ventanas laterales que tienen diseños angulares pronunciados. Sector transporte y buses: Sirve como junta y guía en las ventanas de vehículos de pasajeros, absorbiendo las vibraciones severas del movimiento y evitando que el agua o el polvo ingresen a la cabina. Estructuras metálicas industriales: Se aplica en los bordes de escotillas de inspección, compuertas deslizantes o paneles móviles de protección para actuar como tope hermético y protector de bordes. | G41: Usos y Aplicaciones Principales Guía para ventanas correderas livianas: Se instala dentro del riel de marcos metálicos, de aluminio o madera. Permite que los vidrios se deslicen suavemente y de forma lineal sin atascarse. Aislamiento acústico y antivibración: Al quedar el vidrio ajustado dentro de la goma, absorbe las vibraciones provocadas por el viento o el movimiento del entorno, evitando el molesto tintineo o ruidos metálicos. Sellado climático y estanqueidad: Su diseño bloquea eficazmente el paso de corrientes de aire, polvo fino, polución y filtraciones de agua de lluvia hacia el interior. Protección del cristal: Evita el contacto directo del filo del vidrio contra las superficies duras del marco, previniendo trizaduras, picaduras o roturas por impactos al cerrar la ventana con fuerza. Vehículos menores y maquinaria: Muy común en cabinas de grúas horquilla, tractores antiguos, embarcaciones pequeñas o vehículos modificados que utilizan ventanas de corredera con canales estrechos. | H41: Usos y Aplicaciones Principales Carrocerías y Ventanas de Buses: Es ampliamente utilizado en el transporte público e interurbano para fijar y guiar los vidrios móviles de los costados del bus, absorbiendo las vibraciones del camino y evitando que el cristal golpee contra el metal del marco. Maquinaria Pesada y Agrícola: Se instala en los canales de las cabinas de grúas horquilla, excavadoras, cargadores frontales y tractores que usan sistemas de ventanas deslizantes en ambientes de alta exigencia física. Vehículos Especiales y de Carga: Sello perimetral y riel guía para furgones, camionetas con cúpulas integradas o vehículos modificados que requieren una tolerancia superior al desgaste por fricción. Estructuras Metálicas Marinas o Industriales: Adecuado para compuertas correderas ligeras o ventanas de cabinas de control donde se necesita impedir de manera eficiente la entrada de polvo, viento y agua de lluvia. | I41: Usos y Aplicaciones Principales Marcos de ventanas en esquinas: Se utiliza para revestir las uniones en ángulo de los marcos metálicos o de aluminio, asegurando que el vidrio se deslice de forma segura sin riesgo de trizaduras por el contacto directo metal-cristal. Maquinaria pesada y agrícola: Se instala en las cabinas de grúas, tractores o excavadoras para sostener y sellar los parabrisas o ventanas laterales que tienen diseños angulares pronunciados. Sector transporte y buses: Sirve como junta y guía en las ventanas de vehículos de pasajeros, absorbiendo las vibraciones severas del movimiento y evitando que el agua o el polvo ingresen a la cabina. Estructuras metálicas industriales: Se aplica en los bordes de escotillas de inspección, compuertas deslizantes o paneles móviles de protección para actuar como tope hermético y protector de bordes. | J41: Usos y Aplicaciones Principales Ventanas de buses y transporte colectivo: Se utiliza de forma masiva en carrocerías de transporte de pasajeros para montar los vidrios móviles. Evita el roce directo metal-cristal y amortigua los movimientos severos en ruta. Cabinas de maquinaria pesada: Se instala en los marcos de ventanas correderas de grúas horquilla, excavadoras, tractores y camiones mineros o agrícolas que operan en entornos con alta vibración. Estructuras modulares y shelters: Funciona como junta hermética en las ventanas deslizantes de oficinas móviles, contenedores habitacionales y casetas de vigilancia. Aislamiento y hermetismo: Bloquea de forma eficiente el ingreso de agua de lluvia, ruidos externos, corrientes de viento y polución o polvo hacia el interior de la cabina. | K41: Usos y Aplicaciones Principales Vagones de Trenes y Subterráneos (Uso Original): Instalación en los marcos de las ventanas correderas del material rodante ferroviario, asegurando que los cristales se deslicen de forma lineal y absorbiendo los movimientos bruscos de la vía. Maquinaria Pesada e Industrial: Se utiliza ampliamente en cabinas de grúas de gran tonelaje, excavadoras mineras y puentes grúa donde las ventanas están sometidas a vibraciones severas y constantes. Vehículos de Transporte de Carga: Riel de goma guía para las ventanas deslizantes de camiones pesados, buses interurbanos o furgones de reparto. Hermetismo y Sellado Climático: Bloquea de manera muy eficiente el ingreso de agua de lluvia, ruidos de motores externos, corrientes de viento y polución o polvo hacia el interior de la cabina. | L41: Usos y Aplicaciones Principales Ventanas residenciales y vitrinas livianas: Se instala dentro de los rieles de aluminio o madera para guiar cristales delgados, permitiendo una apertura suave y lineal sin que el vidrio se mueva hacia los lados. Aislamiento y hermetismo sutil: Bloquea de forma eficiente el paso de corrientes de aire, polvo fino y pequeñas filtraciones de agua en aberturas domésticas. Protección antivibración: Al mantener el vidrio ajustado de manera precisa dentro de su canal estrecho, absorbe las vibraciones ambientales y evita el molesto tintineo provocado por el viento. Proyectos de bricolaje y maquetación: Muy utilizada en la construcción de vitrinas de exhibición, acuarios pequeños, muebles con puertas correderas de acrílico o proyectos manuales que requieren un acabado limpio y discreto. | M41: Usos y Aplicaciones Principales Maquinaria Agrícola e Industrial: Se instala en los marcos de cabinas de tractores, cosechadoras, grúas horquilla y excavadoras, donde los ventanales correderos suelen tener diseños curvos o aerodinámicos para mejorar la visibilidad. Sector Automotriz y Carrocerías Especiales: Muy común en las ventanas laterales deslizantes de furgones de reparto, casas rodantes (motorhomes), cúpulas de camionetas y transporte de pasajeros con ventanas de esquinas redondeadas. Embarcaciones Náuticas: Utilizada en los parabrisas y ventanas de corredera de lanchas, botes y pequeños yates, donde las estructuras siguen las líneas curvas del casco del barco. Estanqueidad y Sello Climático: Evita de manera eficiente las filtraciones de agua de lluvia, ruidos molestos por el viento y el ingreso de polvo o tierra hacia el interior de la cabina. Amortiguación Antivibración: Su compuesto flexible absorbe los movimientos bruscos y las vibraciones constantes del motor o del terreno, impidiendo que el vidrio golpee directamente contra el marco metálico y se trice. | N41: Usos y Aplicaciones Principales Maquinaria Pesada y de Construcción: Se instala de forma masiva en los canales de las ventanas y parabrisas deslizantes de grúas horquilla, excavadoras, retroexcavadoras y cargadores frontales que operan bajo condiciones extremas de vibración. Sector Automotriz y Transporte Colectivo: Funciona como junta guía para los vidrios móviles de buses urbanos, interurbanos, furgones de reparto y vehículos de carga pesada. Hermetismo Climático: Su diseño sella herméticamente los bordes del cristal, bloqueando el ingreso de agua de lluvia, ruidos de motores, corrientes de aire y el polvo suspendido en zonas de trabajo o faenas mineras. Protección Antivibración: El caucho absorbe los impactos constantes provocados por el motor o las imperfecciones del terreno, impidiendo que el vidrio golpee directamente el marco metálico y sufra trizaduras. | O41: Usos y Aplicaciones Principales Marcos de ventanas en cabinas de harneado: Se instala en los canales de las ventanas correderas de las cabinas de control o protección situadas junto a harneros vibratorios industriales (minería y construcción), evitando que la vibración constante rompa o trice los vidrios. Sellado de marcos de marcos mosquiteros y harneros domésticos: En escalas menores, se utiliza para encastrar y fijar mallas de alambre tejidas (mallas harnero) o acrílicos en estructuras deslizantes de limpieza de semillas, arena o cemento. Barrera contra polvo y partículas: Su geometría con labios de presión bloquea de manera muy eficiente el ingreso de polución, tierra suspendida y agua hacia el interior de las zonas protegidas. Amortiguación metal-cristal: Absorbe los impactos mecánicos y evita el rozamiento directo entre los bordes duros de los rieles metálicos de la maquinaria y los paneles deslizantes. | P41: Usos y Aplicaciones Principales Marcos de Parabrisas y Lunetas: Se utiliza en la restauración y montaje de vidrios delanteros o traseros en autos clásicos (como el icónico Austin Mini), vehículos modificados, camiones y maquinaria pesada que requieren una junta perimetral a presión. Fabricación y Bordes de Espejos: Es muy común su uso industrial para el montaje de espejos de gran tamaño, actuando como un borde de seguridad amortiguador que previene cortes y roturas en las esquinas. Sellado de Ventanales Fijos o Deslizantes: Se coloca en estructuras metálicas expuestas a vibraciones moderadas para actuar como barrera hermética, impidiendo el paso de agua de lluvia, polvo fino y corrientes de aire hacia el habitáculo. | Q41: Usos y Aplicaciones Principales Maquinaria de Construcción y Minería: Se instala en las cabinas de retroexcavadoras, cargadores frontales, bulldozers y grúas de gran tonelaje, protegiendo los cristales frente a las vibraciones extremas del motor y el terreno. Vehículos de Transporte Pesado: Utilizada en los marcos de ventanas deslizantes para camiones de carga de alto tonelaje, buses interurbanos y vehículos todoterreno de uso industrial. Estanqueidad y Hermetismo Climático: Su diseño sella a presión los labios del perfil contra el vidrio, bloqueando de manera total el ingreso de agua de lluvia, ruidos de faena, ráfagas de viento y el polvo suspendido. Protección Antivibración: Actúa como un cojinete de seguridad perimetral que evita el contacto directo metal-cristal, previniendo que los vidrios se tricen o quiebren ante impactos bruscos al cerrar las ventanas. | R41: Usos y Aplicaciones Principales Guía para ventanas correderas residenciales y comerciales: Se coloca dentro de los rieles de aluminio o fierro para que los vidrios se deslicen de forma lineal, suave y silenciosa. Protección de cantos vivos y seguridad: Se instala a presión sobre los bordes cortantes de láminas de metal, planchas de acero o vidrios expuestos para evitar accidentes, cortes y raspaduras. Sector automotriz y maquinaria: Funciona como junta guía para las ventanas deslizantes de cabinas de grúas, furgones, cúpulas de camionetas y maquinaria agrícola ligera. Aislamiento y antivibración: Al mantener el panel firmemente abrazado por las paredes de la "U", absorbe las vibraciones ambientales provocadas por el viento o motores, eliminando los ruidos de tintineo. Sellado climático básico: Bloquea de manera eficiente el paso de corrientes de aire, polvo fino y filtraciones leves de agua hacia el interior.
H42: Beneficios Clave del Perfil Doble Canal o Ajuste de Precisión: Su matriz está diseñada para calzar firmemente en la pestaña metálica del marco por un lado, mientras que el canal opuesto recibe el borde del vidrio, asegurando que no se mueva de su eje. Amortiguación de Impactos: Al ser caucho de alta consistencia, absorbe los golpes bruscos al abrir o cerrar las ventanas correderas, previniendo trizaduras en los cristales. Alta Resistencia Mecánica: El compuesto de caucho SBR garantiza que los labios internos del perfil no se desgasten ni se rompan rápidamente debido al roce constante del vidrio al subir, bajar o deslizarse lateralmente. | J42: Características del Producto A diferencia de otros modelos que solo se venden en rollos cerrados de gran metraje, este perfil destaca por su flexibilidad comercial en el mercado chileno de elastómeros: Venta fraccionada: Está disponible para la compra por metro lineal en distribuidores especializados como Cruzeiro Gomas. Esto facilita reparaciones pequeñas o sustituciones rápidas sin necesidad de adquirir un rollo completo. Compuesto de Caucho SBR: Ofrece una excelente tolerancia ante la fricción mecánica constante producida al abrir y cerrar la ventana, impidiendo que el labio de goma se rompa o se deforme rápido.
A43: AJUSTES | B43: DESCRIPCIÓN | C43: AJUSTES ANTIRRUIDO | D43: AJUSTES CONTENEDOR | E43: AJUSTES MALETA | F43: AJUSTES PUERTA
B44: Los ajustes de goma (también conocidos en el mercado técnico como perfiles de ajuste o gomas tapajuntas) se utilizan principalmente para rellenar holguras, absorber tolerancias de fabricación y sellar uniones entre dos componentes estructurales. A diferencia de las correderas que guían piezas móviles, los ajustes son perfiles estáticos que se instalan a presión o mediante encastre para asegurar que no queden separaciones ni juego mecánico entre paneles, marcos o carrocerías. | C44: Los ajustes antirruido (también conocidos como perfiles antivibración o gomas insonorizantes) se utilizan principalmente para eliminar el crujido, mitigar el tintineo y absorber las vibraciones mecánicas en las uniones de estructuras metálicas, plásticas o de vidrio. A diferencia de un sello común, su diseño geométrico y densidad están optimizados para actuar como un colchón amortiguador continuo entre dos piezas rígidas que están sometidas a movimiento constante. | D44: Los ajustes contenedor son perfiles técnicos de goma (fabricados generalmente en caucho EPDM o SBR de alta dureza, típicamente 70 Shore-A) diseñados específicamente para sellar de forma hermética los perímetros de las compuertas y puertas de los contenedores marítimos o de carga (shipping containers). A diferencia de los ajustes vehiculares comunes, estos perfiles poseen una geometría robusta (muchas veces en forma de "J", "H" o con labios dobles de presión) pensada para resistir las brutales condiciones del transporte transoceánico y terrestre. | E44: El ajuste maleta (también conocido como perfil de maleta universal o burlete automotriz) es un perfil de goma híbrido diseñado específicamente para sellar herméticamente y amortiguar el cierre de las tapas de maleteros (maletas) de autos, camionetas, furgones y buses. Su estructura técnica cuenta con una base rígida en forma de "U" (que a menudo incluye un armado metálico o nervios internos para fijarse firmemente al canto de la lata) unida a un bulbo o "globo" de goma esponjosa lateral. Al cerrar la maleta del vehículo, esta sección esponjosa se deforma por compresión, garantizando un sello perfecto. | F44: Los ajustes de puerta (comúnmente denominados burletes, gomas de puerta o perfiles de estanqueidad) se utilizan principalmente para sellar herméticamente el perímetro de las puertas móviles, amortiguar los impactos al cerrar y aislar el interior de agentes externos. Dependiendo de si se aplican en el sector automotriz, residencial o industrial, su función varía entre la absorción de vibraciones y la mejora de la eficiencia térmica.
B45: Usos y Aplicaciones Principales Montaje de parabrisas y lunetas fijos: Actúan como el complemento de sellado perimetral en vehículos y maquinaria pesada, rellenando el espacio exacto entre el vidrio, la goma base y la lata de la cabina. Carrocerías y paneles industriales: Se insertan en las uniones de las planchas metálicas de buses, furgones o frentes de cabinas para ocultar las fijaciones (remaches o tornillos), otorgando una terminación estética y hermética. Construcción y tabiquería modular: Se aplican en las juntas de paneles divisorios, oficinas modulares y estructuras de aluminio para evitar el paso del aire y la luz entre las uniones de los módulos. Aislamiento acústico y antivibración: Al rellenar herméticamente los vacíos estructurales, impiden que las piezas choquen entre sí debido a las vibraciones del motor o del viento, eliminando ruidos molestos. Sellado contra la intemperie: Evitan que el agua de lluvia, el polvo fino de las faenas o la humedad se filtren hacia el interior de los habitáculos o tableros eléctricos. | C45: Usos y Aplicaciones Principales Cabinas de maquinaria pesada y agrícola: Se instalan en los puntos de contacto entre los paneles metálicos de la carrocería, puertas y marcos de tractores, grúas u horquillas para cortar la transmisión del ruido del motor hacia el interior. Carrocerías de buses y furgones: Se colocan de forma perimetral en las uniones de las planchas de revestimiento interior y cielo de los vehículos de transporte para eliminar los ruidos por torsión del chasis en ruta. Soportes de tableros eléctricos y ductos: Funcionan como aislante acústico en las bases o abrazaderas de sistemas de ventilación, climatización (HVAC) y cajas eléctricas, evitando que la vibración del equipo resuene en las paredes. Estructuras de aluminio y ventanales: Se introducen a presión en las holguras de portones pesados, mamparas o ventanas fijas para evitar el molesto golpeteo provocado por las ráfagas de viento. | D45: Usos y Aplicaciones Principales Puertas de Contenedores Marítimos e Industriales: Es su uso primordial. Se instalan en los bordes de las dos hojas de la puerta trasera de contenedores de 20 y 40 pies para garantizar un cierre totalmente hermético bajo presión de las barras de la falleba. Casas y Módulos Contenedores (Tiny Houses): En la arquitectura modular, se utilizan para sellar de manera estanca las uniones de ventanas, ampliaciones o los accesos de contenedores modificados para uso habitacional u oficinas. Furgones de Carga y Camiones Térmicos: Se aplican en los marcos de puertas traseras y laterales de camiones de reparto o ramplas refrigeradas para evitar la pérdida de frío o el ingreso de contaminantes. Bodegas Móviles y Shelter Tecnológicos: Sellado de compuertas en contenedores adaptados como salas eléctricas, generadores o bodegas de almacenamiento de materiales en faenas mineras y de construcción. | E45: Usos y Aplicaciones Principales Maleteros de Vehículos (Uso Primordial): Se instala en todo el contorno del marco metálico de la maleta de automóviles sedán, hatchback, SUV y camionetas. Evita que la tapa golpee fierro con fierro al cerrarse bruscamente. Capós y Compartimentos de Motores: Se aplica en el contorno del motor delantero para contener los ruidos mecánicos y aislar térmicamente la zona, impidiendo que los gases o el calor pasen hacia la cabina o la ventilación. Portalones Traseros y Quintas Puertas: Sello perimetral para las compuertas traseras de furgones de carga, ambulancias o vehículos comerciales. Estanqueidad contra Fluidos y Polvo: Su función crítica es impedir que el agua de lluvia, el agua del lavado a presión, el polvo de caminos de tierra o la polución ingresen al maletero, protegiendo el equipaje y la rueda de repuesto. Insonorización Acústica: Absorbe las vibraciones generadas por la torsión del chasis en movimiento y bloquea el paso de los ruidos del viento (siseo) a altas velocidades en carretera. | F45: Usos y Aplicaciones Principales Sector Automotriz y Transporte: Se instalan en el contorno del marco de las puertas de autos, camiones y buses. Su función es evitar que la puerta golpee directamente la carrocería, bloquear el ingreso de agua de lluvia o lavado, y aislar el ruido del viento a altas velocidades. Hogar y Construcción (Puertas Residenciales): Se colocan en los marcos de puertas de madera, aluminio o PVC para evitar las corrientes de aire (chiflonazos), mejorar el aislamiento acústico entre habitaciones y mantener la climatización (calefacción o aire acondicionado), optimizando el gasto energético. Cámaras Frigoríficas y Sector Gastronómico: Perfiles de gran envergadura que sellan herméticamente las puertas de refrigeradores industriales y salas frías, impidiendo la pérdida de temperatura crítica. Tableros Eléctricos y Maquinaria: Protegen los componentes internos de tableros de control o motores en faenas mineras e industriales, bloqueando por completo la entrada de polvo fino, tierra y humedad.
E46: Características del Material y Formatos Para asegurar una durabilidad extrema a la intemperie, este perfil técnico se fabrica con estándares industriales muy específicos: Compuesto de Caucho EPDM: La sección de ajuste y el bulbo esponjoso están hechos de EPDM. Este material destaca por su sobresaliente resistencia a la radiación UV, al ozono y a temperaturas extremas, evitando que la goma se reseque, se trice o se pegue con el tiempo. Formato de Venta: En el mercado nacional de elastómeros, empresas especializadas como la Tienda Cruzeiro Gomas comercializan este insumo bajo denominaciones como el Ajuste Maleta Universal PV10 CNA en rollos de 50 metros. No obstante, muchos distribuidores automotrices también lo venden fraccionado por metro lineal para reparaciones particulares. Instalación sin Adhesivos: Gracias a su alma de acero o nervios plásticos internos, el perfil se inserta a presión manualmente (o con la ayuda de un mazo de goma blanda) directamente sobre la pestaña metálica del vehículo, quedando fijo de inmediato sin necesidad de pegamentos.
A47: PLANCHA EVA | B47: PLANCHA EVA NEGRO | C47: PLANCHA EVA COLOR
B48: La plancha de EVA negra se utiliza principalmente para amortiguar impactos, aislar ruidos o vibraciones, proteger mercancías y confeccionar estructuras moldeadas. Al ser de color negro, es la preferida en sectores industriales, deportivos y de utilería pesada porque es altamente limpia frente al polvo, la grasa y el desgaste mecánico. | C48: La plancha de EVA de colores (Etileno Acetato de Vinilo) es un material blando, ligero, impermeable y altamente elástico que se utiliza principalmente en educación parvularia, manualidades escolares, diseño de calzado, confección de disfraces (cosplay) y amortiguación de zonas infantiles. A diferencia de la plancha negra (que es más industrial), las planchas de colores se fabrican con pigmentos brillantes, no tóxicos y lavables, ideales para proyectos visuales y recreativos.
B49: Usos y Aplicaciones Principales según su Rubro Logística y Embalaje Técnico (Casetas y Maletas): Se recorta a medida para crear el fondo o las "cunas" protectoras en maletines de herramientas, estuches de instrumentos musicales, cámaras fotográficas y componentes ópticos, evitando que los objetos se golpeen al ser trasladados. Construcción e Insonorización Acústica: Se coloca como una capa intermedia debajo de pisos flotantes, alfombras o tabiquería de yeso-cartón. Su estructura de celda cerrada absorbe eficazmente los ruidos de pisadas y las vibraciones mecánicas entre pisos. Deporte, Fitness y Zonas de Juego: Es la base estándar para colchonetas de gimnasio, zonas de yoga, tatamis de artes marciales y pisos amortiguadores para zonas de pesas de alto tráfico. Además de proteger el suelo base, previene lesiones en las articulaciones al entrenar. Talleres de Cosplay, Escenografía y Teatro: Es el material rey en las artes escénicas. Las planchas (especialmente las de alta densidad) son termoformables; al aplicarles calor con una pistola de aire, se pueden doblar y moldear de forma exacta para fabricar armaduras, cascos, escudos y réplicas de utilería ligera. Transporte y Revestimiento de Vehículos: Se instala en el suelo de tolvas, carros de arrastre o maleteros de furgones de reparto para amortiguar la carga, amortiguar el ruido del motor y evitar el deslizamiento de cajas. | C49: Usos y Aplicaciones Principales Manualidades Escolares y Cotillón: Es el material más popular en jardines infantiles y colegios para cortar letras, figuras, máscaras, sombreros de cumpleaños, maquetas y decoraciones de salas de clases. Cosplay y Diseño de Vestuario: Los creadores de disfraces utilizan las planchas de colores primarios o metálicos como base. Al ser un material termoformable (se moldea aplicando calor con una pistola de aire), permite dar forma exacta a armaduras, cascos, espadas y accesorios llamativos. Pisos de Goma Eva Interconectables (Tatamis): Se utiliza en formatos cuadrados con bordes tipo puzzle para cubrir el suelo de salas de juego infantiles, jardines y dormitorios. Su objetivo es amortiguar caídas de niños pequeños y aislar el frío del piso. Industria del Calzado: Planchas de colores pasteles o vivos se procesan para fabricar las plantillas, entresuelas y suelas de sandalias veraniegas, chalas de baño y calzado infantil por su ligereza. Publicidad y Merchandising: Fabricación de llaveros flotantes, mousepads, viseras promocionales y rompecabezas didácticos.
A50: CORREAS | B50: CORREAS PK | C50: CORREAS 3L | D50: CORREAS 3V | E50: CORREAS A | F50: CORREAS B | G50: CORREAS C
B51: Las correas PK (también llamadas correas Poly-V, acanaladas o serpentinas) se utilizan principalmente para transmitir potencia por fricción desde el cigüeñal de un motor hacia múltiples accesorios periféricos de forma simultánea.La letra "K" indica que cumple con la norma de perfil automotriz estándar, y el número que acompaña la sigla indica cuántas estrías o canales longitudinales tiene (por ejemplo, una correa 6PK tiene 6 canales). | C51: Las correas 3L son correas trapezoidales (en forma de "V") diseñadas específicamente para transmisiones de potencia fraccionada (FHP o Fractional Horsepower) y servicio liviano, operando generalmente en sistemas con motores de menos de 1 a 3 caballos de fuerza (HP). Dentro de la categoría de correas ligeras, la sección 3L es la más pequeña y delgada de los estándares industriales, destacando por su alta flexibilidad en poleas de diámetros muy reducidos. | D51: Las correas 3V son correas trapezoidales (en forma de "V") de cuña estrecha y alta capacidad, diseñadas bajo la norma americana para transmitir potencias de bajas a moderadas (hasta 25 HP) en espacios sumamente reducidos.A diferencia de las correas clásicas, su perfil es más alto en relación con su ancho. Esto distribuye mejor las tensiones internas y permite transmitir hasta un 30% más de potencia utilizando poleas considerablemente más pequeñas y distancias entre centros más cortas. | E51: Las correas tipo A (o sección A) son las correas trapezoidales en forma de "V" más utilizadas y universales del mercado industrial, agrícola y automotriz clásico. Pertenecen a la serie de correas clásicas y están diseñadas para transmisiones de potencia media (operando de forma óptima en motores de 1 a 10 HP). Su funcionamiento se basa en el efecto cuña: la correa se acopla a presión contra los costados laterales de la ranura de la polea, aumentando drásticamente la fricción y evitando deslizamientos sin necesidad de dientes | F51: Las correas tipo B (o sección B) son correas trapezoidales en forma de "V" de la serie clásica, diseñadas específicamente para transmisiones de potencia media a alta (operando de forma óptima en motores de 5 a 25 HP). Son considerablemente más anchas y robustas que las secciones clásicas menores (como la "Z" o la "A"), lo que les permite soportar torques más elevados y condiciones exigentes de trabajo continuo en la industria pesada, la construcción y el sector agrícola. Su funcionamiento se basa en el efecto cuña, acoplándose a presión contra las paredes laterales de la polea para transmitir la fuerza por fricción. | G51: Las correas tipo C (o sección C) son correas trapezoidales en forma de "V" pertenecientes a la serie clásica industrial. Están diseñadas específicamente para transmisiones de alta potencia y torque severo, operando de manera óptima en motores grandes que van desde los 15 hasta los 100 HP. Al ser componentes robustos de gran envergadura, se utilizan en aplicaciones de servicio pesado continuo donde las correas menores (como la A o la B) se romperían o patinarían de inmediato debido a la carga mecánica extrema. Su funcionamiento se basa en el efecto cuña, acoplándose fuertemente contra las paredes laterales de las poleas industriales.
B52: Usos y Aplicaciones Principales Sistemas de accesorios automotrices (Uso Primordial): Es la correa que conecta la polea principal del motor con componentes críticos del vehículo: - Alternador: Para generar la carga de la batería. - Bomba de dirección hidráulica: Para suavizar el movimiento del volante. - Compresor del aire acondicionado: Para enfriar el habitáculo. - Bomba de agua: (En algunos motores) para hacer circular el refrigerante. Maquinaria Industrial Compacta: Se aplica en motores eléctricos e industriales que requieren altas velocidades de rotación y poleas de diámetro pequeño, como en compresores de aire, ventiladores industriales y sistemas HVAC de edificios. Línea Blanca y Electrodomésticos: Muy utilizadas en los tambores de lavadoras y secadoras industriales o domésticas debido a su funcionamiento silencioso y alta eficiencia de transmisión. | C52: Usos y Aplicaciones Principales Al ser correas compactas que trabajan por fricción en engranajes de alta velocidad y distancias cortas entre centros, se usan habitualmente en: Línea blanca y electrodomésticos: Lavadoras domésticas (como las tradicionales de tipo "tanquecito"), secadoras de ropa y refrigeradores antiguos. Sistemas de climatización (HVAC): Ventiladores de escritorio, extractores de aire pequeños, sopladores residenciales y sistemas ligeros de calefacción. Herramientas de taller y garaje: Pequeñas mezcladoras de concreto portátiles, compresores de aire caseros de bajo flujo y taladros de pedestal de banco. Equipos de jardinería: Cortadoras de césped ligeras, sopladoras de hojas y motocultivadores pequeños. Maquinaria agrícola menor: Pequeñas máquinas de ordeño automáticas o molinos de grano de baja escala. | D52: Usos y Aplicaciones Principales Gracias a su diseño compacto de alta resistencia al aceite, calor y estática, se utilizan ampliamente en: Maquinaria Industrial de Alta Velocidad: Compresores de aire de pistón de tamaño medio, sistemas de ventilación comercial, extractores industriales y sopladores de aire. Equipos Agrícolas de Carga Moderada: Pequeños sistemas de trituración, motobombas de agua para riego, e implementos acoplados a motores diésel o eléctricos. Sistemas de Transmisión Múltiple: Cuando el espacio físico no permite instalar varias correas clásicas (como las tipo A o B), se utilizan juegos de correas 3V (simples o unidas en banda) para transferir un torque elevado sin riesgo de deslizamiento. Herramientas de Taller Industriales: Tornos mecánicos, sierras circulares de banco pesadas y taladros de pedestal de alta producción. | E52: Usos y Aplicaciones Principales Al ser el tamaño estándar más versátil y de mayor stock a nivel global, se encuentra masivamente en: Maquinaria Industrial Ligera y Mediana: Compresores de aire de pistón de taller, extractores e inyectores de aire industriales, ventiladores de refrigeración de gran escala y cintas transportadoras ligeras. Herramientas de Taller Eléctricas: Tornos mecánicos de banco, taladros de pedestal industriales, sierras circulares de mesa para madera y lijadoras de banda fijas. Sector Agrícola y Maquinaria de Campo: Pequeños molinos de granos, motobombas de agua para riego superficial, picadoras de forraje y sistemas auxiliares acoplados a tractores. Automotriz Clásico y Pesado: En vehículos antiguos, camiones o maquinaria pesada, se utiliza para mover componentes individuales como el alternador, la bomba de agua o el ventilador del radiador (previo a la popularización masiva de las correas planas PK) | F52: Usos y Aplicaciones Principales Al ser uno de los perfiles industriales más masivos y con mayor resistencia estructural al estiramiento, se encuentra habitualmente en: Maquinaria de Construcción: Es la correa estándar por excelencia para mover los tambores de las betoneras u hormigoneras, así como en vibrocompactadores y cortadoras de pavimento de gran escala. Sistemas de Ventilación e Industrial Pesado: Extractores e inyectores de aire industriales (sistemas HVAC de edificios), sopladores de gran envergadura y torres de refrigeración. Herramientas y Maquinaria de Taller: Compresores de aire de pistón industriales de alta presión (tanques de 200 a 500 litros), tornos mecánicos pesados y grandes sierras circulares para maderas o metales. Sector Agrícola: Cosechadoras, trituradoras de forraje, molinos de grano industriales y motobombas de agua de alto caudal acopladas a motores diésel o eléctricos. Transmisión por Fajas Múltiples: En aplicaciones donde un solo motor supera los 20 HP, se instalan juegos de 2, 3 o más correas tipo B en paralelo sobre poleas multicanal para repartir la carga sin que ninguna patine. | G52: Usos y Aplicaciones Principales Su alta resistencia estructural, reforzada con miembros de tracción internos de poliéster preestirado, la posiciona masivamente en maquinaria de gran tamaño: Industria Minera y Canteras: Es la correa estándar para mover chancadoras o trituradoras de mandíbula, molinos de bolas y grandes poleas motrices en cintas transportadoras que movilizan toneladas de mineral bruto. Maquinaria Agrícola de Gran Escala: Se instala en los sistemas de trilla y picado de cosechadoras combinadas, tractores de alta potencia y molinos de grano industriales. Sistemas del Rubro Maderero y Construcción: Motores principales de sierras de cinta para troncos gigantes, cepilladoras industriales y mezcladoras de hormigón estacionarias de alta capacidad. Sistemas de Ventilación Extrema: Extractores de aire de gran envergadura en minas subterráneas, inyectores de aire para túneles y grandes torres de enfriamiento industriales. Transmisión por Fajas Múltiples: En motores industriales de alto caballaje (sobre 50 HP), es indispensable montar juegos emparejados de 3, 4 o más correas tipo C en paralelo sobre poleas multicanal para transferir el torque total sin pérdidas de revoluciones.
A53: MANGUERAS | B53: MANGUERA ACRILO NITRILO CON TELA | C53: MANGUERA ACRILO NITRILO SIN TELA | D53: MANG. AGUA CALIENTE CALEFACCION | E53: MANGUERA PVC
B54: La manguera de acrilonitrilo con tela (comúnmente conocida como manguera de caucho nitrilo, NBR o de alta presión reforzada) se utiliza principalmente para la conducción, descarga y transferencia de petróleo, combustibles, aceites y fluidos industriales bajo condiciones de presión moderada a alta. El acrilonitrilo (NBR) proporciona una resistencia química excepcional frente a los hidrocarburos (evitando que la goma se ablande o degrade), mientras que la malla de tela interna (refuerzo textil de alta tenacidad) le otorga estabilidad estructural, evita que la manguera se deforme y le permite soportar altas presiones de trabajo y picos de sobrecarga sin reventar. | C54: La manguera de acrilonitrilo sin tela (también conocida como manguera de nitrilo puro, NBR mono-capa o tubo de acrilonitrilo) se utiliza principalmente para la conducción por gravedad, vacío o muy baja presión de combustibles, aceites, grasas e hidrocarburos líquidos. Al carecer de un refuerzo textil interno (malla de tela), esta manguera es sumamente flexible, económica y fácil de manipular, pero tiene una resistencia mecánica limitada. Por esta razón, su uso está estrictamente restringido a sistemas donde el fluido corre libremente sin acumulaciones de presión interna, ya que una presión superior a 15 o 30 PSI (según el espesor de la pared) la expandiría hasta reventarla. | D54: La manguera para agua caliente y calefacción es un conducto flexible diseñado específicamente para transportar fluidos a temperaturas elevadas (habitualmente entre -40°C y +125°C) de forma continua, sin perder rigidez, deformarse ni sufrir agrietamientos. En el mercado industrial y automotriz, estas mangueras están fabricadas de caucho EPDM (Etileno Propileno Dieno) y cuentan con un refuerzo interno de malla textil trenzada de alta tenacidad. Este diseño les permite soportar tanto el calor extremo como las presiones moderadas del sistema (generalmente hasta 75 o 150 PSI) sin riesgo de reventar. | E54: La manguera de PVC (Cloruro de Polivinilo) se utiliza principalmente para la conducción, succión, descarga y distribución de agua, aire, fluidos alimenticios y productos químicos ligeros en los sectores agrícola, industrial, de construcción y doméstico. Es uno de los insumos más populares del mercado debido a su excelente relación precio-calidad, ligereza, flexibilidad y la capacidad de fabricarse en formatos transparentes que permiten monitorear visualmente el flujo interno.
B55: Usos y Aplicaciones Principales Sistemas de Combustible y Automoción: Conducción de gasolina, petróleo diésel y biodiésel en líneas de alimentación y retorno para camiones, buses, maquinaria agrícola y motores marinos. Circuitos Hidráulicos de Baja y Media Presión: Utilizada como línea de retorno de aceite hidráulico, sistemas de dirección asistida y líneas de lubricación industrial donde se requiere flexibilidad y resistencia al aceite caliente. Transferencia y Carga de Combustible: Abastecimiento en faenas mineras o de construcción mediante bombas de traspaso desde estanques estacionarios hacia vehículos pesados. Líneas de Aire Comprimido con Neblina de Aceite: Ideal para herramientas neumáticas industriales de gran envergadura. Las mangueras estándar se deshacen por dentro debido al aceite lubricante del compresor, pero el acrilonitrilo resiste este ataque de forma continua. Control de Incendios e Industria Pesada (Formatos Planos / Ribeteados): Ciertas mangueras de nitrilo de tres capas con refuerzo textil circular se usan en brigadas contra incendios y refinerías debido a su alta resistencia al arrastre, al roce severo y al contacto con químicos | C55: Usos y Aplicaciones Principales Líneas de Retorno de Combustible: Conductos que devuelven el excedente de diésel o gasolina desde los inyectores o el carburador hacia el estanque en motores convencionales y maquinaria ligera. Sistemas de Vacío y Ventilación: Mangueras de avance de vacío en distribuidores automotrices, conductos de ventilación del cárter (válvula PCV) y recirculación de gases cargados con neblina de aceite. Líneas de Purga y Desagüe: Conductos para drenar filtros de combustible (trampas de agua), fondos de estanques o cubetas de carburadores. Traspaso de Hidrocarburos por Gravedad: Sifonaje o llenado de pequeños estanques (para motos, cortadoras de césped o generadores portátiles) donde el combustible baja únicamente por su propio peso. Maquinaria de Dosificación y Laboratorio: Conducción de aceites lubricantes en sistemas de engrase automatizado gota a gota que operan a presiones insignificantes. | D55: Usos y Aplicaciones Principales Sistemas de Calefacción Automotriz: Conexión del bloque del motor hacia el radiador de la calefacción ubicado al interior del tablero de autos, camiones y buses. Transporta el refrigerante caliente para climatizar la cabina. Circuitos de Refrigeración de Motores: Conducción de agua combinada con aditivos anticongelantes (etilenglicol) hacia el radiador principal en maquinaria agrícola, minera e industrial pesada. Conexiones de Calderas y Calefonts (Línea Sanitaria): En formatos residenciales o comerciales, se emplean para enlazar la salida de agua caliente de los calentadores hacia la red de distribución interna de la edificación. Limpieza Industrial con Agua Caliente: Conducción de agua a elevadas temperaturas para labores de lavado y sanitización en plantas procesadoras de alimentos, lecherías y laboratorios. Intercambiadores de Calor: Transporte de fluidos térmicos en sistemas de climatización centralizada o climatización HVAC en edificios y complejos industriales. | E55: Clasificación de Mangueras de PVC según su Uso Específico Riego y Jardinería (Uso Doméstico y Agrícola Ligero): Son las mangueras tradicionales de color verde o amarillo. Cuentan con un trenzado de hilo de poliéster intermedio que les permite soportar la presión del agua de red doméstica (hasta 90 PSI) para regar patios, huertos y lavar vehículos sin deformarse. Succión y Descarga Industrial (Mangueras Espiraladas): Poseen un resorte helicoidal rígido de PVC (espiral) incrustado en su estructura. Este refuerzo evita que la manguera se chupe, colapse o se estrangule cuando se genera vacío. Se usan para succionar agua con barro, arena o piedras desde pozos, piscinas, canales o inundaciones mediante motobombas. Conducción Alimentaria (PVC Atóxico / Grado Alimento): Cumplen con estrictas certificaciones sanitarias (FDA). Son totalmente transparentes, inodoras e insípidas. Se emplean en la industria cervecera, plantas lecheras, embotelladoras de jugos y transporte de agua potable. Evacuación de Grandes Caudales (Manguera Plana o Layflat): Son mangueras colapsables de alta resistencia que se enrollan de forma plana cuando no transportan fluido. Son el estándar para la salida de agua de bombas de pozo profundo, riego por goteo agrícola masivo y faenas mineras. Medición y Dosificación por Gravedad (PVC Cristal Monocapa): Tubos delgados de PVC 100% transparentes sin mallas internas. Se usan en la construcción como mangueras de nivel (para nivelar pisos y muros usando agua), en acuarios, laboratorios y purgas de fluidos sin presión.
B56: Estructura de Tres Capas (Tricapa) Tubo Interior (Acrilonitrilo / NBR): Capa completamente lisa en contacto directo con el fluido. Es 100% impermeable a los hidrocarburos y aceites. Refuerzo Intermedio (Malla de Tela): Trenzado de hilos sintéticos de alta resistencia (como poliéster, nylon o poliamida) embutido de forma compacta para tolerar la presión. Cubierta Exterior (Goma Sintética con impresión de tela): Capa exterior rugosa o con textura de lona diseñada para resistir el arrastre por el suelo, la abrasión, el ozono, la intemperie y salpicaduras de agentes químicos. | C56: Ventajas y Características Clave Flexibilidad Superior: Permite realizar curvas extremadamente cerradas y dobleces en espacios de motor muy reducidos sin estrangularse ni colapsar. Resistencia Química Homogénea: Toda la manguera es de acrilonitrilo puro. Si el exterior entra en contacto con aceite o grasa del motor, no se degradará (a diferencia de las mangueras con tela, cuya cubierta exterior a veces es de caucho SBR común). Facilidad de Conexión: Se expande ligeramente de forma manual, lo que permite introducirla a presión en espigos o niples metálicos de forma rápida. | D56: Características de su Construcción Técnica Para operar de forma segura bajo condiciones térmicas severas, estas mangueras constan de una estructura de tres capas perfectamente integrada: Tubo Interior (Caucho EPDM puro): Es completamente liso para asegurar un flujo constante. Es altamente resistente al agua hirviendo, al vapor, al ozono y a los aditivos químicos anticorrosivos del refrigerante. Refuerzo Central (Malla de Fibra Sintética): Un trenzado de hilos de poliéster, nylon o aramida embutido en el hule que le otorga la resistencia estructural necesaria para manejar las presiones internas y evitar que la manguera se chupe o colapse. Cubierta Exterior (Caucho EPDM reforzado): Diseñada para soportar las condiciones climáticas del exterior, la radiación UV del sol, el envejecimiento por calor bajo el capó de un motor y los roces mecánicos accidentales. | E56: Restricciones Críticas de Uso No apta para Agua Caliente: El PVC es un termoplástico; se ablanda drásticamente sobre los 50°C a 60°C. Usarla con agua hirviendo o vapor destruirá la manguera y provocará roturas por presión de forma inmediata. Sensibilidad al Frío Extremo: En climas helados (cercanos a 0°C o menos), el PVC tiende a rigidizarse y volverse quebradizo si se manipula con brusquedad.
A57: ADHESIVOS | B57: ADHESIVO GOBUSA
B58: El adhesivo de contacto Gobusa se utiliza principalmente en la industria, construcción y talleres técnicos para lograr uniones fuertes, elásticas y permanentes entre materiales flexibles y rígidos. Al ser un pegamento elastomérico de base solvente, destaca por su adherencia instantánea por contacto (doble contacto) y su gran resistencia a la humedad. Una de sus mayores ventajas técnicas en el mercado chileno es su fórmula segura: no contiene solventes prohibidos ni altamente tóxicos como tolueno, benceno o compuestos clorados, lo que facilita su aplicación segura en interiores ventilados.
B59: Usos y Aplicaciones Principales Instalación de Revestimientos y Pisos: Es el estándar para fijar rollos de goma, pisos de caucho, vinilos, alfombras y palmetas de pasto sintético sobre bases de concreto o madera. Industria del Caucho y Goma: Se emplea masivamente para pegar planchas de goma (como EVA, neopreno o SBR) y perfiles técnicos en canales metálicos. Tapicería y Automoción: Ideal para el pegado de espumas, telas, cueros y revestimientos internos en la restauración de asientos de vehículos, techos de cabinas y paneles de puertas. Mueblería y Carpintería: Utilizado para el laminado de Formalita (laminados plásticos) sobre tableros de madera, MDF o aglomerados. Calzado y Marroquinería: Reparación y armado de calzado mediante la unión firme de suelas de goma con cuero o materiales sintéticos.
B60: Especificaciones Técnicas y Rendimiento Rendimiento: Rinde aproximadamente entre 4 y 5 metros cuadrados por litro por capa. Tiempo de secado para contacto: Requiere dejar evaporar los solventes entre 15 y 30 minutos antes de unir las piezas.Temperatura de trabajo: Se recomienda aplicar en ambientes entre 10°C y 35°C. Propiedades de la unión: Mantiene una excelente flexibilidad, lo que evita que el pegamento se cristalice o se quiebre en materiales sometidos a movimiento continuo o flexión.
A61: RODON MACIZO ACRILO NITRILO | B61: DESCRIPCIÓN | C61: USOS Y APLICACIONES PRINCIPALES | D61: ESPECIFICACIONES TÉCNICAS CLAVE
B62: El rodón macizo de acrilonitrilo (también conocido como cordón tórico de NBR, hule nitrilo compacto o cuerda Buna-N) se utiliza principalmente para la confección de juntas tóricas (O-Rings) a medida y cierres herméticos de alta presión en sistemas que están en contacto directo con aceites, grasas y derivados del petróleo. A diferencia de las versiones esponjosas, al ser un material macizo o compacto (con una dureza estándar de 70 Shore-A), ofrece una nula porosidad y una alta resistencia mecánica. Esto le permite soportar torques de apriete elevados, presiones severas y uso dinámico sin deformarse ni permitir filtraciones. | C62: Fabricación de O-Rings Gigantes o Especiales: Es su uso primordial en maestranzas y talleres. Permite cortar el cordón a la longitud exacta necesaria para sellar bridas o uniones mecánicas de gran diámetro, uniendo los dos extremos con un adhesivo instantáneo de cianoacrilato de alta resistencia. Sistemas Hidráulicos y Neumáticos: Actúa como sello estático y dinámico en cilindros, bloques de válvulas, pistones y bombas hidráulicas que operan con aceites minerales e hidrocarburos. Cierres Herméticos de Depósitos y Tapas: Sellado perimetral en tapas de tanques de combustibles, contenedores de lubricantes, depósitos industriales o agitadores donde el apriete de los pernos es muy fuerte. Transformadores Eléctricos: Se emplea ampliamente en el sector energético para sellar las juntas de los transformadores que contienen aceite dieléctrico, evitando fugas y la contaminación del fluido. Sector Automotriz y Motores: Juntas e insertos para tapas de válvulas, filtros de aceite, bombas de agua y carcasas de transmisión que trabajen a temperaturas moderadas. | D62: Resistencia Química Sobresaliente: Su formulación es químicamente impermeable frente a combustibles (diésel, kerosene), aceites minerales, grasas animales/vegetales y fluidos hidráulicos. Evita que la goma se ablande, se disuelva o pierda su elasticidad. Rango Térmico de Operación: Soporta de forma continua temperaturas que van desde los -30°C hasta los +90°C (algunos compuestos de alta gama toleran picos de hasta 120°C). Baja Permeabilidad: Excelente retención ante el escape de gases y aire cargado con neblinas de aceite.
A63: REGATONES | B63: DESCRIPCIÓN | C63: USOS Y APLICACIONES PRINCIPALES | D63: TIPOS DE AJUSTE O FIJACIÓN
B64: Los regatones son piezas protectoras que se colocan en los extremos inferiores de las patas de muebles, perfiles metálicos, herramientas o equipos de asistencia médica. Su función principal es evitar rayones en el piso, absorber impactos, aislar el ruido del arrastre y proporcionar una base antideslizante o facilitar el deslizamiento según el material del que estén hechos. Además de proteger la superficie del suelo (cerámica, madera o flotante), actúan como un tapón estanco que impide la entrada de humedad, polvo o basura al interior de los tubos metálicos | C64: Regatones de Goma o Caucho (Uso Antideslizante y de Seguridad) Están fabricados con elastómeros de alta consistencia que ofrecen un gran coeficiente de fricción. Muebles pesados y tránsito: Ideal para sillas de colegios, mesas de restaurantes y camas, evitando que el mobiliario se mueva involuntariamente al usarse. Línea Médica (Tipo Muleta o Barril): Modelos reforzados que se instalan en las puntas de bastones, muletas, andadores y sillas de ruedas. Su diseño engomado garantiza el agarre al suelo para prevenir caídas de pacientes. Maquinaria Industrial: Bases de apoyo elásticas que amortiguan las microvibraciones de motores ligeros o mesas de trabajo de talleres. | D64: Regatón Exterior (Tipo Capuchón): Se abraza firmemente por fuera de la pata o tubo cilíndrico. Es el más común para patas delgadas de metal o madera. Regatón Interior (Tipo Tapón con Aletas): Cuenta con nervaduras plásticas laterales. Se introduce a presión (a golpes suaves con un mazo de goma) dentro de perfiles tubulares cuadrados, rectangulares o redondos, quedando al ras de la estructura metálica.
A65: RODON MACIZO SBR | B65: DESCRIPCIÓN | C65: USOS Y APLICACIONES PRINCIPALES
B66: El rodón macizo de SBR (o cordón de goma compacto de sección redonda) se utiliza principalmente como sello estático de alta presión, tope de amortiguación mecánica y empaquetadura elástica en uniones fijas que no están expuestas a aceites ni combustibles. Al ser un material macizo o compacto (con una dureza estándar de 70 Shore-A), carece de burbujas de aire internas. Esto le otorga una alta resistencia al aplastamiento, gran firmeza estructural y la capacidad de soportar fuertes torques de apriete sin deformarse ni perder su capacidad de sellado. | C66: Fabricación de empaquetaduras y O'Rings a medida: Se utiliza en talleres mecánicos e industriales para confeccionar anillos de sellado de gran diámetro para bridas, tapas de estanques de agua o ductos de ventilación. Se corta a la longitud exacta y se une con adhesivo instantáneo. Cierres herméticos de compuertas pesadas: Actúa como junta de estanqueidad en compuertas de descarga de silos, tolvas de áridos, mezcladoras de hormigón y portones industriales que ejercen un fuerte cierre por pernos o palancas. Topes e insertos antivibración: Funciona como barra o pasador amortiguador en uniones mecánicas, bases de maquinaria pesada y soportes estructurales para disipar ráfagas de vibración y evitar el choque directo metal-metal. Juntas de dilatación pesadas en construcción: Se inserta a presión como cordón de relleno estructural en juntas de expansión profundas de pisos industriales de concreto antes de aplicar el sellador elastomérico final.

Sheet Hoja2
A1: SKU | B1: Nombre Web | C1: Descripción Corta | D1: Precio (CLP) | E1: Categoría | F1: Subcategoría | G1: Atributos | H1: URL Imagen
A2: I313120A | B2: Contenedor de Basura Azul Tapa y Ruedas 120 litros 46 cm x 55 cm x 96 cm | C2: Contenedor de basura azul fabricado en HDPE estabilizado ultravioleta con tapa abatible con bisagras para fácil uso. Incorpora dos ruedas de goma de 200mm para movilidad eficiente. Diseño de una sola pieza que facilita la limpieza y manejo | D2: 28990 | E2: Aseo | F2: Basureros y papeleros | H2: https://cruzeirogomas.cl/wp-content/uploads/2025/01/15281519_I313120A_1_Contenedor_de_Basura_120_lts__2_ruedas_Azul-1.jpg
A3: I307CONO700 | B3: Conos de Seguridad Vial 70 cm Naranjo con Doble Banda Reflectante PVC | C3: Conos de seguridad vial con doble banda reflectante fabricados de PVC-polivinil flexible lo que hace que no decolore prematuramente. Posee dos collares reflectantes para que su uso sea tanto de día como de noche | D3: 9149 | E3: Seguridad Vial | F3: Conos | H3: https://cruzeirogomas.cl/wp-content/uploads/2025/01/15381369_I307CONO700_2-1.jpg
A4: I3071207587 | B4: Tope de Estacionamiento Ind. delimitado carga pesada 120mm x 75mm x 87mm | C4: Su construcción robusta y dimensiones optimizadas garantizan resistencia extrema a impactos de vehículos pesados, con 2 perforaciones de anclaje para fijación segura en zonas de alta exigencia logística | D4: 9198 | E4: Seguridad Vial | F4: Lomos de toro y rampas | H4: https://cruzeirogomas.cl/wp-content/uploads/2025/01/15381399_tope_muelle-1.png
A5: I307PC4210 | B5: Protector 5 Cables 1 7/8" 10 Toneladas 900 mm x 500 mm x 55 mm con Unión | C5: Cinco canales internos que garantizan protección óptima y organización del cableado múltiple de gran calibre | D5: 70781 | E5: Seguridad Vial | F5: Estacionamiento | H5: https://cruzeirogomas.cl/wp-content/uploads/2025/01/15381414_I307PC4210_1_protector_5_cables_1_78_10ton__900x500x55mm_cunion-1.jpg
A6: I275CLIP11P-15 | B6: Piso de PVC Rollo Clips Plata 1,2 mm Espesor x 1 m Ancho x 15 m | C6: Piso PVC Clips color plata, antideslizante y resistente, ideal para proteger superficies en pasillos, escaleras y áreas de tránsito frecuente, brindando seguridad y durabilidad. | D6: 135141 | E6: Pisos | F6: Pisos de PVC | H6: https://cruzeirogomas.cl/wp-content/uploads/2025/01/16064234_I275CLIP21G-PISO_R_PVC_CLIPS_1_2_MMS_X_2_MTS_GRIS_ROLLO_25_MTS-1.jpg
A7: I313240A | B7: Basurero Azul Tapa y Ruedas 240 litros 56 cm x 70 cm x 101 cm | C7: Basurero azul de 240 litros fabricado en HDPE estabilizado ultravioleta con tapa abatible con bisagras para fácil uso. Incorpora dos ruedas de goma de 200mm para movilidad eficiente. Diseño de una sola pieza que facilita la limpieza y manejo | D7: 48453 | E7: Aseo | F7: Basureros y papeleros | H7: https://cruzeirogomas.cl/wp-content/uploads/2025/01/16069620_I313120A_1_Contenedor_de_Basura_120_lts__2_ruedas_Azul-1.jpg
A8: I313240G | B8: Basurero Gris Tapa y Ruedas 240 litros 56 cm x 70 cm x 101 cm | C8: Basurero gris de 240 litros fabricado en HDPE estabilizado ultravioleta con tapa abatible con bisagras para fácil uso | D8: 48453 | E8: Aseo | F8: Basureros y papeleros | H8: https://cruzeirogomas.cl/wp-content/uploads/2025/01/16069865_I313120G-2.jpg
A9: I272PASA2050 | B9: Piso Pastelón Caucho 20 mm x 50 cm x 50 cm Azul | C9: Baldosa de caucho pastelón antideslizante, ideal para áreas de juegos, gimnasios y espacios deportivos que requieren máxima absorción de impactos y seguridad | D9: 5990 | E9: Pisos | F9: Pastelones | H9: https://cruzeirogomas.cl/wp-content/uploads/2025/01/4.png
A10: I272PASV2050 | B10: Piso Pastelón Caucho 20 mm x 50 cm x 50 cm Verde | C10: Baldosa de caucho pastelón antideslizante, ideal para áreas de juegos, gimnasios y espacios deportivos que requieren máxima absorción de impactos y seguridad | D10: 5990 | E10: Pisos | F10: Pastelones | H10: https://cruzeirogomas.cl/wp-content/uploads/2025/01/7-2.png
A11: I272PASG2050 | B11: Piso Pastelón Caucho 20 mm x 50 cm x 50 cm Gris | C11: Baldosa de caucho pastelón antideslizante, ideal para áreas de juegos, gimnasios y espacios deportivos que requieren máxima absorción de impactos y seguridad | D11: 5990 | E11: Pisos | F11: Pastelones | H11: https://cruzeirogomas.cl/wp-content/uploads/2025/01/10-2.png
A12: I272PASN2050 | B12: Piso Pastelón Caucho 20 mm x 50 cm x 50 cm Negro | C12: Baldosa de caucho pastelón antideslizante, ideal para áreas de juegos, gimnasios y espacios deportivos que requieren máxima absorción de impactos y seguridad | D12: 5990 | E12: Pisos | F12: Pastelones | H12: https://cruzeirogomas.cl/wp-content/uploads/2025/01/2-3.png
A13: I274FELP004-12 | B13: Piso PVC Rollo Tipo Nomad Gris 12 mm Espesor x 1,20 m Ancho x 12 m | C13: Limpiapiés Nomad de vinilo continuo, atrapa suciedad y facilita limpieza. Ideal para entradas, fácil instalación. | D13: 169332 | E13: Pisos | F13: Pisos de PVC | H13: https://cruzeirogomas.cl/wp-content/uploads/2025/01/16094196_I274FELP004_1_Alfombra_limpiapie_pvc_nomad_1_20_mts_ancho__12mm_espesor_gris-1.jpg
... A68: I228158089CA | B68: Grada Estriada Negro Amarillo 4 mm x 300 mm x 1500 mm | C68: Grada estriada fabricada en caucho natural/SBR con diseño bicolor para máxima seguridad en escalones | D68: 14200 | E68: Pisos | F68: Gradas | H68: https://cruzeirogomas.cl/wp-content/uploads/2025/01/I228158559CA.jpg
A69: I228AL127523 | B69: Ángulo Grada Antideslizante Plateado 23 mm x 75 mm x 1200 mm | C69: Ángulo de grada antideslizante en PVC y aluminio, resistente a humedad y químicos. Ideal para escaleras en edificios y espacios públicos. | D69: 24600 | E69: Pisos | H69: https://cruzeirogomas.cl/wp-content/uploads/2025/01/16143433_I228AL127523W-1.jpg
A70: I220EVA20RA | B70: Piso Plancha Eva Tatami 20X1000X1000Mm Azul/Rojo C/Ensamble | C70: Material EVA Etil-Vinil-AcetatoAlta resistencia al impacto y baja relación de transformación por compresiónEspesor 20 mmMedidas 1.0 x 1.0 metrosColor Azul/Roja Fácil para la limpieza y el mantenimiento Vida útil de largo plazoAntideslizante, Resistencia de choque, Resistencia de abrasión, Protege de CaídasAntiestático, Impermeable a prueba del agua | D70: 10612 | E70: Decohaus | F70: Piso plancha | H70: https://cruzeirogomas.cl/wp-content/uploads/2025/01/16143676_I220EVA20RA-1_PISO_PLANCHA_EVA_TATAMI_20X1000X1000MM_AZUL_ROJO_CENSAMBLE-1.jpeg
A71: I219EVA8153N | B71: Piso Plancha Eva Negra 8 mm 1500 mm 3000 mm | C71: Plancha lisa de baja densidad con excelente resistencia a la deformación, que ofrece aislación térmica, acústica y protección contra humedad. Fácil de cortar y pegar, ideal para construcción como aislante en muros y pisos; lavable, no tóxico, inodoro y reciclable con baja absorción de agua | D71: 29202 | E71: Pisos | F71: Piso plancha | H71: https://cruzeirogomas.cl/wp-content/uploads/2025/01/plancha_de_goma_202603181130.webp
A72: I219EVA15153N | B72: Piso Plancha Eva Negra 15 mm 1500 mm 3000 mm | C72: Excelente resistencia a deformación de baja densidadCon una muy buena aislación térmica, sonora y humedad. | D72: 81054 | E72: Pisos | F72: Piso plancha | H72: https://cruzeirogomas.cl/wp-content/uploads/2025/01/D_NQ_NP_864579-MLC52907408807_122022-O.webp
A73: I219EVA12153N | B73: Piso Plancha Eva 12Xx1500X3000Mm Negra | C73: Formato Plancha, liso.Excelente resistencia a deformación de baja densidadCon una muy buena aislación térmica, sonora y humedad.Muy fácil de cortar por medio de cuchillo, tijera, sistema láser.Fácil de pegar con adhesivos en base a Neopreno y Poliuretano.En el área Construcción es muy utilizado como aislante térmico en muros y como aislante acústic | D73: 38181 | E73: Pisos | F73: Piso plancha | H73: https://cruzeirogomas.cl/wp-content/uploads/2025/01/plancha_de_goma_202603181130.webp
A74: I219EVA20153N | B74: Piso Plancha Eva Negra 20 mm 1500 mm 3000 mm | C74: Con una muy buena aislación térmica, sonora y humedad. Muy fácil de cortar por medio de cuchillo, tijera, sistema láser. Fácil de pegar con adhesivos en base a Neopreno y Poliuretano. | D74: 104617 | E74: Pisos | F74: Piso plancha | H74: https://cruzeirogomas.cl/wp-content/uploads/2025/01/plancha_de_goma_202603181130.webp
A75: I342E1050C-50 | B75: Esponja Cna 10 X 50Mm Rollo 50 Mts | C75: Perfil de goma esponja dimensionada de caucho en compuesto EPDM. Excelente resistencia al agua, vapor, al ozono. Aplicaciones: Uso general para evitar el contacto entre materiales como vidrio-metal, u otros. Características: Compuesto: Etileno Propileno (EPDM)Espesor: 10 mmAncho: 50 mmColor: NegroDureza (Shore A): 15 +/- 5Densidad: 1,45 gr/ccResis | D75: 141367 | E75: Perfiles de goma | F75: Esponjas | H75: https://cruzeirogomas.cl/wp-content/uploads/2025/01/16144005_I342E1050C-3.jpg
A76: I342E2525C-50 | B76: Esponja Cna 25 X 25Mm Rollo 50 Mts | C76: Perfil de goma esponja dimensionada de caucho en compuesto EPDM. Excelente resistencia al agua, vapor, al ozono. Aplicaciones: Uso general para evitar el contacto entre materiales como vidrio-metal, u otros. Características: Compuesto: Etileno Propileno (EPDM)Espesor: 25 mmAncho: 25 mmColor: NegroDureza (Shore A): 15 +/- 5Densidad: 1,45 gr/ccResis | D76: 176645 | E76: Perfiles de goma | F76: Esponjas | H76: https://cruzeirogomas.cl/wp-content/uploads/2025/01/16144030_I342E1050C-3.jpg
A77: I342E0550C-50 | B77: Esponja Cna 5 X 50Mm Rollo 50 Mts | C77: Perfil de goma esponja dimensionada de caucho en compuesto EPDM. Excelente resistencia al agua, vapor, al ozono. Aplicaciones: Uso general para evitar el contacto entre materiales como vidrio-metal, u otros. Características: Compuesto: Etileno Propileno (EPDM)Espesor: 5 mmAncho: 50 mmColor: NegroDureza (Shore A): 15 +/- 5Densidad: 1,45 gr/ccResist | D77: 88322 | E77: Perfiles de goma | F77: Esponjas | H77: https://cruzeirogomas.cl/wp-content/uploads/2025/01/16154205_I342E1050C-3.jpg
A78: I342E2025C-50 | B78: Esponja Cna 20 X 25Mm Rollo 50 Mts | C78: Perfil de goma esponja dimensionada de caucho en compuesto EPDM. Excelente resistencia al agua, vapor, al ozono. Aplicaciones: Uso general para evitar el contacto entre materiales como vidrio-metal, u otros. Características: Compuesto: Etileno Propileno (EPDM)Espesor: 20 mmAncho: 25 mmColor: NegroDureza (Shore A): 15 +/- 5Densidad: 1,45 gr/ccResis | D78: 141367 | E78: Perfiles de goma | F78: Esponjas | H78: https://cruzeirogomas.cl/wp-content/uploads/2025/01/16154799_I342E1050C-3.jpg
A79: I342E1020C-50 | B79: Esponja Cna 10 X 20Mm Rollo 50 Mts | C79: Perfil de goma esponja dimensionada de caucho en compuesto EPDM. Excelente resistencia al agua, vapor, al ozono. Aplicaciones: Uso general para evitar el contacto entre materiales como vidrio-metal, u otros. Características: Compuesto: Etileno Propileno (EPDM)Espesor: 10 mmAncho: 20 mmColor: NegroDureza (Shore A): 15 +/- 5Densidad: 1,45 gr/ccResis | D79: 58967 | E79: Perfiles de goma | F79: Esponjas | H79: https://cruzeirogomas.cl/wp-content/uploads/2025/01/16154894_I342E1050C-3.jpg
A80: I342E2030C-50 | B80: Esponja Cna 20 X 30Mm Rollo 50 Mts | C80: Perfil de goma esponja dimensionada de caucho en compuesto EPDM. Excelente resistencia al agua, vapor, al ozono. Aplicaciones: Uso general para evitar el contacto entre materiales como vidrio-metal, u otros. Características: Compuesto: Etileno Propileno (EPDM)Espesor: 20 mmAncho: 30 mmColor: NegroDureza (Shore A): 15 +/- 5Densidad: 1,45 gr/ccResis | D80: 197245 | E80: Perfiles de goma | F80: Esponjas | H80: https://cruzeirogomas.cl/wp-content/uploads/2025/01/16156262_I342E1050C-3.jpg
A81: I342E10100C-25 | B81: Esponja Cna 10 X 100Mm Rollo 25 Mts | C81: Perfil de goma esponja dimensionada de caucho en compuesto EPDM. Excelente resistencia al agua, vapor, al ozono. Aplicaciones: Uso general para evitar el contacto entre materiales como vidrio-metal, u otros. Características: Compuesto: Etileno Propileno (EPDM)Espesor: 10 mmAncho: 100 mmColor: NegroDureza (Shore A): 15 +/- 5Densidad: 1,45 gr/ccResi | D81: 141367 | E81: Perfiles de goma | F81: Esponjas | H81: https://cruzeirogomas.cl/wp-content/uploads/2025/01/16156442_I342E1050C-3.jpg
... A111: I181EC64T-5 | B111: Empaquetadura Goma 6,4 mm (1/4") x 1 m Ancho Rollo 5 m (China) NR/SBR C/T | C111: Empaquetadura de goma sintética reforzada con tela, ideal para sellado industrial y automotriz con excelente resistencia química y térmica | D111: 122680 | E111: Industrial | F111: Empaquetaduras | H111: https://cruzeirogomas.cl/wp-content/uploads/2025/01/16326407_EMPAQ_CT-1-1.jpg
A112: I183EK32SS-10 | B112: Empaquetadura Goma 3,2mm (1/8") x 1m Ancho x 10m Rollo (Coreana) SBR Sanitario | C112: Empaquetadura de goma importada SBR sanitario blanco grado alimenticio, certificada para uso en industrias de alimentos, bebidas, farmacéuticos y cosméticos | D112: 375156 | E112: Industrial | H112: https://cruzeirogomas.cl/wp-content/uploads/2025/01/16341938_I176EK48AS_EMP_GOMA_KOR__4_8_MMS_316_X_1MT_SBR_SANIT_BLANC_5MPA-1.jpg
A113: I184EC3215-10 | B113: Empaquetadura Goma 3,2 mm (1/8") x 1,5 m Ancho Rollo 10 m (China) NR/SBR S/T | C113: Empaquetadura de goma sintética sin refuerzo textil, ideal para sellado industrial y automotriz con excelente resistencia química y máxima flexibilidad | D113: 128780 | E113: Industrial | F113: Empaquetaduras | H113: https://cruzeirogomas.cl/wp-content/uploads/2025/01/16341951_-1-1.jpg
A114: I181EC96T-5 | B114: Empaquetadura Goma 9.5 mm x 1 m Ancho x 5 m Rollo (China) C/T | C114: Empaquetadura de goma común importada de China fabricada con caucho NR/SBR sin tela, ideal para automoción, industria minera y entornos industriales con alta abrasión que requieren larga vida útil | D114: 181870 | E114: Industrial | F114: Empaquetaduras | H114: https://cruzeirogomas.cl/wp-content/uploads/2025/01/16342305_-1-1.jpg
A115: I181EC32T-10 | B115: Empaquetadura Goma 3,2 mm (1/8") x 1 m Ancho Rollo 10 m (China) NR/SBR C/T | C115: Empaquetadura de goma sintética fabricada en China con compuesto NR/SBR con tela, ideal para sellado industrial con mayor resistencia mecánica y estabilidad dimensional. | D115: 120790 | E115: Industrial | F115: Empaquetaduras | H115: https://cruzeirogomas.cl/wp-content/uploads/2025/01/16342548_-1-1.jpg
A116: I184EC254-5 | B116: Empaquetadura Goma 25,4 mm x 1 m Ancho x 5 m Rollo (China) S/T | C116: Empaquetadura de goma común importada de China fabricada con caucho NR/SBR sin tela, ideal para automoción, industria minera y entornos industriales con alta abrasión que requieren larga vida útil | D116: 335738 | E116: Industrial | F116: Empaquetaduras | H116: https://cruzeirogomas.cl/wp-content/uploads/2025/01/16342644_-1-1.jpg
A117: I184EC79-5 | B117: Empaquetadura Goma 7,9 mm (5/16") x 1 m Ancho x 5 m Rollo (China) S/T | C117: Empaquetadura de goma común importada de China fabricada con caucho NR/SBR sin tela, ideal para automoción, industria minera y entornos industriales con alta abrasión que requieren larga vida útil | D117: 105290 | E117: Industrial | F117: Empaquetaduras | H117: https://cruzeirogomas.cl/wp-content/uploads/2025/01/16342676_-1-1.jpg
A118: I184EC127 | B118: Empaquetadura Goma 12,7 mm (1/2") x 1 m Ancho x 1 m lineal (China) NR/SBR S/T | C118: Empaquetadura de goma sintética de espesor extra grueso fabricada en China con compuesto NR/SBR sin tela, ideal para aplicaciones industriales pesadas que requieren máxima resistencia mecánica | D118: 42236 | E118: Industrial | F118: Empaquetaduras | H118: https://cruzeirogomas.cl/wp-content/uploads/2025/01/16342703_-1-1.jpg
A119: I181EC48T-10 | B119: Empaquetadura Goma 4,76 mm (3/16") x 1 m Ancho Rollo 10 m (China) NR/SBR C/T | C119: Empaquetadura de goma sintética fabricada en China con compuesto NR/SBR con tela, ideal para sellado industrial con mayor resistencia mecánica y estabilidad dimensional | D119: 178500 | E119: Industrial | F119: Empaquetaduras | H119: https://cruzeirogomas.cl/wp-content/uploads/2025/01/16342722_EMPAQ_CT-1-1.jpg
A120: I184EC64-5 | B120: Empaquetadura Goma 6,4 mm (1/4") x 1 m Ancho Rollo 5 m (China) NR/SBR S/T | C120: Empaquetadura de goma sintética de espesor robusto fabricada en China con compuesto NR/SBR sin tela, ideal para sellado industrial pesado y aplicaciones que requieren mayor resistencia mecánica | D120: 95280 | E120: Industrial | F120: Empaquetaduras | H120: https://cruzeirogomas.cl/wp-content/uploads/2025/01/16342818_-1-1.jpg
A121: I184EC32-10 | B121: Empaquetadura Goma 3,2 mm (1/8") x 1 m Ancho Rollo 10 m (China) NR/SBR S/T | C121: Empaquetadura de goma sintética fabricada en China con compuesto NR/SBR sin tela, ideal para sellado industrial y aplicaciones de mediana presión con excelente flexibilidad | D121: 91390 | E121: Industrial | F121: Empaquetaduras | H121: https://cruzeirogomas.cl/wp-content/uploads/2025/01/16342925_-1-1.jpg
A122: I184EC48-10 | B122: Empaquetadura Goma 4,8 mm (3/16") x 1 m Ancho Rollo 10 m (China) NR/SBR S/T | C122: Empaquetadura de goma sintética fabricada en China con compuesto NR/SBR sin tela, ideal para sellado industrial y aplicaciones de mediana presión que requieren resistencia mecánica | D122: 137220 | E122: Industrial | F122: Empaquetaduras | H122: https://cruzeirogomas.cl/wp-content/uploads/2025/01/16342996_-1-1.jpg
A123: I184EC96-5 | B123: Empaquetadura Goma 9,5 mm (3/8") x 1 m Ancho x 5 m Rollo (China) S/T | C123: Empaquetadura de goma común importada de China fabricada con caucho NR/SBR sin tela, ideal para automoción, industria minera y entornos industriales con alta abrasión que requieren larga vida útil | D123: 132000 | E123: Industrial | F123: Empaquetaduras | H123: https://cruzeirogomas.cl/wp-content/uploads/2025/01/16343061_-1-1.jpg
A124: I271PISDI20NE | B124: Piso de Goma Diamantado Negro 3,5 mm Espesor x 2,0 m Ancho x 1 m Lineal | C124: Piso diamantado de goma antideslizante en Caucho Natural/SBR, perfecta para seguridad en pasillos y escaleras. Estabilidad y protección garantizadas. | D124: 22263 | E124: Pisos | F124: Pisos de goma | H124: https://cruzeirogomas.cl/wp-content/uploads/2025/01/16424991_I271PISDIA1NE-1.jpg
... A171: I272PASR2050 | B171: Piso Pastelón Caucho 20 mm x 50 cm x 50 cm Rojo | C171: Baldosa de caucho pastelón antideslizante, ideal para áreas de juegos, gimnasios y espacios deportivos que requieren máxima absorción de impactos y seguridad | D171: 5990 | E171: Pisos | F171: Pastelones | H171: https://cruzeirogomas.cl/wp-content/uploads/2025/01/5.png
A172: I183EK24SS-10 | B172: Empaquetadura Goma 2,4mm (3/32") x 1m Rollo 10m (Corea) SBR Sanitario Blanco | C172: Empaquetadura de goma SBR sanitaria blanca fabricada en Corea, certificada para 5 MPa, con formulación especial para contacto alimentario, ideal para industria alimenticia y farmacéutica | D172: 285114 | E172: Industrial | H172: https://cruzeirogomas.cl/wp-content/uploads/2025/01/19074908_I176EK48AS_EMP_GOMA_KOR__4_8_MMS_316_X_1MT_SBR_SANIT_BLANC_5MPA-1.jpg
A173: I274FELP472 | B173: Piso Felpudo Tipo NOMAD Azul 12 mm Espesor x 400 mm Ancho x 700 mm Largo | C173: Su trama cerrada es ideal para atrapar la suciedad y esconderla en su base mantiene su superficie limpia evitando el arrastre de suciedad al interior del inmueble | D173: 4989 | E173: Pisos | F173: Pisos de PVC | H173: https://cruzeirogomas.cl/wp-content/uploads/2025/01/19110544_I274FELP8122-1-scaled-1.jpg
A174: I274FELP473 | B174: Piso Felpudo Tipo NOMAD Café 12 mm Espesor x 400 mm Ancho x 700 mm Largo | C174: Atrapa y oculta la suciedad en su base, manteniendo la superficie limpia y reduciendo significativamente los costos de mantenimiento de espacios interiores | D174: 4989 | E174: Pisos | F174: Pisos de PVC | H174: https://cruzeirogomas.cl/wp-content/uploads/2025/01/19110550_NOMAD_CONT_S-T_CAFE-1.jpg
A175: I274FELP476 | B175: Piso Felpudo Tipo NOMAD Rojo 12 mm Espesor x 400 mm Ancho x 700 mm Largo | C175: Atrapa y oculta la suciedad en su base, manteniendo la superficie limpia y reduciendo significativamente los costos de mantenimiento de espacios interiores | D175: 4989 | E175: Pisos | F175: Pisos de PVC | H175: https://cruzeirogomas.cl/wp-content/uploads/2025/01/19110578_I274FELP116-1-scaled-1.jpg
A176: I274FELP474 | B176: Piso Felpudo NOMAD Gris 12 mm Espesor x 400 mm Ancho x 700 mm Largo | C176: Atrapa y oculta la suciedad en su base, manteniendo la superficie limpia y reduciendo significativamente los costos de mantenimiento de espacios interiores | D176: 4989 | E176: Pisos | F176: Pisos de PVC | H176: https://cruzeirogomas.cl/wp-content/uploads/2025/01/19110582_I274FELP12184.-1pg-scaled-1.jpg
A177: I274FELP475 | B177: Piso Felpudo Tipo NOMAD Negro 12 mm Espesor x 400 mm Ancho x 700 mm Largo | C177: Atrapa y oculta la suciedad en su base, manteniendo la superficie limpia y reduciendo significativamente los costos de mantenimiento de espacios interiores | D177: 4989 | E177: Pisos | F177: Pisos de PVC | H177: https://cruzeirogomas.cl/wp-content/uploads/2025/01/19110598_I274FELP12185-1-1.jpg
A178: I184EC3215 | B178: Empaquetadura Goma 3,2 mm (1/8") x 1,5 m Ancho x 1 m Lineal (China) NR/SBR S/T | C178: Empaquetadura de goma sintética fabricada en China con compuesto NR/SBR sin tela, en presentación de 1,5 metros, ideal para sellado industrial y aplicaciones de mediana presión con excelente flexibilidad | D178: 15278 | E178: Industrial | F178: Empaquetaduras | H178: https://cruzeirogomas.cl/wp-content/uploads/2025/01/19124091_-1-1.jpg
A179: I184EC24 | B179: Empaquetadura Goma 2,4 mm (3/32") x 1 m Ancho x 1 m Lineal (China) NR/SBR S/T | C179: Empaquetadura de goma sintética fabricada en China con compuesto NR/SBR sin tela, ideal para sellado industrial y aplicaciones ligeras que requieren flexibilidad y adaptabilidad | D179: 8142 | E179: Industrial | F179: Empaquetaduras | H179: https://cruzeirogomas.cl/wp-content/uploads/2025/01/19124216_-1-1.jpg
A180: I184EC48 | B180: Empaquetadura Goma 4,8 mm (3/16") x 1 m Ancho x 1 m Lineal (China) NR/SBR S/T | C180: Empaquetadura de goma sintética fabricada en China con compuesto NR/SBR sin tela, ideal para sellado industrial y aplicaciones de mediana presión que requieren resistencia mecánica | D180: 15487 | E180: Industrial | F180: Empaquetaduras | H180: https://cruzeirogomas.cl/wp-content/uploads/2025/01/19124249_-1-1.jpg
A181: I184EC9615 | B181: Empaquetadura Goma 9,5 mm (3/8") x 1,5 m Ancho x 1 m Lineal (China) S/T | C181: Empaquetadura de goma común importada de China fabricada con caucho NR/SBR sin tela, ideal para automoción, industria minera y entornos industriales con alta abrasión que requieren larga vida útil | D181: 44247 | E181: Industrial | F181: Empaquetaduras | H181: https://cruzeirogomas.cl/wp-content/uploads/2025/01/19124331_-1-1.jpg
A182: I184EC79 | B182: Empaquetadura Goma 7,9 mm (5/16") x 1 m Ancho x 1 m Lineal (China) NR/SBR S/T | C182: Empaquetadura de goma sintética de espesor extra grueso fabricada en China con compuesto NR/SBR sin tela, ideal para aplicaciones industriales pesadas que requieren máxima resistencia mecánica y absorción de irregularidades | D182: 18359 | E182: Industrial | F182: Empaquetaduras | H182: https://cruzeirogomas.cl/wp-content/uploads/2025/01/19124386_-1-1.jpg
A183: I184EC6420 | B183: Empaquetadura Goma 6,4 mm (1/4") x 2 m Ancho x 1 m lineal (China) NR/SBR S/T | C183: Ideal para sellado industrial pesado y aplicaciones de mayor longitud | D183: 39502 | E183: Industrial | F183: Empaquetaduras | H183: https://cruzeirogomas.cl/wp-content/uploads/2025/01/19143197_-1-1.jpg
A184: F228158091 | B184: Grada Estriada Negro Amarillo 5 mm x 300 mm x 1200 mm | C184: Grada estriada fabricada en caucho natural/SBR con diseño bicolor para máxima seguridad en escalones | D184: 22990 | E184: Pisos | F184: Gradas | H184: https://cruzeirogomas.cl/wp-content/uploads/2025/01/23839067_grada_metro_1-1-1-1.png
... A252: I181EC4815T | B252: Empaquetadura Goma 4,8 mm (3/16") x 1,5 m Ancho x 1 m Lineal (China) NR/SBR C/T | C252: Ideal para sellado industrial con mayor resistencia mecánica y estabilidad dimensiona | D252: 25605 | E252: Industrial | F252: Empaquetaduras | H252: https://cruzeirogomas.cl/wp-content/uploads/2025/01/19562878_EMPAQ_CT-1-1.jpg
A253: I183EK32SS | B253: Empaquetadura Goma 3,2 mm (1/8") x 1 m Ancho x 1 m Lineal SBR Sanitario S/T | C253: Empaquetadura de goma importada SBR sanitario blanco grado alimenticio, certificada para uso en industrias de alimentos, bebidas, farmacéuticos y cosméticos | D253: 37515 | E253: Industrial | H253: https://cruzeirogomas.cl/wp-content/uploads/2025/01/19562896_I176EK48AS_EMP_GOMA_KOR__4_8_MMS_316_X_1MT_SBR_SANIT_BLANC_5MPA-1.jpg
A254: I183EK64SS | B254: Empaquetadura Goma 6,4mm (1/4") x 1m x 1m Lineal (Corea) SBR Sanitario Blanco | C254: Empaquetadura de goma SBR sanitaria blanca de espesor robusto fabricada en Corea, certificada para 5 MPa, con formulación especial para contacto alimentario, ideal para industria alimenticia y farmacéutica pesada | D254: 77031 | E254: Industrial | H254: https://cruzeirogomas.cl/wp-content/uploads/2025/01/19562982_I176EK48AS_EMP_GOMA_KOR__4_8_MMS_316_X_1MT_SBR_SANIT_BLANC_5MPA-1.jpg
A255: I307450250100 | B255: Tope de Estacionamiento Industrial Carga Pesada 450 mm x 250 mm x 100 mm | C255: Su construcción robusta con mayor superficie de contacto proporciona estabilidad superior y resistencia extrema a impactos de vehículos pesados, con 2 perforaciones de anclaje para fijación segura en instalaciones logísticas | D255: 34430 | E255: Seguridad Vial | F255: Lomos de toro y rampas | H255: https://cruzeirogomas.cl/wp-content/uploads/2025/01/19598477_muelle_camion-1.jpg
A256: I307595120100 | B256: Tope de Estacionamiento 595 x 120 x 100 mm Amarillo/Negro con 2 Perforaciones | C256: Tope delimitador de plazas de aparcamiento fabricado en material resistente con colores de alta visibilidad, incluye 2 orificios para fijación segura al suelo | D256: 12106 | E256: Seguridad Vial | F256: Estacionamiento | H256: https://cruzeirogomas.cl/wp-content/uploads/2025/01/19598529_I307595120100-1.jpg
A257: I184EC12 | B257: Empaquetadura Goma 1,2 mm (3/64") x 1 m Ancho x 1 m Lineal (China) NR/SBR S/T | C257: Empaquetadura de goma sintética ultra delgada fabricada en China con compuesto NR/SBR sin tela, ideal para aplicaciones de sellado en espacios muy reducidos y tolerancias mínimas | D257: 3640 | E257: Industrial | F257: Empaquetaduras | H257: https://cruzeirogomas.cl/wp-content/uploads/2025/01/19605861_-1-1.jpg
A258: I181EC127T | B258: Empaquetadura Goma 12,7 mm (1/2") x 1 m Ancho x 1 m Lineal (China) NR/SBR C/T | C258: Empaquetadura de goma sintética de espesor extra grueso fabricada en China con compuesto NR/SBR con tela, ideal para aplicaciones industriales pesadas que requieren máxima resistencia mecánica y dimensional | D258: 55930 | E258: Industrial | F258: Empaquetaduras | H258: https://cruzeirogomas.cl/wp-content/uploads/2025/01/19623984_EMPAQ_CT-1-1.jpg
A259: I1553L200 | B259: Correas # 3 L 200 ..( 19 1/2" Int X 10 Mm. ) | C259: CORREA # 3 L 200 ..( 19 1/2" int x 10 mm. )LienzoCorreas de caucho especial resistente al desgaste y extremadamente flexibleElementos de tracciónLos miembros de cordón de poliéster preestirado proporcionan una alta resistencia a la tracción y mínima elongación Goma de adherenciaLos compuestos de adhesión investigados unen los elementos trac | D259: 2020 | E259: Automotriz | F259: Correas | H259: https://cruzeirogomas.cl/wp-content/uploads/2025/01/19627209_3L-1.jpg
A260: I1553L210 | B260: Correas # 3 L 210 ..( 20" Int X 10 Mm. ) | C260: CORREA # 3 L 210 ..( 20" int x 10 mm. )LienzoCorreas de caucho especial resistente al desgaste y extremadamente flexibleElementos de tracciónLos miembros de cordón de poliéster preestirado proporcionan una alta resistencia a la tracción y mínima elongación Goma de adherenciaLos compuestos de adhesión investigados unen los elementos tr | D260: 2020 | E260: Automotriz | F260: Correas | H260: https://cruzeirogomas.cl/wp-content/uploads/2025/01/19627210_3L-1.jpg
A261: I1573V220 | B261: Correas # 3 V 220 ..( 20 1/4" Int (9.5 X 560 Mm) ) | C261: LienzoCorreas de caucho especial resistente al desgaste y extremadamente flexibleElementos de tracciónLos miembros de cordón de poliéster preestirado proporcionan una alta resistencia a la tracción y mínima elongación Goma de adherenciaLos compuestos de adhesión investigados unen los elementos tracción en su posición y las cuerdas a la goma | D261: 2800 | E261: Automotriz | F261: Correas | H261: https://cruzeirogomas.cl/wp-content/uploads/2025/01/19627212_3L-1.jpg
A262: I1553L230 | B262: Correas # 3 L 230 ..( 21 1/2" Int X 10 Mm. ) | C262: CORREAS # 3 L 230 ..( 21 1/2" int x 10 mm. )LienzoCorreas de caucho especial resistente al desgaste y extremadamente flexibleElementos de tracciónLos miembros de cordón de poliéster preestirado proporcionan una alta resistencia a la tracción y mínima elongación Goma de adherenciaLos compuestos de adhesión investigados unen los elementos t | D262: 2020 | E262: Automotriz | F262: Correas | H262: https://cruzeirogomas.cl/wp-content/uploads/2025/01/19627214_3L-1.jpg
A263: I1553L240 | B263: Correas # 3 L 240 ..( 22 1/2" Int X 10 Mm. ) | C263: CORREA # 3 L 240 ..( 22 1/2" int x 10 mm. )LienzoCorreas de caucho especial resistente al desgaste y extremadamente flexibleElementos de tracciónLos miembros de cordón de poliéster preestirado proporcionan una alta resistencia a la tracción y mínima elongación Goma de adherenciaLos compuestos de adhesión investigados unen los elementos trac | D263: 2020 | E263: Automotriz | F263: Correas | H263: https://cruzeirogomas.cl/wp-content/uploads/2025/01/19627216_3L-1.jpg
A264: I1553L250 | B264: Correas # 3 L 250 ..( 23 1/2" Int X 10 Mm. ) | C264: CORREA # 3 L 250 ..( 23 1/2" int x 10 mm. )LienzoCorreas de caucho especial resistente al desgaste y extremadamente flexibleElementos de tracciónLos miembros de cordón de poliéster preestirado proporcionan una alta resistencia a la tracción y mínima elongación Goma de adherenciaLos compuestos de adhesión investigados unen los elementos trac | D264: 2020 | E264: Automotriz | F264: Correas | H264: https://cruzeirogomas.cl/wp-content/uploads/2025/01/19627218_3L-1.jpg
A265: I1553L260 | B265: Correas # 3 L 260 ..( 24 1/2" Int X 10 Mm. ) | C265: CORREA # 3 L 260 ..( 24 1/2" int x 10 mm. )LienzoCorreas de caucho especial resistente al desgaste y extremadamente flexibleElementos de tracciónLos miembros de cordón de poliéster preestirado proporcionan una alta resistencia a la tracción y mínima elongación Goma de adherenciaLos compuestos de adhesión investigados unen los elementos trac | D265: 2020 | E265: Automotriz | F265: Correas | H265: https://cruzeirogomas.cl/wp-content/uploads/2025/01/19627220_3L-1.jpg
A266: I1553L280 | B266: Correas # 3 L 280 ..( 26 3/4" Int X 10 Mm. ) | C266: La correa acanalada en V DRB, con su alta flexibilidad y sección transversal única, es adecuada para transmisiones de alta velocidad y potencia. | D266: 2020 | E266: Automotriz | F266: Correas | H266: https://cruzeirogomas.cl/wp-content/uploads/2025/01/19627222_3L-1.jpg
... A414: I1678PK2470 | B414: Correas 8Pk-2470 Dongil | C414: CORREA 6PK-1355 DONGIL La alta flexibilidad debido a la sección transversal única de la correa permite una larga vida útil y transmisiones compactas. Las correas acanaladas DRB son adecuadas para accionamientos de alta velocidad y transmisiones de alta potencia . La correa acanalada en V se denomina " Correa en V poli" Diseñado para un exc | D414: 21060 | E414: Automotriz | F414: Correas | H414: https://cruzeirogomas.cl/wp-content/uploads/2025/01/20113074_6pk-1.jpg
A415: F227158200 | B415: Ángulo Grada Estriada Negro 5 mm x 70 mm x 2400 mm | C415: Grada en ángulo fabricada en caucho natural/SBR con diseño para máxima seguridad en escalones. | D415: 30030 | E415: Pisos | H415: https://cruzeirogomas.cl/wp-content/uploads/2025/01/22512301_nariz-de-grada-37-x-37-t-12m-negra-1-1.jpg
A416: F227158212 | B416: Ángulo Grada Estriada Gris 5 mm x 50 mm x 2400 mm | C416: Grada en ángulo fabricada en caucho natural con diseño para máxima seguridad en escalones | D416: 31930 | E416: Pisos | H416: https://cruzeirogomas.cl/wp-content/uploads/2025/01/20114409_10-1.jpg
A417: F228158059 | B417: Grada Estriada Negro 5 mm x 300 mm x 1200 mm | C417: Grada antideslizante fabricada en caucho natural con diseño estriado con pestaña para máxima seguridad | D417: 17990 | E417: Pisos | F417: Gradas | H417: https://cruzeirogomas.cl/wp-content/uploads/2025/01/w1004h1500fitpad.webp
A418: F228158369 | B418: Grada Estriada Negro 5 mm x 300 mm x 1500 mm | C418: Grada antideslizante fabricada en caucho natural con diseño estriado y pestaña para máxima seguridad | D418: 12990 | E418: Pisos | F418: Gradas | H418: https://cruzeirogomas.cl/wp-content/uploads/2025/01/shopping-1.webp
A419: F285164005 | B419: Regaton No. 5 Diam 3/4" Para Baston | C419: Regatón No. 5 Diam 3/4" Para Bastón-Fabricado Por Cruzeiro Gomas | D419: 1610 | E419: Perfiles de goma | F419: Perfiles | H419: https://cruzeirogomas.cl/wp-content/uploads/2025/01/20114531_REGATON_REDONDO-1.png
A420: F285164008 | B420: Regaton No. 8 Diam 7/8" | C420: Regatón No. 8 Diam 7/8"-Fabricado Por Cruzeiro Gomas | D420: 1030 | E420: Perfiles de goma | F420: Perfiles | H420: https://cruzeirogomas.cl/wp-content/uploads/2025/01/20114555_REGATON_REDONDO-1.png
A421: F285164020 | B421: Regaton No. 20 Diam 3/8" | C421: Regatón No. 20 Diam 3/8"-Fabricado Por Cruzeiro Gomas | D421: 1680 | E421: Perfiles de goma | F421: Perfiles | H421: https://cruzeirogomas.cl/wp-content/uploads/2025/01/20114557_REGATON_REDONDO-1.png
A422: F285164043 | B422: Regaton No. 43 15 X 15 Mms | C422: Regatón No. 43 15 X 15 Mms-Fabricado Por Cruzeiro Gomas | D422: 830 | E422: Perfiles de goma | F422: Perfiles | H422: https://cruzeirogomas.cl/wp-content/uploads/2025/01/20114560_40_X_40_MNS_REGATON-1.png
A423: I247A150095-25 | B423: Mang. Goma Flexhose Agua/Aire 150Lbs 9,5X16Mm 3/8" Rollo 25 Mts | C423: Manguera caucho para agua y aire con refuerzo textilTubo y cubierta nr/ sbr, cubierta con mediana resistencia a intemperie y abrasión, refuerzo textil trenzadoConducción de agua y aire a presión, uso industrial y automotrizNegro c/raya azulRollo 25 mt | D423: 37030 | E423: Automotriz | F423: Mangueras | H423: https://cruzeirogomas.cl/wp-content/uploads/2025/01/20114597_W-1.jpg
A424: I247A300064-25 | B424: Mang. Goma Flexhose Agua/Aire 300Lbs 6,4X12Mm 1/4" Rollo 25 Mts | C424: Manguera caucho para agua y aire con refuerzo textilTubo y cubierta nr/ sbr, cubierta con mediana resistencia a intemperie y abrasión, refuerzo textil trenzadoConducción de agua y aire a presión, uso industrial y automotrizNegro c/raya azulRollo 25 mt | D424: 24030 | E424: Automotriz | F424: Mangueras | H424: https://cruzeirogomas.cl/wp-content/uploads/2025/01/20114620_1-1.png
A425: I1677PK0990 | B425: Correas 7Pk-0990 Dongil | C425: CORREA 6PK-1355 DONGIL La alta flexibilidad debido a la sección transversal única de la correa permite una larga vida útil y transmisiones compactas. Las correas acanaladas DRB son adecuadas para accionamientos de alta velocidad y transmisiones de alta potencia . La correa acanalada en V se denomina " Correa en V poli" Diseñado para un exc | D425: 7620 | E425: Automotriz | F425: Correas | H425: https://cruzeirogomas.cl/wp-content/uploads/2025/01/20114696_6pk-1.jpg
A426: I1677PK1015 | B426: Correas 7Pk-1015 Dongil | C426: CORREA 6PK-1355 DONGIL La alta flexibilidad debido a la sección transversal única de la correa permite una larga vida útil y transmisiones compactas. Las correas acanaladas DRB son adecuadas para accionamientos de alta velocidad y transmisiones de alta potencia . La correa acanalada en V se denomina " Correa en V poli" Diseñado para un exc | D426: 7770 | E426: Automotriz | F426: Correas | H426: https://cruzeirogomas.cl/wp-content/uploads/2025/01/20114698_6pk-1.jpg
A427: I1677PK1040 | B427: Correas 7Pk-1040 Dongil | C427: CORREA 6PK-1355 DONGIL La alta flexibilidad debido a la sección transversal única de la correa permite una larga vida útil y transmisiones compactas. Las correas acanaladas DRB son adecuadas para accionamientos de alta velocidad y transmisiones de alta potencia . La correa acanalada en V se denomina " Correa en V poli" Diseñado para un exc | D427: 7930 | E427: Automotriz | F427: Correas | H427: https://cruzeirogomas.cl/wp-content/uploads/2025/01/20114700_6pk-1.jpg
A428: I1677PK1055 | B428: Correas 7Pk-1055 Dongil | C428: CORREA 6PK-1355 DONGIL La alta flexibilidad debido a la sección transversal única de la correa permite una larga vida útil y transmisiones compactas. Las correas acanaladas DRB son adecuadas para accionamientos de alta velocidad y transmisiones de alta potencia . La correa acanalada en V se denomina " Correa en V poli" Diseñado para un exc | D428: 8040 | E428: Automotriz | F428: Correas | H428: https://cruzeirogomas.cl/wp-content/uploads/2025/01/20114716_6pk-1.jpg
... A557: I275PASINT25-5 | B557: Pasto Sintético Rollo Ornamental Jardín Verde/Café 25 mm Espesor x 2 m Ancho x 5 m | C557: Pasto sintético de alta calidad con fibras resistentes a rayos UV en tonos verdes y cafés que imita el aspecto natural | D557: 132890 | E557: Pisos | F557: Pasto sintético | H557: https://cruzeirogomas.cl/wp-content/uploads/2025/01/20356639_I275PASINT25-2-1.jpg
A558: P197AL15205 | B558: Esponja Autoadhesiva Pvc 15X20 Mmsx5Mts Negro | C558: DescripciónScapa 3259 espuma de media densidad y celdas cerradas recubiertas por un lado con adhesivo acrílico sensible a la presión. Aplicaciones– En tabiques: ayuda a reducir la transmisión del sonido y compensa superficies irregulares.– Techumbres y revestimiento: entrega un eficiente sello al agua, aire y polvo al ser usado entre marcos de las | D558: 16270 | E558: Perfiles de goma | H558: https://cruzeirogomas.cl/wp-content/uploads/2025/01/20468342_2-1.jpg
A559: P197AL3012N | B559: Esponja Autoadhesiva Pvc 3X12 Mmsx25Mts Neg Rollo | C559: DescripciónScapa 3259 espuma de media densidad y celdas cerradas recubiertas por un lado con adhesivo acrílico sensible a la presión. Aplicaciones– En tabiques: ayuda a reducir la transmisión del sonido y compensa superficies irregulares.– Techumbres y revestimiento: entrega un eficiente sello al agua, aire y polvo al ser usado entre marcos de las | D559: 13190 | E559: Perfiles de goma | H559: https://cruzeirogomas.cl/wp-content/uploads/2025/01/20468351_espoja_negra-1.png
A560: P197AL3019N | B560: Esponja Autoadhesiva Pvc 3X19 Mmsx25Mts Neg Rollo | C560: DescripciónScapa 3259 espuma de media densidad y celdas cerradas recubiertas por un lado con adhesivo acrílico sensible a la presión. Aplicaciones– En tabiques: ayuda a reducir la transmisión del sonido y compensa superficies irregulares.– Techumbres y revestimiento: entrega un eficiente sello al agua, aire y polvo al ser usado entre marcos de las | D560: 22720 | E560: Perfiles de goma | H560: https://cruzeirogomas.cl/wp-content/uploads/2025/01/20468370_2-1.jpg
A561: P197AL3025N | B561: Esponja Autoadhesiva Pvc 3X25 Mmsx25Mts Neg Rollo | C561: Esponja Autoadhesiva Pvc de media densidad y celdas cerradas recubiertas por un lado con adhesivo acrílico sensible a la presión. Aplicaciones– En tabiques: ayuda a reducir la transmisión del sonido y compensa superficies irregulares.– Techumbres y revestimiento: entrega un eficiente sello al agua, aire y polvo al ser usado entre marcos de las | D561: 35490 | E561: Perfiles de goma | H561: https://cruzeirogomas.cl/wp-content/uploads/2025/01/20468392_2-1.jpg
A562: P197AL4519N | B562: Esponja Autoadhesiva Pvc 4,5X19 Mmsx15Mts Neg Rollo | C562: DescripciónScapa 3259 espuma de media densidad y celdas cerradas recubiertas por un lado con adhesivo acrílico sensible a la presión. Aplicaciones– En tabiques: ayuda a reducir la transmisión del sonido y compensa superficies irregulares.– Techumbres y revestimiento: entrega un eficiente sello al agua, aire y polvo al ser usado entre marcos de las | D562: 22600 | E562: Perfiles de goma | H562: https://cruzeirogomas.cl/wp-content/uploads/2025/01/20468415_2-1.jpg
A563: P197AL4525N | B563: Esponja Autoadhesiva Pvc 4,5X25 Mmsx15Mts Neg Rollo | C563: DescripciónScapa 3259 espuma de media densidad y celdas cerradas recubiertas por un lado con adhesivo acrílico sensible a la presión. Aplicaciones– En tabiques: ayuda a reducir la transmisión del sonido y compensa superficies irregulares.– Techumbres y revestimiento: entrega un eficiente sello al agua, aire y polvo al ser usado entre marcos de las | D563: 24040 | E563: Perfiles de goma | H563: https://cruzeirogomas.cl/wp-content/uploads/2025/01/20468434_2-1.jpg
A564: P197AL6012N | B564: Esponja Autoadhesiva Pvc 6X12 Mmsx12Mts Neg Rollo | C564: DescripciónScapa 3259 espuma de media densidad y celdas cerradas recubiertas por un lado con adhesivo acrílico sensible a la presión. Aplicaciones– En tabiques: ayuda a reducir la transmisión del sonido y compensa superficies irregulares.– Techumbres y revestimiento: entrega un eficiente sello al agua, aire y polvo al ser usado entre marcos de las | D564: 11620 | E564: Perfiles de goma | H564: https://cruzeirogomas.cl/wp-content/uploads/2025/01/20468447_2-1.jpg
A565: P197AL6019N | B565: Esponja Autoadhesiva Pvc 6X19 Mmsx12Mts Neg Rollo | C565: DescripciónScapa 3259 espuma de media densidad y celdas cerradas recubiertas por un lado con adhesivo acrílico sensible a la presión. Aplicaciones– En tabiques: ayuda a reducir la transmisión del sonido y compensa superficies irregulares.– Techumbres y revestimiento: entrega un eficiente sello al agua, aire y polvo al ser usado entre marcos de las | D565: 18420 | E565: Perfiles de goma | H565: https://cruzeirogomas.cl/wp-content/uploads/2025/01/20468462_2-1.jpg
A566: P197AL6038N | B566: Esponja Autoadhesiva Pvc 6X38 Mmsx12Mts Neg Rollo | C566: DescripciónScapa 3259 espuma de media densidad y celdas cerradas recubiertas por un lado con adhesivo acrílico sensible a la presión. Aplicaciones– En tabiques: ayuda a reducir la transmisión del sonido y compensa superficies irregulares.– Techumbres y revestimiento: entrega un eficiente sello al agua, aire y polvo al ser usado entre marcos de las | D566: 35850 | E566: Perfiles de goma | H566: https://cruzeirogomas.cl/wp-content/uploads/2025/01/20468476_2-1.jpg
A567: P197AL935025 | B567: Esponja Autoadhesiva Pvc 3X50 Mmsx25Mts Neg Rollo | C567: DescripciónScapa 3259 espuma de media densidad y celdas cerradas recubiertas por un lado con adhesivo acrílico sensible a la presión. Aplicaciones– En tabiques: ayuda a reducir la transmisión del sonido y compensa superficies irregulares.– Techumbres y revestimiento: entrega un eficiente sello al agua, aire y polvo al ser usado entre marcos de las | D567: 61020 | E567: Perfiles de goma | H567: https://cruzeirogomas.cl/wp-content/uploads/2025/01/20468493_2-1.jpg
A568: P197AL3012G | B568: Esponja Autoadhesiva Pvc 3X12 Mmsx25Mts Gris Rollo | C568: DescripciónScapa 3259 espuma de media densidad y celdas cerradas recubiertas por un lado con adhesivo acrílico sensible a la presión. Aplicaciones– En tabiques: ayuda a reducir la transmisión del sonido y compensa superficies irregulares.– Techumbres y revestimiento: entrega un eficiente sello al agua, aire y polvo al ser usado entre marcos de las | D568: 13030 | E568: Perfiles de goma | H568: https://cruzeirogomas.cl/wp-content/uploads/2025/01/20468590_3-1.jpg
A569: P197AL3019G | B569: Esponja Autoadhesiva Pvc 3X19 Mmsx25Mts Gris Rollo | C569: DescripciónScapa 3259 espuma de media densidad y celdas cerradas recubiertas por un lado con adhesivo acrílico sensible a la presión. Aplicaciones– En tabiques: ayuda a reducir la transmisión del sonido y compensa superficies irregulares.– Techumbres y revestimiento: entrega un eficiente sello al agua, aire y polvo al ser usado entre marcos de las | D569: 22720 | E569: Perfiles de goma | H569: https://cruzeirogomas.cl/wp-content/uploads/2025/01/20468652_3-1.jpg
... A575: P197AL6038G | B575: Esponja Autoadhesiva Pvc 6X38 Mmsx12Mts Gris Rollo | C575: DescripciónScapa 3259 espuma de media densidad y celdas cerradas recubiertas por un lado con adhesivo acrílico sensible a la presión. Aplicaciones– En tabiques: ayuda a reducir la transmisión del sonido y compensa superficies irregulares.– Techumbres y revestimiento: entrega un eficiente sello al agua, aire y polvo al ser usado entre marcos de las | D575: 35850 | E575: Perfiles de goma | H575: https://cruzeirogomas.cl/wp-content/uploads/2025/01/20468747_3-1.jpg
